Workbook
Name AR_Customers: 'Analysis'!$V$170:$V$177
Name AR_Sales: 'Analysis'!$W$170:$W$176

Sheet Dashboard
B1: ACCOUNTS RECEIVABLE DASHBOARD | N1: Client Filter | P1: All | AA1: =IF(Analysis!D7=0,AD1,"") | AB1: =IF(Analysis!D7>0,AD1,"") | AC1: =IF(Analysis!D7<0,AD1,"") -> -0.05B (-0.8%) | AD1: =TEXT(Analysis!D7/1000000000,"+0.00;-0.00;0.00")&"B ("&TEXT(Analysis!E7,"+0.0%;-0.0%;0.0%")&")" -> -0.05B (-0.8%) | AE1: ="Current: "&TEXT(Analysis!B7/1000000000,"0.00")&"B VND" -> Current: 5.78B VND | AF1: ="Prior: "&TEXT(Analysis!C7/1000000000,"0.00")&"B VND" -> Prior: 5.83B VND | AG1: Overdue Ratio (1–60 Days) | AH1: =TEXT(Analysis!B16,"0.0%") -> 11.3%
B2: Report Date: | D2: 46300 | N2: Sales Rep Filter | P2: All | AA2: =IF(Analysis!D8=0,AD2,"") | AB2: =IF(Analysis!D8>0,AD2,"") | AC2: =IF(Analysis!D8<0,AD2,"") -> -0.08B (-1.9%) | AD2: =TEXT(Analysis!D8/1000000000,"+0.00;-0.00;0.00")&"B ("&TEXT(Analysis!E8,"+0.0%;-0.0%;0.0%")&")" -> -0.08B (-1.9%) | AE2: ="Current: "&TEXT(Analysis!B8/1000000000,"0.00")&"B VND" -> Current: 4.02B VND | AF2: ="Prior: "&TEXT(Analysis!C8/1000000000,"0.00")&"B VND" -> Prior: 4.10B VND | AG2: Receivables Ratio (>60 Days) | AH2: =TEXT(Analysis!B17,"0.0%") -> 7.9%
B3: Current and prior invoice records. Public demonstration workbook. | N3: Status Filter | P3: All | AA3: =IF(Analysis!D9=0,AD3,"") | AB3: =IF(Analysis!D9>0,AD3,"") | AC3: =IF(Analysis!D9<0,AD3,"") -> -0.13B (-1.3%) | AD3: =TEXT(Analysis!D9/1000000000,"+0.00;-0.00;0.00")&"B ("&TEXT(Analysis!E9,"+0.0%;-0.0%;0.0%")&")" -> -0.13B (-1.3%) | AE3: ="Current: "&TEXT(Analysis!B9/1000000000,"0.00")&"B VND" -> Current: 9.80B VND | AF3: ="Prior: "&TEXT(Analysis!C9/1000000000,"0.00")&"B VND" -> Prior: 9.93B VND | AG3: Total Overdue Ratio | AH3: =TEXT(Analysis!B18,"0.0%") -> 19.2%
B6: Total Outstanding AR | E6: Avg Overdue Days | G6: >60d / Total Overdue | I6: Top Client Share | K6: Top 3 Clients Share | N6: Due in Next 10 Days | Z6: ='Analysis'!D6 -> 1.7123355e+10
B7: =TEXT(Analysis!B6/1000000000,"0.00")&"B VND" -> 51.06B VND | E7: =TEXT(Analysis!B56,"0.0")&" Days" -> 39.5 Days | G7: =TEXT(Analysis!B57,"0.0%") -> 41.0% | I7: =TEXT(Analysis!B58,"0.0%") -> 76.5% | K7: =TEXT(Analysis!B59,"0.0%") -> 91.5% | N7: =TEXT(Analysis!B11/1000000000,"0.00")&"B VND" -> 3.81B VND
B9: ="Prior: "&TEXT(Analysis!C6/1000000000,"0.00")&"B VND" -> Prior: 33.93B VND | E9: ="Prior: "&TEXT(Analysis!C56,"0.0")&" Days" -> Prior: 40.0 Days | G9: ="Prior: "&TEXT(Analysis!C57,"0.0%") -> Prior: 41.3% | I9: ="Prior: "&TEXT(Analysis!C58,"0.0%") -> Prior: 69.9% | K9: ="Prior: "&TEXT(Analysis!C59,"0.0%") -> Prior: 95.3% | N9: ="Prior: "&TEXT(Analysis!C11/1000000000,"0.00")&"B VND" -> Prior: 3.35B VND
B10: =TEXT('Analysis'!D6/1000000000,"+0.00;-0.00;0.00")&"B ("&TEXT('Analysis'!E6,"+0.0%;-0.0%;0.0%")&")" -> +17.12B (+50.5%) | E10: =TEXT('Analysis'!D56,"+0.0;-0.0;0.0")&" Days ("&TEXT('Analysis'!E56,"+0.0%;-0.0%;0.0%")&")" -> -0.5 Days (-1.3%) | G10: =TEXT('Analysis'!D57*100,"+0.0;-0.0;0.0")&" pp" -> -0.3 pp | I10: =TEXT('Analysis'!D58*100,"+0.0;-0.0;0.0")&" pp" -> +6.6 pp | K10: =TEXT('Analysis'!D59*100,"+0.0;-0.0;0.0")&" pp" -> -3.7 pp | N10: =TEXT('Analysis'!D11/1000000000,"+0.00;-0.00;0.00")&"B ("&TEXT('Analysis'!E11,"+0.0%;-0.0%;0.0%")&")" -> +0.47B (+13.9%)
Z11: ='Analysis'!D11 -> 4.6513087e+08
B12: Overdue Ratio (1–60 Days) | G12: Receivables Ratio (>60 Days) | K12: Total Overdue Ratio
B21: =TEXT('Analysis'!B16,"0.0%") -> 11.3% | G21: =TEXT('Analysis'!B17,"0.0%") -> 7.9% | K21: =TEXT('Analysis'!B18,"0.0%") -> 19.2%
B22: ="Current: "&TEXT('Analysis'!B7/1000000000,"0.00")&" B VND" -> Current: 5.52B VND | G22: ="Current: "&TEXT('Analysis'!B8/1000000000,"0.00")&" B VND" -> Current: 3.84B VND | K22: ="Current: "&TEXT('Analysis'!B9/1000000000,"0.00")&" B VND" -> Current: 9.36B VND
B27: Customer/staff filters apply to the overview. Status also filters the charts and collection list.
B28: 98 current invoices. All customer and staff groups reconcile to the current ledger total.
Z56: ='Analysis'!D56 -> -0.52699735
Z57: ='Analysis'!D57 -> -0.0026233793
Z58: ='Analysis'!D58 -> 0.065755063
Z59: ='Analysis'!D59 -> -0.037499327
B69: Client Account | D69: Current Balance | F69: Prior Balance | G69: In-Term Debt | H69: Overdue Debt | J69: Sales Representative | K69: Current Balance | L69: Prior Balance | N69: In-Term Debt | P69: Overdue Debt
B70: Client Beta (Heavy Const.) | D70: ='Analysis'!B170 -> 2.000343e+09 | F70: ='Analysis'!C170 -> 1.6031727e+09 | G70: ='Analysis'!D170 -> 4.50339e+08 | H70: ='Analysis'!E170 -> 1.550004e+09 | J70: Senior Sales Rep 1 | K70: ='Analysis'!H170 -> 1.4614668e+10 | L70: ='Analysis'!I170 -> 1.4415883e+10 | N70: ='Analysis'!J170 -> 1.0509252e+10 | P70: ='Analysis'!K170 -> 4.105416e+09
B71: Client Delta (Commercial Facade) | D71: ='Analysis'!B171 -> 2.283114e+09 | F71: ='Analysis'!C171 -> 0 | G71: ='Analysis'!D171 -> 2.283114e+09 | H71: ='Analysis'!E171 -> 0 | J71: Senior Sales Rep 2 | K71: ='Analysis'!H171 -> 3.0092673e+10 | L71: ='Analysis'!I171 -> 1.5416999e+10 | N71: ='Analysis'!J171 -> 2.8416993e+10 | P71: ='Analysis'!K171 -> 1.67568e+09
B72: Client Alpha (Steel EPC) | D72: ='Analysis'!B172 -> 3.9053817e+10 | F72: ='Analysis'!C172 -> 2.3724533e+10 | G72: ='Analysis'!D172 -> 3.6498405e+10 | H72: ='Analysis'!E172 -> 2.555412e+09 | J72: Sales Rep 6 | K72: ='Analysis'!H172 -> 0 | L72: ='Analysis'!I172 -> 0 | N72: ='Analysis'!J172 -> 0 | P72: ='Analysis'!K172 -> 0
B73: Client Alpha Sub-Contract | D73: ='Analysis'!B173 -> 3.6531814e+09 | F73: ='Analysis'!C173 -> 4.5051769e+09 | G73: ='Analysis'!D173 -> 1.9775014e+09 | H73: ='Analysis'!E173 -> 1.67568e+09 | J73: Sales Rep 4 | K73: ='Analysis'!H173 -> 43462950 | L73: ='Analysis'!I173 -> 0 | N73: ='Analysis'!J173 -> 43462950 | P73: ='Analysis'!K173 -> 0
B74: Client Epsilon (Equipment) | D74: ='Analysis'!B174 -> 43462950 | F74: ='Analysis'!C174 -> 0 | G74: ='Analysis'!D174 -> 43462950 | H74: ='Analysis'!E174 -> 0 | J74: Sales Rep 5 | K74: ='Analysis'!H174 -> 324663 | L74: ='Analysis'!I174 -> 333943.13 | N74: ='Analysis'!J174 -> 324663 | P74: ='Analysis'!K174 -> 0
B75: Client Zeta (Building Tech) | D75: ='Analysis'!B175 -> 324663 | F75: ='Analysis'!C175 -> 333943.13 | G75: ='Analysis'!D175 -> 324663 | H75: ='Analysis'!E175 -> 0 | J75: Sales Rep 3 | K75: ='Analysis'!H175 -> 4.021632e+09 | L75: ='Analysis'!I175 -> 4.0993038e+09 | N75: ='Analysis'!J175 -> 0 | P75: ='Analysis'!K175 -> 4.021632e+09
B76: Client Gamma (Offshore Energy) | D76: ='Analysis'!B176 -> 4.021632e+09 | F76: ='Analysis'!C176 -> 4.0993038e+09 | G76: ='Analysis'!D176 -> 0 | H76: ='Analysis'!E176 -> 4.021632e+09

Sheet Current AR
A1: Current-period invoice ledger. Names, identifiers and financial amounts have been changed for publication.
D3: 46300
A5: Customer | B5: Legal Name | C5: Document Number | D5: Invoice Number | E5: Invoice Date | F5: Due Date | G5: Invoice Gross Amount | H5: Receipts Applied | I5: Outstanding Balance | J5: Sales Representative | K5: Business Type | L5: Project | M5: Description | N5: Promised Payment Date | O5: Last Contact | P5: Next Action | Q5: Days Overdue | R5: Customer / Staff Match | S5: Selected Balance | T5: Selected Overdue | U5: Status Match | V5: Filtered Balance | W5: Overdue Days × Balance | Y5: Stable Document Key
A6: Client Beta (Heavy Const.) | B6: CLIENT BETA HEAVY INDUSTRIAL CONSTRUCTION CORP | C6: AR-00001 | D6: 70000001 | E6: 46262 | F6: 46292 | G6: 75501400 | H6: 0 | I6: 75501400 | J6: Senior Sales Rep 1 | K6: Trading | L6: Project 002 | M6: Collection note 001 | Q6: =IF(ISNUMBER(F6),Dashboard!$D$2-F6,"") -> 8 | R6: =IF(AND(OR(Dashboard!$P$1="All",A6=Dashboard!$P$1),OR(Dashboard!$P$2="All",J6=Dashboard!$P$2)),1,0) -> 1 | S6: =I6*R6 -> 75501400 | T6: =IF(AND(ISNUMBER(Q6),Q6>0),S6,0) -> 75501400 | U6: =IF(OR(Dashboard!$P$3="All",AND(Dashboard!$P$3="Not due",Q6<0),AND(Dashboard!$P$3="Due in 10 days",Q6>=-10,Q6<=0),AND(Dashboard!$P$3="Due in 30 days",Q6>=-30,Q6<=0),AND(Dashboard!$P$3="Overdue 1–60 days",Q6>0,Q6<=60),AND(Dashboard!$P$3="Over 60 days",Q6>60),AND(Dashboard!$P$3="All overdue",Q6>0)),1,0) -> 1 | V6: =S6*U6 -> 75501400 | W6: =IF(Q6>0,T6*Q6,0) -> 604011200 | X6: =IF(V6>0,COUNTIF($V$6:V6,">0"),"") -> 1 | Y6: =C6&"|"&D6 -> AR-00001|70000001 | AA6: ["Demo Company 265", "AR-00001", "70000001", "2026-08-28"]
A7: Client Beta (Heavy Const.) | B7: CLIENT BETA HEAVY INDUSTRIAL CONSTRUCTION CORP | C7: AR-00002 | D7: 70000002 | E7: 46262 | F7: 46292 | G7: 920560752 | H7: 0 | I7: 920560752 | J7: Senior Sales Rep 1 | K7: Trading | L7: Project 003 | M7: Collection note 001 | Q7: =IF(ISNUMBER(F7),Dashboard!$D$2-F7,"") -> 8 | R7: =IF(AND(OR(Dashboard!$P$1="All",A7=Dashboard!$P$1),OR(Dashboard!$P$2="All",J7=Dashboard!$P$2)),1,0) -> 1 | S7: =I7*R7 -> 920560752 | T7: =IF(AND(ISNUMBER(Q7),Q7>0),S7,0) -> 920560752 | U7: =IF(OR(Dashboard!$P$3="All",AND(Dashboard!$P$3="Not due",Q7<0),AND(Dashboard!$P$3="Due in 10 days",Q7>=-10,Q7<=0),AND(Dashboard!$P$3="Due in 30 days",Q7>=-30,Q7<=0),AND(Dashboard!$P$3="Overdue 1–60 days",Q7>0,Q7<=60),AND(Dashboard!$P$3="Over 60 days",Q7>60),AND(Dashboard!$P$3="All overdue",Q7>0)),1,0) -> 1 | V7: =S7*U7 -> 920560752 | W7: =IF(Q7>0,T7*Q7,0) -> 7364486016 | X7: =IF(V7>0,COUNTIF($V$6:V7,">0"),"") -> 2 | Y7: =C7&"|"&D7 -> AR-00002|70000002 | AA7: ["Demo Company 265", "AR-00002", "70000002", "2026-08-28"]
A8: Client Beta (Heavy Const.) | B8: CLIENT BETA HEAVY INDUSTRIAL CONSTRUCTION CORP | C8: AR-00003 | D8: 70000003 | E8: 46262 | F8: 46292 | G8: 553941849 | H8: 0 | I8: 553941849 | J8: Senior Sales Rep 1 | K8: Trading | L8: Project 004 | M8: Collection note 001 | Q8: =IF(ISNUMBER(F8),Dashboard!$D$2-F8,"") -> 8 | R8: =IF(AND(OR(Dashboard!$P$1="All",A8=Dashboard!$P$1),OR(Dashboard!$P$2="All",J8=Dashboard!$P$2)),1,0) -> 1 | S8: =I8*R8 -> 553941849 | T8: =IF(AND(ISNUMBER(Q8),Q8>0),S8,0) -> 553941849 | U8: =IF(OR(Dashboard!$P$3="All",AND(Dashboard!$P$3="Not due",Q8<0),AND(Dashboard!$P$3="Due in 10 days",Q8>=-10,Q8<=0),AND(Dashboard!$P$3="Due in 30 days",Q8>=-30,Q8<=0),AND(Dashboard!$P$3="Overdue 1–60 days",Q8>0,Q8<=60),AND(Dashboard!$P$3="Over 60 days",Q8>60),AND(Dashboard!$P$3="All overdue",Q8>0)),1,0) -> 1 | V8: =S8*U8 -> 553941849 | W8: =IF(Q8>0,T8*Q8,0) -> 4431534792 | X8: =IF(V8>0,COUNTIF($V$6:V8,">0"),"") -> 3 | Y8: =C8&"|"&D8 -> AR-00003|70000003 | AA8: ["Demo Company 265", "AR-00003", "70000003", "2026-08-28"]
A9: Client Beta (Heavy Const.) | B9: CLIENT BETA HEAVY INDUSTRIAL CONSTRUCTION CORP | C9: AR-00004 | D9: 70000004 | E9: 46294 | F9: 46324 | G9: 450339000 | H9: 0 | I9: 450339000 | J9: Senior Sales Rep 1 | K9: Trading | L9: Project 005 | M9: Collection note 001 | Q9: =IF(ISNUMBER(F9),Dashboard!$D$2-F9,"") -> -24 | R9: =IF(AND(OR(Dashboard!$P$1="All",A9=Dashboard!$P$1),OR(Dashboard!$P$2="All",J9=Dashboard!$P$2)),1,0) -> 1 | S9: =I9*R9 -> 450339000 | T9: =IF(AND(ISNUMBER(Q9),Q9>0),S9,0) -> 0 | U9: =IF(OR(Dashboard!$P$3="All",AND(Dashboard!$P$3="Not due",Q9<0),AND(Dashboard!$P$3="Due in 10 days",Q9>=-10,Q9<=0),AND(Dashboard!$P$3="Due in 30 days",Q9>=-30,Q9<=0),AND(Dashboard!$P$3="Overdue 1–60 days",Q9>0,Q9<=60),AND(Dashboard!$P$3="Over 60 days",Q9>60),AND(Dashboard!$P$3="All overdue",Q9>0)),1,0) -> 1 | V9: =S9*U9 -> 450339000 | W9: =IF(Q9>0,T9*Q9,0) -> 0 | X9: =IF(V9>0,COUNTIF($V$6:V9,">0"),"") -> 4 | Y9: =C9&"|"&D9 -> AR-00004|70000004 | AA9: ["Demo Company 265", "AR-00004", "70000004", "2026-09-29"]
A10: Client Delta (Commercial Facade) | B10: CLIENT DELTA COMMERCIAL FACADES LTD | C10: AR-00005 | D10: 70000005 | E10: 46289 | F10: 46349 | G10: 1821258559 | H10: 0 | I10: 1821258559 | J10: Sales Rep 6 | K10: Trading | M10: Collection note 002 | Q10: =IF(ISNUMBER(F10),Dashboard!$D$2-F10,"") -> -49 | R10: =IF(AND(OR(Dashboard!$P$1="All",A10=Dashboard!$P$1),OR(Dashboard!$P$2="All",J10=Dashboard!$P$2)),1,0) -> 1 | S10: =I10*R10 -> 1821258559 | T10: =IF(AND(ISNUMBER(Q10),Q10>0),S10,0) -> 0 | U10: =IF(OR(Dashboard!$P$3="All",AND(Dashboard!$P$3="Not due",Q10<0),AND(Dashboard!$P$3="Due in 10 days",Q10>=-10,Q10<=0),AND(Dashboard!$P$3="Due in 30 days",Q10>=-30,Q10<=0),AND(Dashboard!$P$3="Overdue 1–60 days",Q10>0,Q10<=60),AND(Dashboard!$P$3="Over 60 days",Q10>60),AND(Dashboard!$P$3="All overdue",Q10>0)),1,0) -> 1 | V10: =S10*U10 -> 1821258559 | W10: =IF(Q10>0,T10*Q10,0) -> 0 | X10: =IF(V10>0,COUNTIF($V$6:V10,">0"),"") -> 5 | Y10: =C10&"|"&D10 -> AR-00005|70000005 | AA10: ["Demo Company 045", "AR-00005", "70000005", "2026-09-24"]
A11: Client Delta (Commercial Facade) | B11: CLIENT DELTA COMMERCIAL FACADES LTD | C11: AR-00006 | D11: 70000006 | E11: 46294 | F11: 46354 | G11: 149214834 | H11: 0 | I11: 149214834 | J11: Sales Rep 6 | K11: Trading | M11: Collection note 003 | Q11: =IF(ISNUMBER(F11),Dashboard!$D$2-F11,"") -> -54 | R11: =IF(AND(OR(Dashboard!$P$1="All",A11=Dashboard!$P$1),OR(Dashboard!$P$2="All",J11=Dashboard!$P$2)),1,0) -> 1 | S11: =I11*R11 -> 149214834 | T11: =IF(AND(ISNUMBER(Q11),Q11>0),S11,0) -> 0 | U11: =IF(OR(Dashboard!$P$3="All",AND(Dashboard!$P$3="Not due",Q11<0),AND(Dashboard!$P$3="Due in 10 days",Q11>=-10,Q11<=0),AND(Dashboard!$P$3="Due in 30 days",Q11>=-30,Q11<=0),AND(Dashboard!$P$3="Overdue 1–60 days",Q11>0,Q11<=60),AND(Dashboard!$P$3="Over 60 days",Q11>60),AND(Dashboard!$P$3="All overdue",Q11>0)),1,0) -> 1 | V11: =S11*U11 -> 149214834 | W11: =IF(Q11>0,T11*Q11,0) -> 0 | X11: =IF(V11>0,COUNTIF($V$6:V11,">0"),"") -> 6 | Y11: =C11&"|"&D11 -> AR-00006|70000006 | AA11: ["Demo Company 045", "AR-00006", "70000006", "2026-09-29"]
A12: Client Delta (Commercial Facade) | B12: CLIENT DELTA COMMERCIAL FACADES LTD | C12: AR-00007 | D12: 70000007 | E12: 46294 | F12: 46354 | G12: 28421874 | H12: 0 | I12: 28421874 | J12: Sales Rep 6 | K12: Trading | M12: Collection note 003 | Q12: =IF(ISNUMBER(F12),Dashboard!$D$2-F12,"") -> -54 | R12: =IF(AND(OR(Dashboard!$P$1="All",A12=Dashboard!$P$1),OR(Dashboard!$P$2="All",J12=Dashboard!$P$2)),1,0) -> 1 | S12: =I12*R12 -> 28421874 | T12: =IF(AND(ISNUMBER(Q12),Q12>0),S12,0) -> 0 | U12: =IF(OR(Dashboard!$P$3="All",AND(Dashboard!$P$3="Not due",Q12<0),AND(Dashboard!$P$3="Due in 10 days",Q12>=-10,Q12<=0),AND(Dashboard!$P$3="Due in 30 days",Q12>=-30,Q12<=0),AND(Dashboard!$P$3="Overdue 1–60 days",Q12>0,Q12<=60),AND(Dashboard!$P$3="Over 60 days",Q12>60),AND(Dashboard!$P$3="All overdue",Q12>0)),1,0) -> 1 | V12: =S12*U12 -> 28421874 | W12: =IF(Q12>0,T12*Q12,0) -> 0 | X12: =IF(V12>0,COUNTIF($V$6:V12,">0"),"") -> 7 | Y12: =C12&"|"&D12 -> AR-00007|70000007 | AA12: ["Demo Company 045", "AR-00007", "70000007", "2026-09-29"]
A13: Client Delta (Commercial Facade) | B13: CLIENT DELTA COMMERCIAL FACADES LTD | C13: AR-00008 | D13: 70000008 | E13: 46298 | F13: 46358 | G13: 284218732 | H13: 0 | I13: 284218732 | J13: Sales Rep 6 | K13: Trading | L13: Project 002 | M13: Collection note 004 | Q13: =IF(ISNUMBER(F13),Dashboard!$D$2-F13,"") -> -58 | R13: =IF(AND(OR(Dashboard!$P$1="All",A13=Dashboard!$P$1),OR(Dashboard!$P$2="All",J13=Dashboard!$P$2)),1,0) -> 1 | S13: =I13*R13 -> 284218732 | T13: =IF(AND(ISNUMBER(Q13),Q13>0),S13,0) -> 0 | U13: =IF(OR(Dashboard!$P$3="All",AND(Dashboard!$P$3="Not due",Q13<0),AND(Dashboard!$P$3="Due in 10 days",Q13>=-10,Q13<=0),AND(Dashboard!$P$3="Due in 30 days",Q13>=-30,Q13<=0),AND(Dashboard!$P$3="Overdue 1–60 days",Q13>0,Q13<=60),AND(Dashboard!$P$3="Over 60 days",Q13>60),AND(Dashboard!$P$3="All overdue",Q13>0)),1,0) -> 1 | V13: =S13*U13 -> 284218732 | W13: =IF(Q13>0,T13*Q13,0) -> 0 | X13: =IF(V13>0,COUNTIF($V$6:V13,">0"),"") -> 8 | Y13: =C13&"|"&D13 -> AR-00008|70000008 | AA13: ["Demo Company 045", "AR-00008", "70000008", "2026-10-03"]
A14: Client Alpha (Steel EPC) | B14: CLIENT ALPHA STEEL STRUCTURE CORPORATION | C14: AR-00009 | D14: 70000009 | E14: 46189 | F14: 46264 | G14: 91483402 | H14: 0 | I14: 91483402 | J14: Senior Sales Rep 1 | K14: Trading | L14: Project 003 | M14: Collection note 005 | Q14: =IF(ISNUMBER(F14),Dashboard!$D$2-F14,"") -> 36 | R14: =IF(AND(OR(Dashboard!$P$1="All",A14=Dashboard!$P$1),OR(Dashboard!$P$2="All",J14=Dashboard!$P$2)),1,0) -> 1 | S14: =I14*R14 -> 91483402 | T14: =IF(AND(ISNUMBER(Q14),Q14>0),S14,0) -> 91483402 | U14: =IF(OR(Dashboard!$P$3="All",AND(Dashboard!$P$3="Not due",Q14<0),AND(Dashboard!$P$3="Due in 10 days",Q14>=-10,Q14<=0),AND(Dashboard!$P$3="Due in 30 days",Q14>=-30,Q14<=0),AND(Dashboard!$P$3="Overdue 1–60 days",Q14>0,Q14<=60),AND(Dashboard!$P$3="Over 60 days",Q14>60),AND(Dashboard!$P$3="All overdue",Q14>0)),1,0) -> 1 | V14: =S14*U14 -> 91483402 | W14: =IF(Q14>0,T14*Q14,0) -> 3293402472 | X14: =IF(V14>0,COUNTIF($V$6:V14,">0"),"") -> 9 | Y14: =C14&"|"&D14 -> AR-00009|70000009 | AA14: ["Demo Company 010", "AR-00009", "70000009", "2026-06-16"]
A15: Client Alpha (Steel EPC) | B15: CLIENT ALPHA STEEL STRUCTURE CORPORATION | C15: AR-00010 | D15: 70000010 | E15: 46191 | F15: 46266 | G15: 454201191 | H15: 0 | I15: 454201191 | J15: Senior Sales Rep 1 | K15: Trading | L15: Project 004 | M15: Collection note 006 | Q15: =IF(ISNUMBER(F15),Dashboard!$D$2-F15,"") -> 34 | R15: =IF(AND(OR(Dashboard!$P$1="All",A15=Dashboard!$P$1),OR(Dashboard!$P$2="All",J15=Dashboard!$P$2)),1,0) -> 1 | S15: =I15*R15 -> 454201191 | T15: =IF(AND(ISNUMBER(Q15),Q15>0),S15,0) -> 454201191 | U15: =IF(OR(Dashboard!$P$3="All",AND(Dashboard!$P$3="Not due",Q15<0),AND(Dashboard!$P$3="Due in 10 days",Q15>=-10,Q15<=0),AND(Dashboard!$P$3="Due in 30 days",Q15>=-30,Q15<=0),AND(Dashboard!$P$3="Overdue 1–60 days",Q15>0,Q15<=60),AND(Dashboard!$P$3="Over 60 days",Q15>60),AND(Dashboard!$P$3="All overdue",Q15>0)),1,0) -> 1 | V15: =S15*U15 -> 454201191 | W15: =IF(Q15>0,T15*Q15,0) -> 15442840494 | X15: =IF(V15>0,COUNTIF($V$6:V15,">0"),"") -> 10 | Y15: =C15&"|"&D15 -> AR-00010|70000010 | AA15: ["Demo Company 010", "AR-00010", "70000010", "2026-06-18"]
A16: Client Alpha (Steel EPC) | B16: CLIENT ALPHA STEEL STRUCTURE CORPORATION | C16: AR-00011 | D16: 70000011 | E16: 46197 | F16: 46272 | G16: 114561937 | H16: 0 | I16: 114561937 | J16: Senior Sales Rep 1 | K16: Trading | L16: Project 005 | M16: Collection note 007 | Q16: =IF(ISNUMBER(F16),Dashboard!$D$2-F16,"") -> 28 | R16: =IF(AND(OR(Dashboard!$P$1="All",A16=Dashboard!$P$1),OR(Dashboard!$P$2="All",J16=Dashboard!$P$2)),1,0) -> 1 | S16: =I16*R16 -> 114561937 | T16: =IF(AND(ISNUMBER(Q16),Q16>0),S16,0) -> 114561937 | U16: =IF(OR(Dashboard!$P$3="All",AND(Dashboard!$P$3="Not due",Q16<0),AND(Dashboard!$P$3="Due in 10 days",Q16>=-10,Q16<=0),AND(Dashboard!$P$3="Due in 30 days",Q16>=-30,Q16<=0),AND(Dashboard!$P$3="Overdue 1–60 days",Q16>0,Q16<=60),AND(Dashboard!$P$3="Over 60 days",Q16>60),AND(Dashboard!$P$3="All overdue",Q16>0)),1,0) -> 1 | V16: =S16*U16 -> 114561937 | W16: =IF(Q16>0,T16*Q16,0) -> 3207734236 | X16: =IF(V16>0,COUNTIF($V$6:V16,">0"),"") -> 11 | Y16: =C16&"|"&D16 -> AR-00011|70000011 | AA16: ["Demo Company 010", "AR-00011", "70000011", "2026-06-24"]
A17: Client Alpha (Steel EPC) | B17: CLIENT ALPHA STEEL STRUCTURE CORPORATION | C17: AR-00012 | D17: 70000012 | E17: 46210 | F17: 46285 | G17: 54738470 | H17: 0 | I17: 54738470 | J17: Senior Sales Rep 1 | K17: Trading | L17: Project 006 | M17: Collection note 008 | Q17: =IF(ISNUMBER(F17),Dashboard!$D$2-F17,"") -> 15 | R17: =IF(AND(OR(Dashboard!$P$1="All",A17=Dashboard!$P$1),OR(Dashboard!$P$2="All",J17=Dashboard!$P$2)),1,0) -> 1 | S17: =I17*R17 -> 54738470 | T17: =IF(AND(ISNUMBER(Q17),Q17>0),S17,0) -> 54738470 | U17: =IF(OR(Dashboard!$P$3="All",AND(Dashboard!$P$3="Not due",Q17<0),AND(Dashboard!$P$3="Due in 10 days",Q17>=-10,Q17<=0),AND(Dashboard!$P$3="Due in 30 days",Q17>=-30,Q17<=0),AND(Dashboard!$P$3="Overdue 1–60 days",Q17>0,Q17<=60),AND(Dashboard!$P$3="Over 60 days",Q17>60),AND(Dashboard!$P$3="All overdue",Q17>0)),1,0) -> 1 | V17: =S17*U17 -> 54738470 | W17: =IF(Q17>0,T17*Q17,0) -> 821077050 | X17: =IF(V17>0,COUNTIF($V$6:V17,">0"),"") -> 12 | Y17: =C17&"|"&D17 -> AR-00012|70000012 | AA17: ["Demo Company 010", "AR-00012", "70000012", "2026-07-07"]
A18: Client Alpha (Steel EPC) | B18: CLIENT ALPHA STEEL STRUCTURE CORPORATION | C18: AR-00013 | D18: 70000013 | E18: 46210 | F18: 46285 | G18: 867074591 | H18: 0 | I18: 867074591 | J18: Senior Sales Rep 1 | K18: Trading | L18: Project 007 | M18: Collection note 008 | Q18: =IF(ISNUMBER(F18),Dashboard!$D$2-F18,"") -> 15 | R18: =IF(AND(OR(Dashboard!$P$1="All",A18=Dashboard!$P$1),OR(Dashboard!$P$2="All",J18=Dashboard!$P$2)),1,0) -> 1 | S18: =I18*R18 -> 867074591 | T18: =IF(AND(ISNUMBER(Q18),Q18>0),S18,0) -> 867074591 | U18: =IF(OR(Dashboard!$P$3="All",AND(Dashboard!$P$3="Not due",Q18<0),AND(Dashboard!$P$3="Due in 10 days",Q18>=-10,Q18<=0),AND(Dashboard!$P$3="Due in 30 days",Q18>=-30,Q18<=0),AND(Dashboard!$P$3="Overdue 1–60 days",Q18>0,Q18<=60),AND(Dashboard!$P$3="Over 60 days",Q18>60),AND(Dashboard!$P$3="All overdue",Q18>0)),1,0) -> 1 | V18: =S18*U18 -> 867074591 | W18: =IF(Q18>0,T18*Q18,0) -> 13006118865 | X18: =IF(V18>0,COUNTIF($V$6:V18,">0"),"") -> 13 | Y18: =C18&"|"&D18 -> AR-00013|70000013 | AA18: ["Demo Company 010", "AR-00013", "70000013", "2026-07-07"]
A19: Client Alpha (Steel EPC) | B19: CLIENT ALPHA STEEL STRUCTURE CORPORATION | C19: AR-00014 | D19: 70000014 | E19: 46210 | F19: 46285 | G19: 21434303 | H19: 0 | I19: 21434303 | J19: Senior Sales Rep 1 | K19: Trading | L19: Project 008 | M19: Collection note 008 | Q19: =IF(ISNUMBER(F19),Dashboard!$D$2-F19,"") -> 15 | R19: =IF(AND(OR(Dashboard!$P$1="All",A19=Dashboard!$P$1),OR(Dashboard!$P$2="All",J19=Dashboard!$P$2)),1,0) -> 1 | S19: =I19*R19 -> 21434303 | T19: =IF(AND(ISNUMBER(Q19),Q19>0),S19,0) -> 21434303 | U19: =IF(OR(Dashboard!$P$3="All",AND(Dashboard!$P$3="Not due",Q19<0),AND(Dashboard!$P$3="Due in 10 days",Q19>=-10,Q19<=0),AND(Dashboard!$P$3="Due in 30 days",Q19>=-30,Q19<=0),AND(Dashboard!$P$3="Overdue 1–60 days",Q19>0,Q19<=60),AND(Dashboard!$P$3="Over 60 days",Q19>60),AND(Dashboard!$P$3="All overdue",Q19>0)),1,0) -> 1 | V19: =S19*U19 -> 21434303 | W19: =IF(Q19>0,T19*Q19,0) -> 321514545 | X19: =IF(V19>0,COUNTIF($V$6:V19,">0"),"") -> 14 | Y19: =C19&"|"&D19 -> AR-00014|70000014 | AA19: ["Demo Company 010", "AR-00014", "70000014", "2026-07-07"]
A20: Client Alpha (Steel EPC) | B20: CLIENT ALPHA STEEL STRUCTURE CORPORATION | C20: AR-00015 | D20: 70000015 | E20: 46218 | F20: 46293 | G20: 146356352 | H20: 0 | I20: 146356352 | J20: Senior Sales Rep 1 | K20: Trading | L20: Project 002 | M20: Collection note 009 | Q20: =IF(ISNUMBER(F20),Dashboard!$D$2-F20,"") -> 7 | R20: =IF(AND(OR(Dashboard!$P$1="All",A20=Dashboard!$P$1),OR(Dashboard!$P$2="All",J20=Dashboard!$P$2)),1,0) -> 1 | S20: =I20*R20 -> 146356352 | T20: =IF(AND(ISNUMBER(Q20),Q20>0),S20,0) -> 146356352 | U20: =IF(OR(Dashboard!$P$3="All",AND(Dashboard!$P$3="Not due",Q20<0),AND(Dashboard!$P$3="Due in 10 days",Q20>=-10,Q20<=0),AND(Dashboard!$P$3="Due in 30 days",Q20>=-30,Q20<=0),AND(Dashboard!$P$3="Overdue 1–60 days",Q20>0,Q20<=60),AND(Dashboard!$P$3="Over 60 days",Q20>60),AND(Dashboard!$P$3="All overdue",Q20>0)),1,0) -> 1 | V20: =S20*U20 -> 146356352 | W20: =IF(Q20>0,T20*Q20,0) -> 1024494464 | X20: =IF(V20>0,COUNTIF($V$6:V20,">0"),"") -> 15 | Y20: =C20&"|"&D20 -> AR-00015|70000015 | AA20: ["Demo Company 010", "AR-00015", "70000015", "2026-07-15"]
A21: Client Alpha (Steel EPC) | B21: CLIENT ALPHA STEEL STRUCTURE CORPORATION | C21: AR-00016 | D21: 70000016 | E21: 46220 | F21: 46295 | G21: 203352659 | H21: 0 | I21: 203352659 | J21: Senior Sales Rep 1 | K21: Trading | L21: Project 003 | M21: Collection note 008 | Q21: =IF(ISNUMBER(F21),Dashboard!$D$2-F21,"") -> 5 | R21: =IF(AND(OR(Dashboard!$P$1="All",A21=Dashboard!$P$1),OR(Dashboard!$P$2="All",J21=Dashboard!$P$2)),1,0) -> 1 | S21: =I21*R21 -> 203352659 | T21: =IF(AND(ISNUMBER(Q21),Q21>0),S21,0) -> 203352659 | U21: =IF(OR(Dashboard!$P$3="All",AND(Dashboard!$P$3="Not due",Q21<0),AND(Dashboard!$P$3="Due in 10 days",Q21>=-10,Q21<=0),AND(Dashboard!$P$3="Due in 30 days",Q21>=-30,Q21<=0),AND(Dashboard!$P$3="Overdue 1–60 days",Q21>0,Q21<=60),AND(Dashboard!$P$3="Over 60 days",Q21>60),AND(Dashboard!$P$3="All overdue",Q21>0)),1,0) -> 1 | V21: =S21*U21 -> 203352659 | W21: =IF(Q21>0,T21*Q21,0) -> 1016763295 | X21: =IF(V21>0,COUNTIF($V$6:V21,">0"),"") -> 16 | Y21: =C21&"|"&D21 -> AR-00016|70000016 | AA21: ["Demo Company 010", "AR-00016", "70000016", "2026-07-17"]
A22: Client Alpha (Steel EPC) | B22: CLIENT ALPHA STEEL STRUCTURE CORPORATION | C22: AR-00017 | D22: 70000017 | E22: 46220 | F22: 46295 | G22: 271688134 | H22: 0 | I22: 271688134 | J22: Senior Sales Rep 1 | K22: Trading | L22: Project 004 | M22: Collection note 008 | Q22: =IF(ISNUMBER(F22),Dashboard!$D$2-F22,"") -> 5 | R22: =IF(AND(OR(Dashboard!$P$1="All",A22=Dashboard!$P$1),OR(Dashboard!$P$2="All",J22=Dashboard!$P$2)),1,0) -> 1 | S22: =I22*R22 -> 271688134 | T22: =IF(AND(ISNUMBER(Q22),Q22>0),S22,0) -> 271688134 | U22: =IF(OR(Dashboard!$P$3="All",AND(Dashboard!$P$3="Not due",Q22<0),AND(Dashboard!$P$3="Due in 10 days",Q22>=-10,Q22<=0),AND(Dashboard!$P$3="Due in 30 days",Q22>=-30,Q22<=0),AND(Dashboard!$P$3="Overdue 1–60 days",Q22>0,Q22<=60),AND(Dashboard!$P$3="Over 60 days",Q22>60),AND(Dashboard!$P$3="All overdue",Q22>0)),1,0) -> 1 | V22: =S22*U22 -> 271688134 | W22: =IF(Q22>0,T22*Q22,0) -> 1358440670 | X22: =IF(V22>0,COUNTIF($V$6:V22,">0"),"") -> 17 | Y22: =C22&"|"&D22 -> AR-00017|70000017 | AA22: ["Demo Company 010", "AR-00017", "70000017", "2026-07-17"]
A23: Client Alpha (Steel EPC) | B23: CLIENT ALPHA STEEL STRUCTURE CORPORATION | C23: AR-00018 | D23: 70000018 | E23: 46220 | F23: 46295 | G23: 330520960 | H23: 0 | I23: 330520960 | J23: Senior Sales Rep 1 | K23: Trading | L23: Project 005 | M23: Collection note 008 | Q23: =IF(ISNUMBER(F23),Dashboard!$D$2-F23,"") -> 5 | R23: =IF(AND(OR(Dashboard!$P$1="All",A23=Dashboard!$P$1),OR(Dashboard!$P$2="All",J23=Dashboard!$P$2)),1,0) -> 1 | S23: =I23*R23 -> 330520960 | T23: =IF(AND(ISNUMBER(Q23),Q23>0),S23,0) -> 330520960 | U23: =IF(OR(Dashboard!$P$3="All",AND(Dashboard!$P$3="Not due",Q23<0),AND(Dashboard!$P$3="Due in 10 days",Q23>=-10,Q23<=0),AND(Dashboard!$P$3="Due in 30 days",Q23>=-30,Q23<=0),AND(Dashboard!$P$3="Overdue 1–60 days",Q23>0,Q23<=60),AND(Dashboard!$P$3="Over 60 days",Q23>60),AND(Dashboard!$P$3="All overdue",Q23>0)),1,0) -> 1 | V23: =S23*U23 -> 330520960 | W23: =IF(Q23>0,T23*Q23,0) -> 1652604800 | X23: =IF(V23>0,COUNTIF($V$6:V23,">0"),"") -> 18 | Y23: =C23&"|"&D23 -> AR-00018|70000018 | AA23: ["Demo Company 010", "AR-00018", "70000018", "2026-07-17"]
A24: Client Alpha (Steel EPC) | B24: CLIENT ALPHA STEEL STRUCTURE CORPORATION | C24: AR-00019 | D24: 70000019 | E24: 46225 | F24: 46300 | G24: 36887245 | H24: 0 | I24: 36887245 | J24: Senior Sales Rep 1 | K24: Trading | L24: Project 006 | M24: Collection note 007 | Q24: =IF(ISNUMBER(F24),Dashboard!$D$2-F24,"") -> 0 | R24: =IF(AND(OR(Dashboard!$P$1="All",A24=Dashboard!$P$1),OR(Dashboard!$P$2="All",J24=Dashboard!$P$2)),1,0) -> 1 | S24: =I24*R24 -> 36887245 | T24: =IF(AND(ISNUMBER(Q24),Q24>0),S24,0) -> 0 | U24: =IF(OR(Dashboard!$P$3="All",AND(Dashboard!$P$3="Not due",Q24<0),AND(Dashboard!$P$3="Due in 10 days",Q24>=-10,Q24<=0),AND(Dashboard!$P$3="Due in 30 days",Q24>=-30,Q24<=0),AND(Dashboard!$P$3="Overdue 1–60 days",Q24>0,Q24<=60),AND(Dashboard!$P$3="Over 60 days",Q24>60),AND(Dashboard!$P$3="All overdue",Q24>0)),1,0) -> 1 | V24: =S24*U24 -> 36887245 | W24: =IF(Q24>0,T24*Q24,0) -> 0 | X24: =IF(V24>0,COUNTIF($V$6:V24,">0"),"") -> 19 | Y24: =C24&"|"&D24 -> AR-00019|70000019 | AA24: ["Demo Company 010", "AR-00019", "70000019", "2026-07-22"]
... A70: Client Alpha (Steel EPC) | B70: CLIENT ALPHA STEEL STRUCTURE CORPORATION | C70: AR-00065 | D70: 70000065 | E70: 46282 | F70: 46357 | G70: 154151485 | H70: 0 | I70: 154151485 | J70: Senior Sales Rep 1 | K70: Trading | L70: Project 003 | M70: Collection note 011 | Q70: =IF(ISNUMBER(F70),Dashboard!$D$2-F70,"") -> -57 | R70: =IF(AND(OR(Dashboard!$P$1="All",A70=Dashboard!$P$1),OR(Dashboard!$P$2="All",J70=Dashboard!$P$2)),1,0) -> 1 | S70: =I70*R70 -> 154151485 | T70: =IF(AND(ISNUMBER(Q70),Q70>0),S70,0) -> 0 | U70: =IF(OR(Dashboard!$P$3="All",AND(Dashboard!$P$3="Not due",Q70<0),AND(Dashboard!$P$3="Due in 10 days",Q70>=-10,Q70<=0),AND(Dashboard!$P$3="Due in 30 days",Q70>=-30,Q70<=0),AND(Dashboard!$P$3="Overdue 1–60 days",Q70>0,Q70<=60),AND(Dashboard!$P$3="Over 60 days",Q70>60),AND(Dashboard!$P$3="All overdue",Q70>0)),1,0) -> 1 | V70: =S70*U70 -> 154151485 | W70: =IF(Q70>0,T70*Q70,0) -> 0 | X70: =IF(V70>0,COUNTIF($V$6:V70,">0"),"") -> 65 | Y70: =C70&"|"&D70 -> AR-00065|70000065 | AA70: ["Demo Company 010", "AR-00065", "70000065", "2026-09-17"]
A71: Client Alpha (Steel EPC) | B71: CLIENT ALPHA STEEL STRUCTURE CORPORATION | C71: AR-00066 | D71: 70000066 | E71: 46288 | F71: 46358 | G71: 1378039877 | H71: 0 | I71: 1378039877 | J71: Senior Sales Rep 2 | K71: Project | M71: Collection note 014 | Q71: =IF(ISNUMBER(F71),Dashboard!$D$2-F71,"") -> -58 | R71: =IF(AND(OR(Dashboard!$P$1="All",A71=Dashboard!$P$1),OR(Dashboard!$P$2="All",J71=Dashboard!$P$2)),1,0) -> 1 | S71: =I71*R71 -> 1378039877 | T71: =IF(AND(ISNUMBER(Q71),Q71>0),S71,0) -> 0 | U71: =IF(OR(Dashboard!$P$3="All",AND(Dashboard!$P$3="Not due",Q71<0),AND(Dashboard!$P$3="Due in 10 days",Q71>=-10,Q71<=0),AND(Dashboard!$P$3="Due in 30 days",Q71>=-30,Q71<=0),AND(Dashboard!$P$3="Overdue 1–60 days",Q71>0,Q71<=60),AND(Dashboard!$P$3="Over 60 days",Q71>60),AND(Dashboard!$P$3="All overdue",Q71>0)),1,0) -> 1 | V71: =S71*U71 -> 1378039877 | W71: =IF(Q71>0,T71*Q71,0) -> 0 | X71: =IF(V71>0,COUNTIF($V$6:V71,">0"),"") -> 66 | Y71: =C71&"|"&D71 -> AR-00066|70000066 | AA71: ["Demo Company 010", "AR-00066", "70000066", "2026-09-23"]
A72: Client Alpha (Steel EPC) | B72: CLIENT ALPHA STEEL STRUCTURE CORPORATION | C72: AR-00067 | D72: 70000067 | E72: 46288 | F72: 46358 | G72: 2781998738 | H72: 0 | I72: 2781998738 | J72: Senior Sales Rep 2 | K72: Project | M72: Collection note 015 | Q72: =IF(ISNUMBER(F72),Dashboard!$D$2-F72,"") -> -58 | R72: =IF(AND(OR(Dashboard!$P$1="All",A72=Dashboard!$P$1),OR(Dashboard!$P$2="All",J72=Dashboard!$P$2)),1,0) -> 1 | S72: =I72*R72 -> 2781998738 | T72: =IF(AND(ISNUMBER(Q72),Q72>0),S72,0) -> 0 | U72: =IF(OR(Dashboard!$P$3="All",AND(Dashboard!$P$3="Not due",Q72<0),AND(Dashboard!$P$3="Due in 10 days",Q72>=-10,Q72<=0),AND(Dashboard!$P$3="Due in 30 days",Q72>=-30,Q72<=0),AND(Dashboard!$P$3="Overdue 1–60 days",Q72>0,Q72<=60),AND(Dashboard!$P$3="Over 60 days",Q72>60),AND(Dashboard!$P$3="All overdue",Q72>0)),1,0) -> 1 | V72: =S72*U72 -> 2781998738 | W72: =IF(Q72>0,T72*Q72,0) -> 0 | X72: =IF(V72>0,COUNTIF($V$6:V72,">0"),"") -> 67 | Y72: =C72&"|"&D72 -> AR-00067|70000067 | AA72: ["Demo Company 010", "AR-00067", "70000067", "2026-09-23"]
A73: Client Alpha (Steel EPC) | B73: CLIENT ALPHA STEEL STRUCTURE CORPORATION | C73: AR-00068 | D73: 70000068 | E73: 46289 | F73: 46359 | G73: 1233595934 | H73: 0 | I73: 1233595934 | J73: Senior Sales Rep 2 | K73: Project | M73: Collection note 016 | Q73: =IF(ISNUMBER(F73),Dashboard!$D$2-F73,"") -> -59 | R73: =IF(AND(OR(Dashboard!$P$1="All",A73=Dashboard!$P$1),OR(Dashboard!$P$2="All",J73=Dashboard!$P$2)),1,0) -> 1 | S73: =I73*R73 -> 1233595934 | T73: =IF(AND(ISNUMBER(Q73),Q73>0),S73,0) -> 0 | U73: =IF(OR(Dashboard!$P$3="All",AND(Dashboard!$P$3="Not due",Q73<0),AND(Dashboard!$P$3="Due in 10 days",Q73>=-10,Q73<=0),AND(Dashboard!$P$3="Due in 30 days",Q73>=-30,Q73<=0),AND(Dashboard!$P$3="Overdue 1–60 days",Q73>0,Q73<=60),AND(Dashboard!$P$3="Over 60 days",Q73>60),AND(Dashboard!$P$3="All overdue",Q73>0)),1,0) -> 1 | V73: =S73*U73 -> 1233595934 | W73: =IF(Q73>0,T73*Q73,0) -> 0 | X73: =IF(V73>0,COUNTIF($V$6:V73,">0"),"") -> 68 | Y73: =C73&"|"&D73 -> AR-00068|70000068 | AA73: ["Demo Company 010", "AR-00068", "70000068", "2026-09-24"]
A74: Client Alpha (Steel EPC) | B74: CLIENT ALPHA STEEL STRUCTURE CORPORATION | C74: AR-00069 | D74: 70000069 | E74: 46289 | F74: 46359 | G74: 3074061247 | H74: 0 | I74: 3074061247 | J74: Senior Sales Rep 2 | K74: Project | M74: Collection note 017 | Q74: =IF(ISNUMBER(F74),Dashboard!$D$2-F74,"") -> -59 | R74: =IF(AND(OR(Dashboard!$P$1="All",A74=Dashboard!$P$1),OR(Dashboard!$P$2="All",J74=Dashboard!$P$2)),1,0) -> 1 | S74: =I74*R74 -> 3074061247 | T74: =IF(AND(ISNUMBER(Q74),Q74>0),S74,0) -> 0 | U74: =IF(OR(Dashboard!$P$3="All",AND(Dashboard!$P$3="Not due",Q74<0),AND(Dashboard!$P$3="Due in 10 days",Q74>=-10,Q74<=0),AND(Dashboard!$P$3="Due in 30 days",Q74>=-30,Q74<=0),AND(Dashboard!$P$3="Overdue 1–60 days",Q74>0,Q74<=60),AND(Dashboard!$P$3="Over 60 days",Q74>60),AND(Dashboard!$P$3="All overdue",Q74>0)),1,0) -> 1 | V74: =S74*U74 -> 3074061247 | W74: =IF(Q74>0,T74*Q74,0) -> 0 | X74: =IF(V74>0,COUNTIF($V$6:V74,">0"),"") -> 69 | Y74: =C74&"|"&D74 -> AR-00069|70000069 | AA74: ["Demo Company 010", "AR-00069", "70000069", "2026-09-24"]
A75: Client Alpha (Steel EPC) | B75: CLIENT ALPHA STEEL STRUCTURE CORPORATION | C75: AR-00070 | D75: 70000070 | E75: 46289 | F75: 46364 | G75: 349295 | H75: 0 | I75: 349295 | J75: Senior Sales Rep 1 | K75: Trading | L75: Project 008 | M75: Collection note 011 | Q75: =IF(ISNUMBER(F75),Dashboard!$D$2-F75,"") -> -64 | R75: =IF(AND(OR(Dashboard!$P$1="All",A75=Dashboard!$P$1),OR(Dashboard!$P$2="All",J75=Dashboard!$P$2)),1,0) -> 1 | S75: =I75*R75 -> 349295 | T75: =IF(AND(ISNUMBER(Q75),Q75>0),S75,0) -> 0 | U75: =IF(OR(Dashboard!$P$3="All",AND(Dashboard!$P$3="Not due",Q75<0),AND(Dashboard!$P$3="Due in 10 days",Q75>=-10,Q75<=0),AND(Dashboard!$P$3="Due in 30 days",Q75>=-30,Q75<=0),AND(Dashboard!$P$3="Overdue 1–60 days",Q75>0,Q75<=60),AND(Dashboard!$P$3="Over 60 days",Q75>60),AND(Dashboard!$P$3="All overdue",Q75>0)),1,0) -> 1 | V75: =S75*U75 -> 349295 | W75: =IF(Q75>0,T75*Q75,0) -> 0 | X75: =IF(V75>0,COUNTIF($V$6:V75,">0"),"") -> 70 | Y75: =C75&"|"&D75 -> AR-00070|70000070 | AA75: ["Demo Company 010", "AR-00070", "70000070", "2026-09-24"]
A76: Client Alpha (Steel EPC) | B76: CLIENT ALPHA STEEL STRUCTURE CORPORATION | C76: AR-00071 | D76: 70000071 | E76: 46289 | F76: 46364 | G76: 95221374 | H76: 0 | I76: 95221374 | J76: Senior Sales Rep 1 | K76: Trading | L76: Project 002 | M76: Collection note 011 | Q76: =IF(ISNUMBER(F76),Dashboard!$D$2-F76,"") -> -64 | R76: =IF(AND(OR(Dashboard!$P$1="All",A76=Dashboard!$P$1),OR(Dashboard!$P$2="All",J76=Dashboard!$P$2)),1,0) -> 1 | S76: =I76*R76 -> 95221374 | T76: =IF(AND(ISNUMBER(Q76),Q76>0),S76,0) -> 0 | U76: =IF(OR(Dashboard!$P$3="All",AND(Dashboard!$P$3="Not due",Q76<0),AND(Dashboard!$P$3="Due in 10 days",Q76>=-10,Q76<=0),AND(Dashboard!$P$3="Due in 30 days",Q76>=-30,Q76<=0),AND(Dashboard!$P$3="Overdue 1–60 days",Q76>0,Q76<=60),AND(Dashboard!$P$3="Over 60 days",Q76>60),AND(Dashboard!$P$3="All overdue",Q76>0)),1,0) -> 1 | V76: =S76*U76 -> 95221374 | W76: =IF(Q76>0,T76*Q76,0) -> 0 | X76: =IF(V76>0,COUNTIF($V$6:V76,">0"),"") -> 71 | Y76: =C76&"|"&D76 -> AR-00071|70000071 | AA76: ["Demo Company 010", "AR-00071", "70000071", "2026-09-24"]
A77: Client Alpha (Steel EPC) | B77: CLIENT ALPHA STEEL STRUCTURE CORPORATION | C77: AR-00072 | D77: 70000072 | E77: 46289 | F77: 46364 | G77: 9559012 | H77: 0 | I77: 9559012 | J77: Senior Sales Rep 1 | K77: Trading | L77: Project 003 | M77: Collection note 011 | Q77: =IF(ISNUMBER(F77),Dashboard!$D$2-F77,"") -> -64 | R77: =IF(AND(OR(Dashboard!$P$1="All",A77=Dashboard!$P$1),OR(Dashboard!$P$2="All",J77=Dashboard!$P$2)),1,0) -> 1 | S77: =I77*R77 -> 9559012 | T77: =IF(AND(ISNUMBER(Q77),Q77>0),S77,0) -> 0 | U77: =IF(OR(Dashboard!$P$3="All",AND(Dashboard!$P$3="Not due",Q77<0),AND(Dashboard!$P$3="Due in 10 days",Q77>=-10,Q77<=0),AND(Dashboard!$P$3="Due in 30 days",Q77>=-30,Q77<=0),AND(Dashboard!$P$3="Overdue 1–60 days",Q77>0,Q77<=60),AND(Dashboard!$P$3="Over 60 days",Q77>60),AND(Dashboard!$P$3="All overdue",Q77>0)),1,0) -> 1 | V77: =S77*U77 -> 9559012 | W77: =IF(Q77>0,T77*Q77,0) -> 0 | X77: =IF(V77>0,COUNTIF($V$6:V77,">0"),"") -> 72 | Y77: =C77&"|"&D77 -> AR-00072|70000072 | AA77: ["Demo Company 010", "AR-00072", "70000072", "2026-09-24"]
A78: Client Alpha (Steel EPC) | B78: CLIENT ALPHA STEEL STRUCTURE CORPORATION | C78: AR-00073 | D78: 70000073 | E78: 46289 | F78: 46364 | G78: 7011259 | H78: 0 | I78: 7011259 | J78: Senior Sales Rep 2 | K78: Trading | L78: Project 004 | M78: Collection note 013 | Q78: =IF(ISNUMBER(F78),Dashboard!$D$2-F78,"") -> -64 | R78: =IF(AND(OR(Dashboard!$P$1="All",A78=Dashboard!$P$1),OR(Dashboard!$P$2="All",J78=Dashboard!$P$2)),1,0) -> 1 | S78: =I78*R78 -> 7011259 | T78: =IF(AND(ISNUMBER(Q78),Q78>0),S78,0) -> 0 | U78: =IF(OR(Dashboard!$P$3="All",AND(Dashboard!$P$3="Not due",Q78<0),AND(Dashboard!$P$3="Due in 10 days",Q78>=-10,Q78<=0),AND(Dashboard!$P$3="Due in 30 days",Q78>=-30,Q78<=0),AND(Dashboard!$P$3="Overdue 1–60 days",Q78>0,Q78<=60),AND(Dashboard!$P$3="Over 60 days",Q78>60),AND(Dashboard!$P$3="All overdue",Q78>0)),1,0) -> 1 | V78: =S78*U78 -> 7011259 | W78: =IF(Q78>0,T78*Q78,0) -> 0 | X78: =IF(V78>0,COUNTIF($V$6:V78,">0"),"") -> 73 | Y78: =C78&"|"&D78 -> AR-00073|70000073 | AA78: ["Demo Company 010", "AR-00073", "70000073", "2026-09-24"]
A79: Client Alpha (Steel EPC) | B79: CLIENT ALPHA STEEL STRUCTURE CORPORATION | C79: AR-00074 | D79: 70000074 | E79: 46289 | F79: 46364 | G79: 5046104601 | H79: 0 | I79: 5046104601 | J79: Senior Sales Rep 2 | K79: Trading | L79: Project 005 | M79: Collection note 013 | Q79: =IF(ISNUMBER(F79),Dashboard!$D$2-F79,"") -> -64 | R79: =IF(AND(OR(Dashboard!$P$1="All",A79=Dashboard!$P$1),OR(Dashboard!$P$2="All",J79=Dashboard!$P$2)),1,0) -> 1 | S79: =I79*R79 -> 5046104601 | T79: =IF(AND(ISNUMBER(Q79),Q79>0),S79,0) -> 0 | U79: =IF(OR(Dashboard!$P$3="All",AND(Dashboard!$P$3="Not due",Q79<0),AND(Dashboard!$P$3="Due in 10 days",Q79>=-10,Q79<=0),AND(Dashboard!$P$3="Due in 30 days",Q79>=-30,Q79<=0),AND(Dashboard!$P$3="Overdue 1–60 days",Q79>0,Q79<=60),AND(Dashboard!$P$3="Over 60 days",Q79>60),AND(Dashboard!$P$3="All overdue",Q79>0)),1,0) -> 1 | V79: =S79*U79 -> 5046104601 | W79: =IF(Q79>0,T79*Q79,0) -> 0 | X79: =IF(V79>0,COUNTIF($V$6:V79,">0"),"") -> 74 | Y79: =C79&"|"&D79 -> AR-00074|70000074 | AA79: ["Demo Company 010", "AR-00074", "70000074", "2026-09-24"]
A80: Client Alpha (Steel EPC) | B80: CLIENT ALPHA STEEL STRUCTURE CORPORATION | C80: AR-00075 | D80: 70000075 | E80: 46289 | F80: 46364 | G80: 37392839 | H80: 0 | I80: 37392839 | J80: Senior Sales Rep 2 | K80: Trading | L80: Project 006 | M80: Collection note 013 | Q80: =IF(ISNUMBER(F80),Dashboard!$D$2-F80,"") -> -64 | R80: =IF(AND(OR(Dashboard!$P$1="All",A80=Dashboard!$P$1),OR(Dashboard!$P$2="All",J80=Dashboard!$P$2)),1,0) -> 1 | S80: =I80*R80 -> 37392839 | T80: =IF(AND(ISNUMBER(Q80),Q80>0),S80,0) -> 0 | U80: =IF(OR(Dashboard!$P$3="All",AND(Dashboard!$P$3="Not due",Q80<0),AND(Dashboard!$P$3="Due in 10 days",Q80>=-10,Q80<=0),AND(Dashboard!$P$3="Due in 30 days",Q80>=-30,Q80<=0),AND(Dashboard!$P$3="Overdue 1–60 days",Q80>0,Q80<=60),AND(Dashboard!$P$3="Over 60 days",Q80>60),AND(Dashboard!$P$3="All overdue",Q80>0)),1,0) -> 1 | V80: =S80*U80 -> 37392839 | W80: =IF(Q80>0,T80*Q80,0) -> 0 | X80: =IF(V80>0,COUNTIF($V$6:V80,">0"),"") -> 75 | Y80: =C80&"|"&D80 -> AR-00075|70000075 | AA80: ["Demo Company 010", "AR-00075", "70000075", "2026-09-24"]
A81: Client Alpha (Steel EPC) | B81: CLIENT ALPHA STEEL STRUCTURE CORPORATION | C81: AR-00076 | D81: 70000076 | E81: 46289 | F81: 46364 | G81: 2613764 | H81: 0 | I81: 2613764 | J81: Senior Sales Rep 2 | K81: Trading | L81: Project 007 | M81: Collection note 013 | Q81: =IF(ISNUMBER(F81),Dashboard!$D$2-F81,"") -> -64 | R81: =IF(AND(OR(Dashboard!$P$1="All",A81=Dashboard!$P$1),OR(Dashboard!$P$2="All",J81=Dashboard!$P$2)),1,0) -> 1 | S81: =I81*R81 -> 2613764 | T81: =IF(AND(ISNUMBER(Q81),Q81>0),S81,0) -> 0 | U81: =IF(OR(Dashboard!$P$3="All",AND(Dashboard!$P$3="Not due",Q81<0),AND(Dashboard!$P$3="Due in 10 days",Q81>=-10,Q81<=0),AND(Dashboard!$P$3="Due in 30 days",Q81>=-30,Q81<=0),AND(Dashboard!$P$3="Overdue 1–60 days",Q81>0,Q81<=60),AND(Dashboard!$P$3="Over 60 days",Q81>60),AND(Dashboard!$P$3="All overdue",Q81>0)),1,0) -> 1 | V81: =S81*U81 -> 2613764 | W81: =IF(Q81>0,T81*Q81,0) -> 0 | X81: =IF(V81>0,COUNTIF($V$6:V81,">0"),"") -> 76 | Y81: =C81&"|"&D81 -> AR-00076|70000076 | AA81: ["Demo Company 010", "AR-00076", "70000076", "2026-09-24"]
A82: Client Alpha (Steel EPC) | B82: CLIENT ALPHA STEEL STRUCTURE CORPORATION | C82: AR-00077 | D82: 70000077 | E82: 46294 | F82: 46369 | G82: 120506759 | H82: 0 | I82: 120506759 | J82: Senior Sales Rep 1 | K82: Trading | L82: Project 008 | M82: Collection note 006 | Q82: =IF(ISNUMBER(F82),Dashboard!$D$2-F82,"") -> -69 | R82: =IF(AND(OR(Dashboard!$P$1="All",A82=Dashboard!$P$1),OR(Dashboard!$P$2="All",J82=Dashboard!$P$2)),1,0) -> 1 | S82: =I82*R82 -> 120506759 | T82: =IF(AND(ISNUMBER(Q82),Q82>0),S82,0) -> 0 | U82: =IF(OR(Dashboard!$P$3="All",AND(Dashboard!$P$3="Not due",Q82<0),AND(Dashboard!$P$3="Due in 10 days",Q82>=-10,Q82<=0),AND(Dashboard!$P$3="Due in 30 days",Q82>=-30,Q82<=0),AND(Dashboard!$P$3="Overdue 1–60 days",Q82>0,Q82<=60),AND(Dashboard!$P$3="Over 60 days",Q82>60),AND(Dashboard!$P$3="All overdue",Q82>0)),1,0) -> 1 | V82: =S82*U82 -> 120506759 | W82: =IF(Q82>0,T82*Q82,0) -> 0 | X82: =IF(V82>0,COUNTIF($V$6:V82,">0"),"") -> 77 | Y82: =C82&"|"&D82 -> AR-00077|70000077 | AA82: ["Demo Company 010", "AR-00077", "70000077", "2026-09-29"]
A83: Client Alpha (Steel EPC) | B83: CLIENT ALPHA STEEL STRUCTURE CORPORATION | C83: AR-00078 | D83: 70000078 | E83: 46294 | F83: 46369 | G83: 120506759 | H83: 0 | I83: 120506759 | J83: Senior Sales Rep 1 | K83: Trading | L83: Project 002 | M83: Collection note 006 | Q83: =IF(ISNUMBER(F83),Dashboard!$D$2-F83,"") -> -69 | R83: =IF(AND(OR(Dashboard!$P$1="All",A83=Dashboard!$P$1),OR(Dashboard!$P$2="All",J83=Dashboard!$P$2)),1,0) -> 1 | S83: =I83*R83 -> 120506759 | T83: =IF(AND(ISNUMBER(Q83),Q83>0),S83,0) -> 0 | U83: =IF(OR(Dashboard!$P$3="All",AND(Dashboard!$P$3="Not due",Q83<0),AND(Dashboard!$P$3="Due in 10 days",Q83>=-10,Q83<=0),AND(Dashboard!$P$3="Due in 30 days",Q83>=-30,Q83<=0),AND(Dashboard!$P$3="Overdue 1–60 days",Q83>0,Q83<=60),AND(Dashboard!$P$3="Over 60 days",Q83>60),AND(Dashboard!$P$3="All overdue",Q83>0)),1,0) -> 1 | V83: =S83*U83 -> 120506759 | W83: =IF(Q83>0,T83*Q83,0) -> 0 | X83: =IF(V83>0,COUNTIF($V$6:V83,">0"),"") -> 78 | Y83: =C83&"|"&D83 -> AR-00078|70000078 | AA83: ["Demo Company 010", "AR-00078", "70000078", "2026-09-29"]
A84: Client Alpha (Steel EPC) | B84: CLIENT ALPHA STEEL STRUCTURE CORPORATION | C84: AR-00079 | D84: 70000079 | E84: 46294 | F84: 46369 | G84: 30367332 | H84: 0 | I84: 30367332 | J84: Senior Sales Rep 1 | K84: Trading | L84: Project 003 | M84: Collection note 009 | Q84: =IF(ISNUMBER(F84),Dashboard!$D$2-F84,"") -> -69 | R84: =IF(AND(OR(Dashboard!$P$1="All",A84=Dashboard!$P$1),OR(Dashboard!$P$2="All",J84=Dashboard!$P$2)),1,0) -> 1 | S84: =I84*R84 -> 30367332 | T84: =IF(AND(ISNUMBER(Q84),Q84>0),S84,0) -> 0 | U84: =IF(OR(Dashboard!$P$3="All",AND(Dashboard!$P$3="Not due",Q84<0),AND(Dashboard!$P$3="Due in 10 days",Q84>=-10,Q84<=0),AND(Dashboard!$P$3="Due in 30 days",Q84>=-30,Q84<=0),AND(Dashboard!$P$3="Overdue 1–60 days",Q84>0,Q84<=60),AND(Dashboard!$P$3="Over 60 days",Q84>60),AND(Dashboard!$P$3="All overdue",Q84>0)),1,0) -> 1 | V84: =S84*U84 -> 30367332 | W84: =IF(Q84>0,T84*Q84,0) -> 0 | X84: =IF(V84>0,COUNTIF($V$6:V84,">0"),"") -> 79 | Y84: =C84&"|"&D84 -> AR-00079|70000079 | AA84: ["Demo Company 010", "AR-00079", "70000079", "2026-09-29"]
A85: Client Alpha (Steel EPC) | B85: CLIENT ALPHA STEEL STRUCTURE CORPORATION | C85: AR-00080 | D85: 70000080 | E85: 46294 | F85: 46369 | G85: 1424478 | H85: 0 | I85: 1424478 | J85: Senior Sales Rep 1 | K85: Trading | L85: Project 004 | M85: Collection note 009 | Q85: =IF(ISNUMBER(F85),Dashboard!$D$2-F85,"") -> -69 | R85: =IF(AND(OR(Dashboard!$P$1="All",A85=Dashboard!$P$1),OR(Dashboard!$P$2="All",J85=Dashboard!$P$2)),1,0) -> 1 | S85: =I85*R85 -> 1424478 | T85: =IF(AND(ISNUMBER(Q85),Q85>0),S85,0) -> 0 | U85: =IF(OR(Dashboard!$P$3="All",AND(Dashboard!$P$3="Not due",Q85<0),AND(Dashboard!$P$3="Due in 10 days",Q85>=-10,Q85<=0),AND(Dashboard!$P$3="Due in 30 days",Q85>=-30,Q85<=0),AND(Dashboard!$P$3="Overdue 1–60 days",Q85>0,Q85<=60),AND(Dashboard!$P$3="Over 60 days",Q85>60),AND(Dashboard!$P$3="All overdue",Q85>0)),1,0) -> 1 | V85: =S85*U85 -> 1424478 | W85: =IF(Q85>0,T85*Q85,0) -> 0 | X85: =IF(V85>0,COUNTIF($V$6:V85,">0"),"") -> 80 | Y85: =C85&"|"&D85 -> AR-00080|70000080 | AA85: ["Demo Company 010", "AR-00080", "70000080", "2026-09-29"]
A86: Client Alpha (Steel EPC) | B86: CLIENT ALPHA STEEL STRUCTURE CORPORATION | C86: AR-00081 | D86: 70000081 | E86: 46294 | F86: 46369 | G86: 6760671 | H86: 0 | I86: 6760671 | J86: Senior Sales Rep 1 | K86: Trading | L86: Project 005 | M86: Collection note 009 | Q86: =IF(ISNUMBER(F86),Dashboard!$D$2-F86,"") -> -69 | R86: =IF(AND(OR(Dashboard!$P$1="All",A86=Dashboard!$P$1),OR(Dashboard!$P$2="All",J86=Dashboard!$P$2)),1,0) -> 1 | S86: =I86*R86 -> 6760671 | T86: =IF(AND(ISNUMBER(Q86),Q86>0),S86,0) -> 0 | U86: =IF(OR(Dashboard!$P$3="All",AND(Dashboard!$P$3="Not due",Q86<0),AND(Dashboard!$P$3="Due in 10 days",Q86>=-10,Q86<=0),AND(Dashboard!$P$3="Due in 30 days",Q86>=-30,Q86<=0),AND(Dashboard!$P$3="Overdue 1–60 days",Q86>0,Q86<=60),AND(Dashboard!$P$3="Over 60 days",Q86>60),AND(Dashboard!$P$3="All overdue",Q86>0)),1,0) -> 1 | V86: =S86*U86 -> 6760671 | W86: =IF(Q86>0,T86*Q86,0) -> 0 | X86: =IF(V86>0,COUNTIF($V$6:V86,">0"),"") -> 81 | Y86: =C86&"|"&D86 -> AR-00081|70000081 | AA86: ["Demo Company 010", "AR-00081", "70000081", "2026-09-29"]
... A101: Client Epsilon (Equipment) | B101: CLIENT EPSILON INDUSTRIAL EQUIPMENT LTD | C101: AR-00096 | D101: 70000096 | E101: 46294 | F101: 46324 | G101: 43462950 | H101: 0 | I101: 43462950 | J101: Sales Rep 4 | K101: Trading | L101: Project 006 | M101: Collection note 022 | Q101: =IF(ISNUMBER(F101),Dashboard!$D$2-F101,"") -> -24 | R101: =IF(AND(OR(Dashboard!$P$1="All",A101=Dashboard!$P$1),OR(Dashboard!$P$2="All",J101=Dashboard!$P$2)),1,0) -> 1 | S101: =I101*R101 -> 43462950 | T101: =IF(AND(ISNUMBER(Q101),Q101>0),S101,0) -> 0 | U101: =IF(OR(Dashboard!$P$3="All",AND(Dashboard!$P$3="Not due",Q101<0),AND(Dashboard!$P$3="Due in 10 days",Q101>=-10,Q101<=0),AND(Dashboard!$P$3="Due in 30 days",Q101>=-30,Q101<=0),AND(Dashboard!$P$3="Overdue 1–60 days",Q101>0,Q101<=60),AND(Dashboard!$P$3="Over 60 days",Q101>60),AND(Dashboard!$P$3="All overdue",Q101>0)),1,0) -> 1 | V101: =S101*U101 -> 43462950 | W101: =IF(Q101>0,T101*Q101,0) -> 0 | X101: =IF(V101>0,COUNTIF($V$6:V101,">0"),"") -> 96 | Y101: =C101&"|"&D101 -> AR-00096|70000096 | AA101: ["CLIENT EPSILON DEMO COMPANY", "AR-00096", "70000096", "2026-09-29"]
A102: Client Zeta (Building Tech) | B102: CLIENT ZETA BUILDING ENVELOPE SOLUTIONS | C102: AR-00097 | D102: 70000097 | E102: 46262 | F102: 46322 | G102: 324663 | H102: 0 | I102: 324663 | J102: Sales Rep 5 | K102: Trading | M102: Collection note 023 | Q102: =IF(ISNUMBER(F102),Dashboard!$D$2-F102,"") -> -22 | R102: =IF(AND(OR(Dashboard!$P$1="All",A102=Dashboard!$P$1),OR(Dashboard!$P$2="All",J102=Dashboard!$P$2)),1,0) -> 1 | S102: =I102*R102 -> 324663 | T102: =IF(AND(ISNUMBER(Q102),Q102>0),S102,0) -> 0 | U102: =IF(OR(Dashboard!$P$3="All",AND(Dashboard!$P$3="Not due",Q102<0),AND(Dashboard!$P$3="Due in 10 days",Q102>=-10,Q102<=0),AND(Dashboard!$P$3="Due in 30 days",Q102>=-30,Q102<=0),AND(Dashboard!$P$3="Overdue 1–60 days",Q102>0,Q102<=60),AND(Dashboard!$P$3="Over 60 days",Q102>60),AND(Dashboard!$P$3="All overdue",Q102>0)),1,0) -> 1 | V102: =S102*U102 -> 324663 | W102: =IF(Q102>0,T102*Q102,0) -> 0 | X102: =IF(V102>0,COUNTIF($V$6:V102,">0"),"") -> 97 | Y102: =C102&"|"&D102 -> AR-00097|70000097 | AA102: ["CLIENT ZETA DEMO COMPANY", "AR-00097", "70000097", "2026-08-28"]
A103: Client Gamma (Offshore Energy) | B103: Demo Company 399 | C103: AR-00098 | D103: 70000098 | E103: 46172 | F103: 46224 | G103: 4021632000 | H103: 0 | I103: 4021632000 | J103: Sales Rep 3 | K103: Trading | L103: Project 008 | M103: Collection note 024 | Q103: =IF(ISNUMBER(F103),Dashboard!$D$2-F103,"") -> 76 | R103: =IF(AND(OR(Dashboard!$P$1="All",A103=Dashboard!$P$1),OR(Dashboard!$P$2="All",J103=Dashboard!$P$2)),1,0) -> 1 | S103: =I103*R103 -> 4021632000 | T103: =IF(AND(ISNUMBER(Q103),Q103>0),S103,0) -> 4021632000 | U103: =IF(OR(Dashboard!$P$3="All",AND(Dashboard!$P$3="Not due",Q103<0),AND(Dashboard!$P$3="Due in 10 days",Q103>=-10,Q103<=0),AND(Dashboard!$P$3="Due in 30 days",Q103>=-30,Q103<=0),AND(Dashboard!$P$3="Overdue 1–60 days",Q103>0,Q103<=60),AND(Dashboard!$P$3="Over 60 days",Q103>60),AND(Dashboard!$P$3="All overdue",Q103>0)),1,0) -> 1 | V103: =S103*U103 -> 4021632000 | W103: =IF(Q103>0,T103*Q103,0) -> 305644032000 | X103: =IF(V103>0,COUNTIF($V$6:V103,">0"),"") -> 98 | Y103: =C103&"|"&D103 -> AR-00098|70000098 | AA103: ["Demo Company 399", "AR-00098", "70000098", "2026-05-30"]

Sheet Prior AR
A1: Prior-period invoice ledger used for comparison. Public demonstration data.
D3: 46284
A5: Customer | B5: Legal Name | C5: Document Number | D5: Invoice Number | E5: Invoice Date | F5: Due Date | G5: Invoice Gross Amount | H5: Receipts Applied | I5: Outstanding Balance | J5: Sales Representative | K5: Business Type | L5: Project | M5: Description | N5: Promised Payment Date | O5: Last Contact | P5: Next Action | Q5: Days Overdue | R5: Customer / Staff Match | S5: Selected Balance | T5: Selected Overdue | U5: Status Match | V5: Filtered Balance | W5: Overdue Days × Balance
A6: Client Beta (Heavy Const.) | B6: CLIENT BETA HEAVY INDUSTRIAL CONSTRUCTION CORP | C6: AR-00001 | D6: 70000001 | E6: 46262 | F6: 46292 | G6: 78091274 | H6: 0 | I6: 78091274 | J6: Senior Sales Rep 1 | K6: Trading | L6: Project 009 | M6: Collection note 001 | Q6: =IF(ISNUMBER(F6),$D$3-F6,"") -> -8 | R6: =IF(AND(OR(Dashboard!$P$1="All",A6=Dashboard!$P$1),OR(Dashboard!$P$2="All",J6=Dashboard!$P$2)),1,0) -> 1 | S6: =I6*R6 -> 78091274 | T6: =IF(AND(ISNUMBER(Q6),Q6>0),S6,0) -> 0 | U6: =IF(OR(Dashboard!$P$3="All",AND(Dashboard!$P$3="Not due",Q6<0),AND(Dashboard!$P$3="Due in 10 days",Q6>=-10,Q6<=0),AND(Dashboard!$P$3="Due in 30 days",Q6>=-30,Q6<=0),AND(Dashboard!$P$3="Overdue 1–60 days",Q6>0,Q6<=60),AND(Dashboard!$P$3="Over 60 days",Q6>60),AND(Dashboard!$P$3="All overdue",Q6>0)),1,0) -> 1 | V6: =S6*U6 -> 78091274 | W6: =IF(Q6>0,T6*Q6,0) -> 0 | X6: =IF(V6>0,COUNTIF($V$6:V6,">0"),"") -> 1 | Y6: =C6&"|"&D6 -> AR-00001|70000001
A7: Client Beta (Heavy Const.) | B7: CLIENT BETA HEAVY INDUSTRIAL CONSTRUCTION CORP | C7: AR-00002 | D7: 70000002 | E7: 46262 | F7: 46292 | G7: 952138129 | H7: 0 | I7: 952138129 | J7: Senior Sales Rep 1 | K7: Trading | L7: Project 009 | M7: Collection note 001 | Q7: =IF(ISNUMBER(F7),$D$3-F7,"") -> -8 | R7: =IF(AND(OR(Dashboard!$P$1="All",A7=Dashboard!$P$1),OR(Dashboard!$P$2="All",J7=Dashboard!$P$2)),1,0) -> 1 | S7: =I7*R7 -> 952138129 | T7: =IF(AND(ISNUMBER(Q7),Q7>0),S7,0) -> 0 | U7: =IF(OR(Dashboard!$P$3="All",AND(Dashboard!$P$3="Not due",Q7<0),AND(Dashboard!$P$3="Due in 10 days",Q7>=-10,Q7<=0),AND(Dashboard!$P$3="Due in 30 days",Q7>=-30,Q7<=0),AND(Dashboard!$P$3="Overdue 1–60 days",Q7>0,Q7<=60),AND(Dashboard!$P$3="Over 60 days",Q7>60),AND(Dashboard!$P$3="All overdue",Q7>0)),1,0) -> 1 | V7: =S7*U7 -> 952138129 | W7: =IF(Q7>0,T7*Q7,0) -> 0 | X7: =IF(V7>0,COUNTIF($V$6:V7,">0"),"") -> 2 | Y7: =C7&"|"&D7 -> AR-00002|70000002
A8: Client Beta (Heavy Const.) | B8: CLIENT BETA HEAVY INDUSTRIAL CONSTRUCTION CORP | C8: AR-00003 | D8: 70000003 | E8: 46262 | F8: 46292 | G8: 572943345 | H8: 0 | I8: 572943345 | J8: Senior Sales Rep 1 | K8: Trading | L8: Project 009 | M8: Collection note 001 | Q8: =IF(ISNUMBER(F8),$D$3-F8,"") -> -8 | R8: =IF(AND(OR(Dashboard!$P$1="All",A8=Dashboard!$P$1),OR(Dashboard!$P$2="All",J8=Dashboard!$P$2)),1,0) -> 1 | S8: =I8*R8 -> 572943345 | T8: =IF(AND(ISNUMBER(Q8),Q8>0),S8,0) -> 0 | U8: =IF(OR(Dashboard!$P$3="All",AND(Dashboard!$P$3="Not due",Q8<0),AND(Dashboard!$P$3="Due in 10 days",Q8>=-10,Q8<=0),AND(Dashboard!$P$3="Due in 30 days",Q8>=-30,Q8<=0),AND(Dashboard!$P$3="Overdue 1–60 days",Q8>0,Q8<=60),AND(Dashboard!$P$3="Over 60 days",Q8>60),AND(Dashboard!$P$3="All overdue",Q8>0)),1,0) -> 1 | V8: =S8*U8 -> 572943345 | W8: =IF(Q8>0,T8*Q8,0) -> 0 | X8: =IF(V8>0,COUNTIF($V$6:V8,">0"),"") -> 3 | Y8: =C8&"|"&D8 -> AR-00003|70000003
A9: Client Alpha (Steel EPC) | B9: CLIENT ALPHA STEEL STRUCTURE CORPORATION | C9: AR-00099 | D9: 70000099 | E9: 46161 | F9: 46236 | G9: 673993453 | H9: 0 | I9: 673993453 | J9: Senior Sales Rep 2 | K9: Trading | L9: Project 010 | M9: Collection note 013 | Q9: =IF(ISNUMBER(F9),$D$3-F9,"") -> 48 | R9: =IF(AND(OR(Dashboard!$P$1="All",A9=Dashboard!$P$1),OR(Dashboard!$P$2="All",J9=Dashboard!$P$2)),1,0) -> 1 | S9: =I9*R9 -> 673993453 | T9: =IF(AND(ISNUMBER(Q9),Q9>0),S9,0) -> 673993453 | U9: =IF(OR(Dashboard!$P$3="All",AND(Dashboard!$P$3="Not due",Q9<0),AND(Dashboard!$P$3="Due in 10 days",Q9>=-10,Q9<=0),AND(Dashboard!$P$3="Due in 30 days",Q9>=-30,Q9<=0),AND(Dashboard!$P$3="Overdue 1–60 days",Q9>0,Q9<=60),AND(Dashboard!$P$3="Over 60 days",Q9>60),AND(Dashboard!$P$3="All overdue",Q9>0)),1,0) -> 1 | V9: =S9*U9 -> 673993453 | W9: =IF(Q9>0,T9*Q9,0) -> 32351685744 | X9: =IF(V9>0,COUNTIF($V$6:V9,">0"),"") -> 4 | Y9: =C9&"|"&D9 -> AR-00099|70000099
A10: Client Alpha (Steel EPC) | B10: CLIENT ALPHA STEEL STRUCTURE CORPORATION | C10: AR-00100 | D10: 70000100 | E10: 46167 | F10: 46242 | G10: 554101470 | H10: 451313869 | I10: 102787601 | J10: Senior Sales Rep 1 | K10: Trading | L10: Project 011 | M10: Collection note 006 | Q10: =IF(ISNUMBER(F10),$D$3-F10,"") -> 42 | R10: =IF(AND(OR(Dashboard!$P$1="All",A10=Dashboard!$P$1),OR(Dashboard!$P$2="All",J10=Dashboard!$P$2)),1,0) -> 1 | S10: =I10*R10 -> 102787601 | T10: =IF(AND(ISNUMBER(Q10),Q10>0),S10,0) -> 102787601 | U10: =IF(OR(Dashboard!$P$3="All",AND(Dashboard!$P$3="Not due",Q10<0),AND(Dashboard!$P$3="Due in 10 days",Q10>=-10,Q10<=0),AND(Dashboard!$P$3="Due in 30 days",Q10>=-30,Q10<=0),AND(Dashboard!$P$3="Overdue 1–60 days",Q10>0,Q10<=60),AND(Dashboard!$P$3="Over 60 days",Q10>60),AND(Dashboard!$P$3="All overdue",Q10>0)),1,0) -> 1 | V10: =S10*U10 -> 102787601 | W10: =IF(Q10>0,T10*Q10,0) -> 4317079242 | X10: =IF(V10>0,COUNTIF($V$6:V10,">0"),"") -> 5 | Y10: =C10&"|"&D10 -> AR-00100|70000100
A11: Client Alpha (Steel EPC) | B11: CLIENT ALPHA STEEL STRUCTURE CORPORATION | C11: AR-00101 | D11: 70000101 | E11: 46167 | F11: 46242 | G11: 34830763 | H11: 0 | I11: 34830763 | J11: Senior Sales Rep 1 | K11: Trading | L11: Project 011 | M11: Collection note 006 | Q11: =IF(ISNUMBER(F11),$D$3-F11,"") -> 42 | R11: =IF(AND(OR(Dashboard!$P$1="All",A11=Dashboard!$P$1),OR(Dashboard!$P$2="All",J11=Dashboard!$P$2)),1,0) -> 1 | S11: =I11*R11 -> 34830763 | T11: =IF(AND(ISNUMBER(Q11),Q11>0),S11,0) -> 34830763 | U11: =IF(OR(Dashboard!$P$3="All",AND(Dashboard!$P$3="Not due",Q11<0),AND(Dashboard!$P$3="Due in 10 days",Q11>=-10,Q11<=0),AND(Dashboard!$P$3="Due in 30 days",Q11>=-30,Q11<=0),AND(Dashboard!$P$3="Overdue 1–60 days",Q11>0,Q11<=60),AND(Dashboard!$P$3="Over 60 days",Q11>60),AND(Dashboard!$P$3="All overdue",Q11>0)),1,0) -> 1 | V11: =S11*U11 -> 34830763 | W11: =IF(Q11>0,T11*Q11,0) -> 1462892046 | X11: =IF(V11>0,COUNTIF($V$6:V11,">0"),"") -> 6 | Y11: =C11&"|"&D11 -> AR-00101|70000101
A12: Client Alpha (Steel EPC) | B12: CLIENT ALPHA STEEL STRUCTURE CORPORATION | C12: AR-00102 | D12: 70000102 | E12: 46167 | F12: 46242 | G12: 207794714 | H12: 0 | I12: 207794714 | J12: Senior Sales Rep 1 | K12: Trading | L12: Project 011 | M12: Collection note 006 | Q12: =IF(ISNUMBER(F12),$D$3-F12,"") -> 42 | R12: =IF(AND(OR(Dashboard!$P$1="All",A12=Dashboard!$P$1),OR(Dashboard!$P$2="All",J12=Dashboard!$P$2)),1,0) -> 1 | S12: =I12*R12 -> 207794714 | T12: =IF(AND(ISNUMBER(Q12),Q12>0),S12,0) -> 207794714 | U12: =IF(OR(Dashboard!$P$3="All",AND(Dashboard!$P$3="Not due",Q12<0),AND(Dashboard!$P$3="Due in 10 days",Q12>=-10,Q12<=0),AND(Dashboard!$P$3="Due in 30 days",Q12>=-30,Q12<=0),AND(Dashboard!$P$3="Overdue 1–60 days",Q12>0,Q12<=60),AND(Dashboard!$P$3="Over 60 days",Q12>60),AND(Dashboard!$P$3="All overdue",Q12>0)),1,0) -> 1 | V12: =S12*U12 -> 207794714 | W12: =IF(Q12>0,T12*Q12,0) -> 8727377988 | X12: =IF(V12>0,COUNTIF($V$6:V12,">0"),"") -> 7 | Y12: =C12&"|"&D12 -> AR-00102|70000102
A13: Client Alpha (Steel EPC) | B13: CLIENT ALPHA STEEL STRUCTURE CORPORATION | C13: AR-00103 | D13: 70000103 | E13: 46167 | F13: 46242 | G13: 505495089 | H13: 0 | I13: 505495089 | J13: Senior Sales Rep 2 | K13: Trading | L13: Project 010 | M13: Collection note 013 | Q13: =IF(ISNUMBER(F13),$D$3-F13,"") -> 42 | R13: =IF(AND(OR(Dashboard!$P$1="All",A13=Dashboard!$P$1),OR(Dashboard!$P$2="All",J13=Dashboard!$P$2)),1,0) -> 1 | S13: =I13*R13 -> 505495089 | T13: =IF(AND(ISNUMBER(Q13),Q13>0),S13,0) -> 505495089 | U13: =IF(OR(Dashboard!$P$3="All",AND(Dashboard!$P$3="Not due",Q13<0),AND(Dashboard!$P$3="Due in 10 days",Q13>=-10,Q13<=0),AND(Dashboard!$P$3="Due in 30 days",Q13>=-30,Q13<=0),AND(Dashboard!$P$3="Overdue 1–60 days",Q13>0,Q13<=60),AND(Dashboard!$P$3="Over 60 days",Q13>60),AND(Dashboard!$P$3="All overdue",Q13>0)),1,0) -> 1 | V13: =S13*U13 -> 505495089 | W13: =IF(Q13>0,T13*Q13,0) -> 21230793738 | X13: =IF(V13>0,COUNTIF($V$6:V13,">0"),"") -> 8 | Y13: =C13&"|"&D13 -> AR-00103|70000103
A14: Client Alpha (Steel EPC) | B14: CLIENT ALPHA STEEL STRUCTURE CORPORATION | C14: AR-00104 | D14: 70000104 | E14: 46171 | F14: 46246 | G14: 130289125 | H14: 0 | I14: 130289125 | J14: Senior Sales Rep 1 | K14: Trading | L14: Project 011 | M14: Collection note 006 | Q14: =IF(ISNUMBER(F14),$D$3-F14,"") -> 38 | R14: =IF(AND(OR(Dashboard!$P$1="All",A14=Dashboard!$P$1),OR(Dashboard!$P$2="All",J14=Dashboard!$P$2)),1,0) -> 1 | S14: =I14*R14 -> 130289125 | T14: =IF(AND(ISNUMBER(Q14),Q14>0),S14,0) -> 130289125 | U14: =IF(OR(Dashboard!$P$3="All",AND(Dashboard!$P$3="Not due",Q14<0),AND(Dashboard!$P$3="Due in 10 days",Q14>=-10,Q14<=0),AND(Dashboard!$P$3="Due in 30 days",Q14>=-30,Q14<=0),AND(Dashboard!$P$3="Overdue 1–60 days",Q14>0,Q14<=60),AND(Dashboard!$P$3="Over 60 days",Q14>60),AND(Dashboard!$P$3="All overdue",Q14>0)),1,0) -> 1 | V14: =S14*U14 -> 130289125 | W14: =IF(Q14>0,T14*Q14,0) -> 4950986750 | X14: =IF(V14>0,COUNTIF($V$6:V14,">0"),"") -> 9 | Y14: =C14&"|"&D14 -> AR-00104|70000104
A15: Client Alpha (Steel EPC) | B15: CLIENT ALPHA STEEL STRUCTURE CORPORATION | C15: AR-00105 | D15: 70000105 | E15: 46184 | F15: 46259 | G15: 505495089 | H15: 0 | I15: 505495089 | J15: Senior Sales Rep 2 | K15: Trading | L15: Project 010 | M15: Collection note 013 | Q15: =IF(ISNUMBER(F15),$D$3-F15,"") -> 25 | R15: =IF(AND(OR(Dashboard!$P$1="All",A15=Dashboard!$P$1),OR(Dashboard!$P$2="All",J15=Dashboard!$P$2)),1,0) -> 1 | S15: =I15*R15 -> 505495089 | T15: =IF(AND(ISNUMBER(Q15),Q15>0),S15,0) -> 505495089 | U15: =IF(OR(Dashboard!$P$3="All",AND(Dashboard!$P$3="Not due",Q15<0),AND(Dashboard!$P$3="Due in 10 days",Q15>=-10,Q15<=0),AND(Dashboard!$P$3="Due in 30 days",Q15>=-30,Q15<=0),AND(Dashboard!$P$3="Overdue 1–60 days",Q15>0,Q15<=60),AND(Dashboard!$P$3="Over 60 days",Q15>60),AND(Dashboard!$P$3="All overdue",Q15>0)),1,0) -> 1 | V15: =S15*U15 -> 505495089 | W15: =IF(Q15>0,T15*Q15,0) -> 12637377225 | X15: =IF(V15>0,COUNTIF($V$6:V15,">0"),"") -> 10 | Y15: =C15&"|"&D15 -> AR-00105|70000105
A16: Client Alpha (Steel EPC) | B16: CLIENT ALPHA STEEL STRUCTURE CORPORATION | C16: AR-00009 | D16: 70000009 | E16: 46189 | F16: 46264 | G16: 97367488 | H16: 0 | I16: 97367488 | J16: Senior Sales Rep 1 | K16: Trading | L16: Project 012 | M16: Collection note 005 | Q16: =IF(ISNUMBER(F16),$D$3-F16,"") -> 20 | R16: =IF(AND(OR(Dashboard!$P$1="All",A16=Dashboard!$P$1),OR(Dashboard!$P$2="All",J16=Dashboard!$P$2)),1,0) -> 1 | S16: =I16*R16 -> 97367488 | T16: =IF(AND(ISNUMBER(Q16),Q16>0),S16,0) -> 97367488 | U16: =IF(OR(Dashboard!$P$3="All",AND(Dashboard!$P$3="Not due",Q16<0),AND(Dashboard!$P$3="Due in 10 days",Q16>=-10,Q16<=0),AND(Dashboard!$P$3="Due in 30 days",Q16>=-30,Q16<=0),AND(Dashboard!$P$3="Overdue 1–60 days",Q16>0,Q16<=60),AND(Dashboard!$P$3="Over 60 days",Q16>60),AND(Dashboard!$P$3="All overdue",Q16>0)),1,0) -> 1 | V16: =S16*U16 -> 97367488 | W16: =IF(Q16>0,T16*Q16,0) -> 1947349760 | X16: =IF(V16>0,COUNTIF($V$6:V16,">0"),"") -> 11 | Y16: =C16&"|"&D16 -> AR-00009|70000009
A17: Client Alpha (Steel EPC) | B17: CLIENT ALPHA STEEL STRUCTURE CORPORATION | C17: AR-00010 | D17: 70000010 | E17: 46191 | F17: 46266 | G17: 483414781 | H17: 0 | I17: 483414781 | J17: Senior Sales Rep 1 | K17: Trading | L17: Project 011 | M17: Collection note 006 | Q17: =IF(ISNUMBER(F17),$D$3-F17,"") -> 18 | R17: =IF(AND(OR(Dashboard!$P$1="All",A17=Dashboard!$P$1),OR(Dashboard!$P$2="All",J17=Dashboard!$P$2)),1,0) -> 1 | S17: =I17*R17 -> 483414781 | T17: =IF(AND(ISNUMBER(Q17),Q17>0),S17,0) -> 483414781 | U17: =IF(OR(Dashboard!$P$3="All",AND(Dashboard!$P$3="Not due",Q17<0),AND(Dashboard!$P$3="Due in 10 days",Q17>=-10,Q17<=0),AND(Dashboard!$P$3="Due in 30 days",Q17>=-30,Q17<=0),AND(Dashboard!$P$3="Overdue 1–60 days",Q17>0,Q17<=60),AND(Dashboard!$P$3="Over 60 days",Q17>60),AND(Dashboard!$P$3="All overdue",Q17>0)),1,0) -> 1 | V17: =S17*U17 -> 483414781 | W17: =IF(Q17>0,T17*Q17,0) -> 8701466058 | X17: =IF(V17>0,COUNTIF($V$6:V17,">0"),"") -> 12 | Y17: =C17&"|"&D17 -> AR-00010|70000010
... A84: Client Gamma (Offshore Energy) | B84: Demo Company 399 | C84: AR-00098 | D84: 70000098 | E84: 46172 | F84: 46217 | G84: 4099303796 | H84: 0 | I84: 4099303796 | J84: Sales Rep 3 | K84: Trading | L84: Project 017 | M84: Collection note 024 | Q84: =IF(ISNUMBER(F84),$D$3-F84,"") -> 67 | R84: =IF(AND(OR(Dashboard!$P$1="All",A84=Dashboard!$P$1),OR(Dashboard!$P$2="All",J84=Dashboard!$P$2)),1,0) -> 1 | S84: =I84*R84 -> 4099303796 | T84: =IF(AND(ISNUMBER(Q84),Q84>0),S84,0) -> 4099303796 | U84: =IF(OR(Dashboard!$P$3="All",AND(Dashboard!$P$3="Not due",Q84<0),AND(Dashboard!$P$3="Due in 10 days",Q84>=-10,Q84<=0),AND(Dashboard!$P$3="Due in 30 days",Q84>=-30,Q84<=0),AND(Dashboard!$P$3="Overdue 1–60 days",Q84>0,Q84<=60),AND(Dashboard!$P$3="Over 60 days",Q84>60),AND(Dashboard!$P$3="All overdue",Q84>0)),1,0) -> 1 | V84: =S84*U84 -> 4099303796 | W84: =IF(Q84>0,T84*Q84,0) -> 274653354332 | X84: =IF(V84>0,COUNTIF($V$6:V84,">0"),"") -> 79 | Y84: =C84&"|"&D84 -> AR-00098|70000098
A85: Client Zeta (Building Tech) | B85: CLIENT ZETA BUILDING ENVELOPE SOLUTIONS | C85: AR-00097 | D85: 70000097 | E85: 46262 | F85: 46322 | G85: 333943 | H85: 0 | I85: 333943 | J85: Sales Rep 5 | K85: Trading | M85: Collection note 023 | Q85: =IF(ISNUMBER(F85),$D$3-F85,"") -> -38 | R85: =IF(AND(OR(Dashboard!$P$1="All",A85=Dashboard!$P$1),OR(Dashboard!$P$2="All",J85=Dashboard!$P$2)),1,0) -> 1 | S85: =I85*R85 -> 333943 | T85: =IF(AND(ISNUMBER(Q85),Q85>0),S85,0) -> 0 | U85: =IF(OR(Dashboard!$P$3="All",AND(Dashboard!$P$3="Not due",Q85<0),AND(Dashboard!$P$3="Due in 10 days",Q85>=-10,Q85<=0),AND(Dashboard!$P$3="Due in 30 days",Q85>=-30,Q85<=0),AND(Dashboard!$P$3="Overdue 1–60 days",Q85>0,Q85<=60),AND(Dashboard!$P$3="Over 60 days",Q85>60),AND(Dashboard!$P$3="All overdue",Q85>0)),1,0) -> 1 | V85: =S85*U85 -> 333943 | W85: =IF(Q85>0,T85*Q85,0) -> 0 | X85: =IF(V85>0,COUNTIF($V$6:V85,">0"),"") -> 80 | Y85: =C85&"|"&D85 -> AR-00097|70000097

Sheet Analysis
A1: ACCOUNTS RECEIVABLE RECONCILIATION & RISK ANALYSIS | R1: 0 | S1: 0 | Z1: 0 | AA1: 0 | AH1: 0 | AI1: 0
R2: =-COS(PI()*B16) -> -0.93739426 | S2: =SIN(PI()*B16) -> 0.34827002 | Z2: =-COS(PI()*B17) -> -0.9695375 | AA2: =SIN(PI()*B17) -> 0.24494294 | AH2: =-COS(PI()*B18) -> -0.8235326 | AI2: =SIN(PI()*B18) -> 0.56726895
R3: 0 | S3: 0 | Z3: 0 | AA3: 0 | AH3: 0 | AI3: 0
A5: KPI Metric | B5: Current Cycle | C5: Prior Cycle | D5: Variance | E5: Change (%) | R5: -1 | S5: =SQRT(MAX(0,1-R5^2)) -> 0 | T5: =IF(ISNUMBER($B$16),IF(AND($C$16=1,R5<=-COS(PI()*$B$16)),S5,NA()),NA()) -> 0 | U5: =IF(ISNUMBER($B$16),IF(AND($C$16=2,R5<=-COS(PI()*$B$16)),S5,NA()),NA()) -> #N/A | V5: =IF(ISNUMBER($B$16),IF(AND($C$16=3,R5<=-COS(PI()*$B$16)),S5,NA()),NA()) -> #N/A | W5: =IF(ISNUMBER($B$16),IF(AND($C$16=4,R5<=-COS(PI()*$B$16)),S5,NA()),NA()) -> #N/A | X5: =IF(ISNUMBER($B$16),IF(AND($C$16=5,R5<=-COS(PI()*$B$16)),S5,NA()),NA()) -> #N/A | Y5: =IF(ISNUMBER($B$16),IF(AND(ISNUMBER($B$16),R5>=MIN(0,$R$2),R5<=MAX(0,$R$2)),IF($R$2=0,0,R5/$R$2*$S$2),NA()),NA()) -> #N/A | Z5: -1 | AA5: =SQRT(MAX(0,1-Z5^2)) -> 0 | AB5: =IF(ISNUMBER($B$17),IF(AND($C$17=1,Z5<=-COS(PI()*$B$17)),AA5,NA()),NA()) -> 0 | AC5: =IF(ISNUMBER($B$17),IF(AND($C$17=2,Z5<=-COS(PI()*$B$17)),AA5,NA()),NA()) -> #N/A | AD5: =IF(ISNUMBER($B$17),IF(AND($C$17=3,Z5<=-COS(PI()*$B$17)),AA5,NA()),NA()) -> #N/A | AE5: =IF(ISNUMBER($B$17),IF(AND($C$17=4,Z5<=-COS(PI()*$B$17)),AA5,NA()),NA()) -> #N/A | AF5: =IF(ISNUMBER($B$17),IF(AND($C$17=5,Z5<=-COS(PI()*$B$17)),AA5,NA()),NA()) -> #N/A | AG5: =IF(ISNUMBER($B$17),IF(AND(ISNUMBER($B$17),Z5>=MIN(0,$Z$2),Z5<=MAX(0,$Z$2)),IF($Z$2=0,0,Z5/$Z$2*$AA$2),NA()),NA()) -> #N/A | AH5: -1 | AI5: =SQRT(MAX(0,1-AH5^2)) -> 0 | AJ5: =IF(ISNUMBER($B$18),IF(AND($C$18=1,AH5<=-COS(PI()*$B$18)),AI5,NA()),NA()) -> 0 | AK5: =IF(ISNUMBER($B$18),IF(AND($C$18=2,AH5<=-COS(PI()*$B$18)),AI5,NA()),NA()) -> #N/A | AL5: =IF(ISNUMBER($B$18),IF(AND($C$18=3,AH5<=-COS(PI()*$B$18)),AI5,NA()),NA()) -> #N/A | AM5: =IF(ISNUMBER($B$18),IF(AND($C$18=4,AH5<=-COS(PI()*$B$18)),AI5,NA()),NA()) -> #N/A | AN5: =IF(ISNUMBER($B$18),IF(AND($C$18=5,AH5<=-COS(PI()*$B$18)),AI5,NA()),NA()) -> #N/A | AO5: =IF(ISNUMBER($B$18),IF(AND(ISNUMBER($B$18),AH5>=MIN(0,$AH$2),AH5<=MAX(0,$AH$2)),IF($AH$2=0,0,AH5/$AH$2*$AI$2),NA()),NA()) -> #N/A
A6: Total Outstanding AR | B6: =SUM('Current AR'!$S$6:$S$103) -> 51055875000 | C6: =SUM('Prior AR'!$S$6:$S$85) -> 33932519997 | D6: =IF(AND(ISNUMBER(B6),ISNUMBER(C6)),B6-C6,"n.a.") -> 17123355003 | E6: =IF(AND(ISNUMBER(C6),C6<>0,ISNUMBER(D6)),D6/C6,"n.a.") -> 0.50462963 | R6: -0.98 | S6: =SQRT(MAX(0,1-R6^2)) -> 0.19899749 | T6: =IF(ISNUMBER($B$16),IF(AND($C$16=1,R6<=-COS(PI()*$B$16)),S6,NA()),NA()) -> 0.19899749 | U6: =IF(ISNUMBER($B$16),IF(AND($C$16=2,R6<=-COS(PI()*$B$16)),S6,NA()),NA()) -> #N/A | V6: =IF(ISNUMBER($B$16),IF(AND($C$16=3,R6<=-COS(PI()*$B$16)),S6,NA()),NA()) -> #N/A | W6: =IF(ISNUMBER($B$16),IF(AND($C$16=4,R6<=-COS(PI()*$B$16)),S6,NA()),NA()) -> #N/A | X6: =IF(ISNUMBER($B$16),IF(AND($C$16=5,R6<=-COS(PI()*$B$16)),S6,NA()),NA()) -> #N/A | Y6: =IF(ISNUMBER($B$16),IF(AND(ISNUMBER($B$16),R6>=MIN(0,$R$2),R6<=MAX(0,$R$2)),IF($R$2=0,0,R6/$R$2*$S$2),NA()),NA()) -> #N/A | Z6: -0.98 | AA6: =SQRT(MAX(0,1-Z6^2)) -> 0.19899749 | AB6: =IF(ISNUMBER($B$17),IF(AND($C$17=1,Z6<=-COS(PI()*$B$17)),AA6,NA()),NA()) -> 0.19899749 | AC6: =IF(ISNUMBER($B$17),IF(AND($C$17=2,Z6<=-COS(PI()*$B$17)),AA6,NA()),NA()) -> #N/A | AD6: =IF(ISNUMBER($B$17),IF(AND($C$17=3,Z6<=-COS(PI()*$B$17)),AA6,NA()),NA()) -> #N/A | AE6: =IF(ISNUMBER($B$17),IF(AND($C$17=4,Z6<=-COS(PI()*$B$17)),AA6,NA()),NA()) -> #N/A | AF6: =IF(ISNUMBER($B$17),IF(AND($C$17=5,Z6<=-COS(PI()*$B$17)),AA6,NA()),NA()) -> #N/A | AG6: =IF(ISNUMBER($B$17),IF(AND(ISNUMBER($B$17),Z6>=MIN(0,$Z$2),Z6<=MAX(0,$Z$2)),IF($Z$2=0,0,Z6/$Z$2*$AA$2),NA()),NA()) -> #N/A | AH6: -0.98 | AI6: =SQRT(MAX(0,1-AH6^2)) -> 0.19899749 | AJ6: =IF(ISNUMBER($B$18),IF(AND($C$18=1,AH6<=-COS(PI()*$B$18)),AI6,NA()),NA()) -> 0.19899749 | AK6: =IF(ISNUMBER($B$18),IF(AND($C$18=2,AH6<=-COS(PI()*$B$18)),AI6,NA()),NA()) -> #N/A | AL6: =IF(ISNUMBER($B$18),IF(AND($C$18=3,AH6<=-COS(PI()*$B$18)),AI6,NA()),NA()) -> #N/A | AM6: =IF(ISNUMBER($B$18),IF(AND($C$18=4,AH6<=-COS(PI()*$B$18)),AI6,NA()),NA()) -> #N/A | AN6: =IF(ISNUMBER($B$18),IF(AND($C$18=5,AH6<=-COS(PI()*$B$18)),AI6,NA()),NA()) -> #N/A | AO6: =IF(ISNUMBER($B$18),IF(AND(ISNUMBER($B$18),AH6>=MIN(0,$AH$2),AH6<=MAX(0,$AH$2)),IF($AH$2=0,0,AH6/$AH$2*$AI$2),NA()),NA()) -> #N/A
A7: Overdue Debt (1–60 Days) | B7: =SUMIFS('Current AR'!$S$6:$S$103,'Current AR'!$Q$6:$Q$103,">0",'Current AR'!$Q$6:$Q$103,"<=60") -> 5781096000 | C7: =SUMIFS('Prior AR'!$S$6:$S$85,'Prior AR'!$Q$6:$Q$85,">0",'Prior AR'!$Q$6:$Q$85,"<=60") -> 5829261123 | D7: =IF(AND(ISNUMBER(B7),ISNUMBER(C7)),B7-C7,"n.a.") -> -48165123 | E7: =IF(AND(ISNUMBER(C7),C7<>0,ISNUMBER(D7)),D7/C7,"n.a.") -> -0.0082626463 | R7: -0.96 | S7: =SQRT(MAX(0,1-R7^2)) -> 0.28 | T7: =IF(ISNUMBER($B$16),IF(AND($C$16=1,R7<=-COS(PI()*$B$16)),S7,NA()),NA()) -> 0.28 | U7: =IF(ISNUMBER($B$16),IF(AND($C$16=2,R7<=-COS(PI()*$B$16)),S7,NA()),NA()) -> #N/A | V7: =IF(ISNUMBER($B$16),IF(AND($C$16=3,R7<=-COS(PI()*$B$16)),S7,NA()),NA()) -> #N/A | W7: =IF(ISNUMBER($B$16),IF(AND($C$16=4,R7<=-COS(PI()*$B$16)),S7,NA()),NA()) -> #N/A | X7: =IF(ISNUMBER($B$16),IF(AND($C$16=5,R7<=-COS(PI()*$B$16)),S7,NA()),NA()) -> #N/A | Y7: =IF(ISNUMBER($B$16),IF(AND(ISNUMBER($B$16),R7>=MIN(0,$R$2),R7<=MAX(0,$R$2)),IF($R$2=0,0,R7/$R$2*$S$2),NA()),NA()) -> #N/A | Z7: -0.96 | AA7: =SQRT(MAX(0,1-Z7^2)) -> 0.28 | AB7: =IF(ISNUMBER($B$17),IF(AND($C$17=1,Z7<=-COS(PI()*$B$17)),AA7,NA()),NA()) -> #N/A | AC7: =IF(ISNUMBER($B$17),IF(AND($C$17=2,Z7<=-COS(PI()*$B$17)),AA7,NA()),NA()) -> #N/A | AD7: =IF(ISNUMBER($B$17),IF(AND($C$17=3,Z7<=-COS(PI()*$B$17)),AA7,NA()),NA()) -> #N/A | AE7: =IF(ISNUMBER($B$17),IF(AND($C$17=4,Z7<=-COS(PI()*$B$17)),AA7,NA()),NA()) -> #N/A | AF7: =IF(ISNUMBER($B$17),IF(AND($C$17=5,Z7<=-COS(PI()*$B$17)),AA7,NA()),NA()) -> #N/A | AG7: =IF(ISNUMBER($B$17),IF(AND(ISNUMBER($B$17),Z7>=MIN(0,$Z$2),Z7<=MAX(0,$Z$2)),IF($Z$2=0,0,Z7/$Z$2*$AA$2),NA()),NA()) -> 0.24253339 | AH7: -0.96 | AI7: =SQRT(MAX(0,1-AH7^2)) -> 0.28 | AJ7: =IF(ISNUMBER($B$18),IF(AND($C$18=1,AH7<=-COS(PI()*$B$18)),AI7,NA()),NA()) -> 0.28 | AK7: =IF(ISNUMBER($B$18),IF(AND($C$18=2,AH7<=-COS(PI()*$B$18)),AI7,NA()),NA()) -> #N/A | AL7: =IF(ISNUMBER($B$18),IF(AND($C$18=3,AH7<=-COS(PI()*$B$18)),AI7,NA()),NA()) -> #N/A | AM7: =IF(ISNUMBER($B$18),IF(AND($C$18=4,AH7<=-COS(PI()*$B$18)),AI7,NA()),NA()) -> #N/A | AN7: =IF(ISNUMBER($B$18),IF(AND($C$18=5,AH7<=-COS(PI()*$B$18)),AI7,NA()),NA()) -> #N/A | AO7: =IF(ISNUMBER($B$18),IF(AND(ISNUMBER($B$18),AH7>=MIN(0,$AH$2),AH7<=MAX(0,$AH$2)),IF($AH$2=0,0,AH7/$AH$2*$AI$2),NA()),NA()) -> #N/A
A8: Doubtful Debt (>60 Days) | B8: =SUMIFS('Current AR'!$S$6:$S$103,'Current AR'!$Q$6:$Q$103,">60") -> 4021632000 | C8: =SUMIFS('Prior AR'!$S$6:$S$85,'Prior AR'!$Q$6:$Q$85,">60") -> 4099303796 | D8: =IF(AND(ISNUMBER(B8),ISNUMBER(C8)),B8-C8,"n.a.") -> -77671796 | E8: =IF(AND(ISNUMBER(C8),C8<>0,ISNUMBER(D8)),D8/C8,"n.a.") -> -0.018947558 | R8: -0.94 | S8: =SQRT(MAX(0,1-R8^2)) -> 0.34117444 | T8: =IF(ISNUMBER($B$16),IF(AND($C$16=1,R8<=-COS(PI()*$B$16)),S8,NA()),NA()) -> 0.34117444 | U8: =IF(ISNUMBER($B$16),IF(AND($C$16=2,R8<=-COS(PI()*$B$16)),S8,NA()),NA()) -> #N/A | V8: =IF(ISNUMBER($B$16),IF(AND($C$16=3,R8<=-COS(PI()*$B$16)),S8,NA()),NA()) -> #N/A | W8: =IF(ISNUMBER($B$16),IF(AND($C$16=4,R8<=-COS(PI()*$B$16)),S8,NA()),NA()) -> #N/A | X8: =IF(ISNUMBER($B$16),IF(AND($C$16=5,R8<=-COS(PI()*$B$16)),S8,NA()),NA()) -> #N/A | Y8: =IF(ISNUMBER($B$16),IF(AND(ISNUMBER($B$16),R8>=MIN(0,$R$2),R8<=MAX(0,$R$2)),IF($R$2=0,0,R8/$R$2*$S$2),NA()),NA()) -> #N/A | Z8: -0.94 | AA8: =SQRT(MAX(0,1-Z8^2)) -> 0.34117444 | AB8: =IF(ISNUMBER($B$17),IF(AND($C$17=1,Z8<=-COS(PI()*$B$17)),AA8,NA()),NA()) -> #N/A | AC8: =IF(ISNUMBER($B$17),IF(AND($C$17=2,Z8<=-COS(PI()*$B$17)),AA8,NA()),NA()) -> #N/A | AD8: =IF(ISNUMBER($B$17),IF(AND($C$17=3,Z8<=-COS(PI()*$B$17)),AA8,NA()),NA()) -> #N/A | AE8: =IF(ISNUMBER($B$17),IF(AND($C$17=4,Z8<=-COS(PI()*$B$17)),AA8,NA()),NA()) -> #N/A | AF8: =IF(ISNUMBER($B$17),IF(AND($C$17=5,Z8<=-COS(PI()*$B$17)),AA8,NA()),NA()) -> #N/A | AG8: =IF(ISNUMBER($B$17),IF(AND(ISNUMBER($B$17),Z8>=MIN(0,$Z$2),Z8<=MAX(0,$Z$2)),IF($Z$2=0,0,Z8/$Z$2*$AA$2),NA()),NA()) -> 0.23748062 | AH8: -0.94 | AI8: =SQRT(MAX(0,1-AH8^2)) -> 0.34117444 | AJ8: =IF(ISNUMBER($B$18),IF(AND($C$18=1,AH8<=-COS(PI()*$B$18)),AI8,NA()),NA()) -> 0.34117444 | AK8: =IF(ISNUMBER($B$18),IF(AND($C$18=2,AH8<=-COS(PI()*$B$18)),AI8,NA()),NA()) -> #N/A | AL8: =IF(ISNUMBER($B$18),IF(AND($C$18=3,AH8<=-COS(PI()*$B$18)),AI8,NA()),NA()) -> #N/A | AM8: =IF(ISNUMBER($B$18),IF(AND($C$18=4,AH8<=-COS(PI()*$B$18)),AI8,NA()),NA()) -> #N/A | AN8: =IF(ISNUMBER($B$18),IF(AND($C$18=5,AH8<=-COS(PI()*$B$18)),AI8,NA()),NA()) -> #N/A | AO8: =IF(ISNUMBER($B$18),IF(AND(ISNUMBER($B$18),AH8>=MIN(0,$AH$2),AH8<=MAX(0,$AH$2)),IF($AH$2=0,0,AH8/$AH$2*$AI$2),NA()),NA()) -> #N/A
A9: Total Overdue & Doubtful | B9: =B7+B8 -> 9802728000 | C9: =C7+C8 -> 9928564919 | D9: =IF(AND(ISNUMBER(B9),ISNUMBER(C9)),B9-C9,"n.a.") -> -125836919 | E9: =IF(AND(ISNUMBER(C9),C9<>0,ISNUMBER(D9)),D9/C9,"n.a.") -> -0.01267423 | R9: -0.92 | S9: =SQRT(MAX(0,1-R9^2)) -> 0.39191836 | T9: =IF(ISNUMBER($B$16),IF(AND($C$16=1,R9<=-COS(PI()*$B$16)),S9,NA()),NA()) -> #N/A | U9: =IF(ISNUMBER($B$16),IF(AND($C$16=2,R9<=-COS(PI()*$B$16)),S9,NA()),NA()) -> #N/A | V9: =IF(ISNUMBER($B$16),IF(AND($C$16=3,R9<=-COS(PI()*$B$16)),S9,NA()),NA()) -> #N/A | W9: =IF(ISNUMBER($B$16),IF(AND($C$16=4,R9<=-COS(PI()*$B$16)),S9,NA()),NA()) -> #N/A | X9: =IF(ISNUMBER($B$16),IF(AND($C$16=5,R9<=-COS(PI()*$B$16)),S9,NA()),NA()) -> #N/A | Y9: =IF(ISNUMBER($B$16),IF(AND(ISNUMBER($B$16),R9>=MIN(0,$R$2),R9<=MAX(0,$R$2)),IF($R$2=0,0,R9/$R$2*$S$2),NA()),NA()) -> 0.34180754 | Z9: -0.92 | AA9: =SQRT(MAX(0,1-Z9^2)) -> 0.39191836 | AB9: =IF(ISNUMBER($B$17),IF(AND($C$17=1,Z9<=-COS(PI()*$B$17)),AA9,NA()),NA()) -> #N/A | AC9: =IF(ISNUMBER($B$17),IF(AND($C$17=2,Z9<=-COS(PI()*$B$17)),AA9,NA()),NA()) -> #N/A | AD9: =IF(ISNUMBER($B$17),IF(AND($C$17=3,Z9<=-COS(PI()*$B$17)),AA9,NA()),NA()) -> #N/A | AE9: =IF(ISNUMBER($B$17),IF(AND($C$17=4,Z9<=-COS(PI()*$B$17)),AA9,NA()),NA()) -> #N/A | AF9: =IF(ISNUMBER($B$17),IF(AND($C$17=5,Z9<=-COS(PI()*$B$17)),AA9,NA()),NA()) -> #N/A | AG9: =IF(ISNUMBER($B$17),IF(AND(ISNUMBER($B$17),Z9>=MIN(0,$Z$2),Z9<=MAX(0,$Z$2)),IF($Z$2=0,0,Z9/$Z$2*$AA$2),NA()),NA()) -> 0.23242784 | AH9: -0.92 | AI9: =SQRT(MAX(0,1-AH9^2)) -> 0.39191836 | AJ9: =IF(ISNUMBER($B$18),IF(AND($C$18=1,AH9<=-COS(PI()*$B$18)),AI9,NA()),NA()) -> 0.39191836 | AK9: =IF(ISNUMBER($B$18),IF(AND($C$18=2,AH9<=-COS(PI()*$B$18)),AI9,NA()),NA()) -> #N/A | AL9: =IF(ISNUMBER($B$18),IF(AND($C$18=3,AH9<=-COS(PI()*$B$18)),AI9,NA()),NA()) -> #N/A | AM9: =IF(ISNUMBER($B$18),IF(AND($C$18=4,AH9<=-COS(PI()*$B$18)),AI9,NA()),NA()) -> #N/A | AN9: =IF(ISNUMBER($B$18),IF(AND($C$18=5,AH9<=-COS(PI()*$B$18)),AI9,NA()),NA()) -> #N/A | AO9: =IF(ISNUMBER($B$18),IF(AND(ISNUMBER($B$18),AH9>=MIN(0,$AH$2),AH9<=MAX(0,$AH$2)),IF($AH$2=0,0,AH9/$AH$2*$AI$2),NA()),NA()) -> #N/A
A10: Total Overdue Ratio | B10: =IF(B6=0,"n.a.",B9/B6) -> 0.192 | C10: =IF(C6=0,"n.a.",C9/C6) -> 0.29259733 | D10: =IF(AND(ISNUMBER(B10),ISNUMBER(C10)),B10-C10,"n.a.") -> -0.10059733 | E10: =IF(AND(ISNUMBER(C10),C10<>0,ISNUMBER(D10)),D10/C10,"n.a.") -> -0.3438081 | R10: -0.9 | S10: =SQRT(MAX(0,1-R10^2)) -> 0.43588989 | T10: =IF(ISNUMBER($B$16),IF(AND($C$16=1,R10<=-COS(PI()*$B$16)),S10,NA()),NA()) -> #N/A | U10: =IF(ISNUMBER($B$16),IF(AND($C$16=2,R10<=-COS(PI()*$B$16)),S10,NA()),NA()) -> #N/A | V10: =IF(ISNUMBER($B$16),IF(AND($C$16=3,R10<=-COS(PI()*$B$16)),S10,NA()),NA()) -> #N/A | W10: =IF(ISNUMBER($B$16),IF(AND($C$16=4,R10<=-COS(PI()*$B$16)),S10,NA()),NA()) -> #N/A | X10: =IF(ISNUMBER($B$16),IF(AND($C$16=5,R10<=-COS(PI()*$B$16)),S10,NA()),NA()) -> #N/A | Y10: =IF(ISNUMBER($B$16),IF(AND(ISNUMBER($B$16),R10>=MIN(0,$R$2),R10<=MAX(0,$R$2)),IF($R$2=0,0,R10/$R$2*$S$2),NA()),NA()) -> 0.33437694 | Z10: -0.9 | AA10: =SQRT(MAX(0,1-Z10^2)) -> 0.43588989 | AB10: =IF(ISNUMBER($B$17),IF(AND($C$17=1,Z10<=-COS(PI()*$B$17)),AA10,NA()),NA()) -> #N/A | AC10: =IF(ISNUMBER($B$17),IF(AND($C$17=2,Z10<=-COS(PI()*$B$17)),AA10,NA()),NA()) -> #N/A | AD10: =IF(ISNUMBER($B$17),IF(AND($C$17=3,Z10<=-COS(PI()*$B$17)),AA10,NA()),NA()) -> #N/A | AE10: =IF(ISNUMBER($B$17),IF(AND($C$17=4,Z10<=-COS(PI()*$B$17)),AA10,NA()),NA()) -> #N/A | AF10: =IF(ISNUMBER($B$17),IF(AND($C$17=5,Z10<=-COS(PI()*$B$17)),AA10,NA()),NA()) -> #N/A | AG10: =IF(ISNUMBER($B$17),IF(AND(ISNUMBER($B$17),Z10>=MIN(0,$Z$2),Z10<=MAX(0,$Z$2)),IF($Z$2=0,0,Z10/$Z$2*$AA$2),NA()),NA()) -> 0.22737506 | AH10: -0.9 | AI10: =SQRT(MAX(0,1-AH10^2)) -> 0.43588989 | AJ10: =IF(ISNUMBER($B$18),IF(AND($C$18=1,AH10<=-COS(PI()*$B$18)),AI10,NA()),NA()) -> 0.43588989 | AK10: =IF(ISNUMBER($B$18),IF(AND($C$18=2,AH10<=-COS(PI()*$B$18)),AI10,NA()),NA()) -> #N/A | AL10: =IF(ISNUMBER($B$18),IF(AND($C$18=3,AH10<=-COS(PI()*$B$18)),AI10,NA()),NA()) -> #N/A | AM10: =IF(ISNUMBER($B$18),IF(AND($C$18=4,AH10<=-COS(PI()*$B$18)),AI10,NA()),NA()) -> #N/A | AN10: =IF(ISNUMBER($B$18),IF(AND($C$18=5,AH10<=-COS(PI()*$B$18)),AI10,NA()),NA()) -> #N/A | AO10: =IF(ISNUMBER($B$18),IF(AND(ISNUMBER($B$18),AH10>=MIN(0,$AH$2),AH10<=MAX(0,$AH$2)),IF($AH$2=0,0,AH10/$AH$2*$AI$2),NA()),NA()) -> #N/A
A11: Due within 10 Days | B11: =SUMIFS('Current AR'!$S$6:$S$103,'Current AR'!$Q$6:$Q$103,">=-10",'Current AR'!$Q$6:$Q$103,"<=0") -> 3810796638 | C11: =SUMIFS('Prior AR'!$S$6:$S$85,'Prior AR'!$Q$6:$Q$85,">=-10",'Prior AR'!$Q$6:$Q$85,"<=0") -> 3345665769 | D11: =IF(AND(ISNUMBER(B11),ISNUMBER(C11)),B11-C11,"n.a.") -> 465130869 | E11: =IF(AND(ISNUMBER(C11),C11<>0,ISNUMBER(D11)),D11/C11,"n.a.") -> 0.13902491 | R11: -0.88 | S11: =SQRT(MAX(0,1-R11^2)) -> 0.47497368 | T11: =IF(ISNUMBER($B$16),IF(AND($C$16=1,R11<=-COS(PI()*$B$16)),S11,NA()),NA()) -> #N/A | U11: =IF(ISNUMBER($B$16),IF(AND($C$16=2,R11<=-COS(PI()*$B$16)),S11,NA()),NA()) -> #N/A | V11: =IF(ISNUMBER($B$16),IF(AND($C$16=3,R11<=-COS(PI()*$B$16)),S11,NA()),NA()) -> #N/A | W11: =IF(ISNUMBER($B$16),IF(AND($C$16=4,R11<=-COS(PI()*$B$16)),S11,NA()),NA()) -> #N/A | X11: =IF(ISNUMBER($B$16),IF(AND($C$16=5,R11<=-COS(PI()*$B$16)),S11,NA()),NA()) -> #N/A | Y11: =IF(ISNUMBER($B$16),IF(AND(ISNUMBER($B$16),R11>=MIN(0,$R$2),R11<=MAX(0,$R$2)),IF($R$2=0,0,R11/$R$2*$S$2),NA()),NA()) -> 0.32694634 | Z11: -0.88 | AA11: =SQRT(MAX(0,1-Z11^2)) -> 0.47497368 | AB11: =IF(ISNUMBER($B$17),IF(AND($C$17=1,Z11<=-COS(PI()*$B$17)),AA11,NA()),NA()) -> #N/A | AC11: =IF(ISNUMBER($B$17),IF(AND($C$17=2,Z11<=-COS(PI()*$B$17)),AA11,NA()),NA()) -> #N/A | AD11: =IF(ISNUMBER($B$17),IF(AND($C$17=3,Z11<=-COS(PI()*$B$17)),AA11,NA()),NA()) -> #N/A | AE11: =IF(ISNUMBER($B$17),IF(AND($C$17=4,Z11<=-COS(PI()*$B$17)),AA11,NA()),NA()) -> #N/A | AF11: =IF(ISNUMBER($B$17),IF(AND($C$17=5,Z11<=-COS(PI()*$B$17)),AA11,NA()),NA()) -> #N/A | AG11: =IF(ISNUMBER($B$17),IF(AND(ISNUMBER($B$17),Z11>=MIN(0,$Z$2),Z11<=MAX(0,$Z$2)),IF($Z$2=0,0,Z11/$Z$2*$AA$2),NA()),NA()) -> 0.22232228 | AH11: -0.88 | AI11: =SQRT(MAX(0,1-AH11^2)) -> 0.47497368 | AJ11: =IF(ISNUMBER($B$18),IF(AND($C$18=1,AH11<=-COS(PI()*$B$18)),AI11,NA()),NA()) -> 0.47497368 | AK11: =IF(ISNUMBER($B$18),IF(AND($C$18=2,AH11<=-COS(PI()*$B$18)),AI11,NA()),NA()) -> #N/A | AL11: =IF(ISNUMBER($B$18),IF(AND($C$18=3,AH11<=-COS(PI()*$B$18)),AI11,NA()),NA()) -> #N/A | AM11: =IF(ISNUMBER($B$18),IF(AND($C$18=4,AH11<=-COS(PI()*$B$18)),AI11,NA()),NA()) -> #N/A | AN11: =IF(ISNUMBER($B$18),IF(AND($C$18=5,AH11<=-COS(PI()*$B$18)),AI11,NA()),NA()) -> #N/A | AO11: =IF(ISNUMBER($B$18),IF(AND(ISNUMBER($B$18),AH11>=MIN(0,$AH$2),AH11<=MAX(0,$AH$2)),IF($AH$2=0,0,AH11/$AH$2*$AI$2),NA()),NA()) -> #N/A
R12: -0.86 | S12: =SQRT(MAX(0,1-R12^2)) -> 0.51029403 | T12: =IF(ISNUMBER($B$16),IF(AND($C$16=1,R12<=-COS(PI()*$B$16)),S12,NA()),NA()) -> #N/A | U12: =IF(ISNUMBER($B$16),IF(AND($C$16=2,R12<=-COS(PI()*$B$16)),S12,NA()),NA()) -> #N/A | V12: =IF(ISNUMBER($B$16),IF(AND($C$16=3,R12<=-COS(PI()*$B$16)),S12,NA()),NA()) -> #N/A | W12: =IF(ISNUMBER($B$16),IF(AND($C$16=4,R12<=-COS(PI()*$B$16)),S12,NA()),NA()) -> #N/A | X12: =IF(ISNUMBER($B$16),IF(AND($C$16=5,R12<=-COS(PI()*$B$16)),S12,NA()),NA()) -> #N/A | Y12: =IF(ISNUMBER($B$16),IF(AND(ISNUMBER($B$16),R12>=MIN(0,$R$2),R12<=MAX(0,$R$2)),IF($R$2=0,0,R12/$R$2*$S$2),NA()),NA()) -> 0.31951574 | Z12: -0.86 | AA12: =SQRT(MAX(0,1-Z12^2)) -> 0.51029403 | AB12: =IF(ISNUMBER($B$17),IF(AND($C$17=1,Z12<=-COS(PI()*$B$17)),AA12,NA()),NA()) -> #N/A | AC12: =IF(ISNUMBER($B$17),IF(AND($C$17=2,Z12<=-COS(PI()*$B$17)),AA12,NA()),NA()) -> #N/A | AD12: =IF(ISNUMBER($B$17),IF(AND($C$17=3,Z12<=-COS(PI()*$B$17)),AA12,NA()),NA()) -> #N/A | AE12: =IF(ISNUMBER($B$17),IF(AND($C$17=4,Z12<=-COS(PI()*$B$17)),AA12,NA()),NA()) -> #N/A | AF12: =IF(ISNUMBER($B$17),IF(AND($C$17=5,Z12<=-COS(PI()*$B$17)),AA12,NA()),NA()) -> #N/A | AG12: =IF(ISNUMBER($B$17),IF(AND(ISNUMBER($B$17),Z12>=MIN(0,$Z$2),Z12<=MAX(0,$Z$2)),IF($Z$2=0,0,Z12/$Z$2*$AA$2),NA()),NA()) -> 0.2172695 | AH12: -0.86 | AI12: =SQRT(MAX(0,1-AH12^2)) -> 0.51029403 | AJ12: =IF(ISNUMBER($B$18),IF(AND($C$18=1,AH12<=-COS(PI()*$B$18)),AI12,NA()),NA()) -> 0.51029403 | AK12: =IF(ISNUMBER($B$18),IF(AND($C$18=2,AH12<=-COS(PI()*$B$18)),AI12,NA()),NA()) -> #N/A | AL12: =IF(ISNUMBER($B$18),IF(AND($C$18=3,AH12<=-COS(PI()*$B$18)),AI12,NA()),NA()) -> #N/A | AM12: =IF(ISNUMBER($B$18),IF(AND($C$18=4,AH12<=-COS(PI()*$B$18)),AI12,NA()),NA()) -> #N/A | AN12: =IF(ISNUMBER($B$18),IF(AND($C$18=5,AH12<=-COS(PI()*$B$18)),AI12,NA()),NA()) -> #N/A | AO12: =IF(ISNUMBER($B$18),IF(AND(ISNUMBER($B$18),AH12>=MIN(0,$AH$2),AH12<=MAX(0,$AH$2)),IF($AH$2=0,0,AH12/$AH$2*$AI$2),NA()),NA()) -> #N/A
R13: -0.84 | S13: =SQRT(MAX(0,1-R13^2)) -> 0.5425864 | T13: =IF(ISNUMBER($B$16),IF(AND($C$16=1,R13<=-COS(PI()*$B$16)),S13,NA()),NA()) -> #N/A | U13: =IF(ISNUMBER($B$16),IF(AND($C$16=2,R13<=-COS(PI()*$B$16)),S13,NA()),NA()) -> #N/A | V13: =IF(ISNUMBER($B$16),IF(AND($C$16=3,R13<=-COS(PI()*$B$16)),S13,NA()),NA()) -> #N/A | W13: =IF(ISNUMBER($B$16),IF(AND($C$16=4,R13<=-COS(PI()*$B$16)),S13,NA()),NA()) -> #N/A | X13: =IF(ISNUMBER($B$16),IF(AND($C$16=5,R13<=-COS(PI()*$B$16)),S13,NA()),NA()) -> #N/A | Y13: =IF(ISNUMBER($B$16),IF(AND(ISNUMBER($B$16),R13>=MIN(0,$R$2),R13<=MAX(0,$R$2)),IF($R$2=0,0,R13/$R$2*$S$2),NA()),NA()) -> 0.31208514 | Z13: -0.84 | AA13: =SQRT(MAX(0,1-Z13^2)) -> 0.5425864 | AB13: =IF(ISNUMBER($B$17),IF(AND($C$17=1,Z13<=-COS(PI()*$B$17)),AA13,NA()),NA()) -> #N/A | AC13: =IF(ISNUMBER($B$17),IF(AND($C$17=2,Z13<=-COS(PI()*$B$17)),AA13,NA()),NA()) -> #N/A | AD13: =IF(ISNUMBER($B$17),IF(AND($C$17=3,Z13<=-COS(PI()*$B$17)),AA13,NA()),NA()) -> #N/A | AE13: =IF(ISNUMBER($B$17),IF(AND($C$17=4,Z13<=-COS(PI()*$B$17)),AA13,NA()),NA()) -> #N/A | AF13: =IF(ISNUMBER($B$17),IF(AND($C$17=5,Z13<=-COS(PI()*$B$17)),AA13,NA()),NA()) -> #N/A | AG13: =IF(ISNUMBER($B$17),IF(AND(ISNUMBER($B$17),Z13>=MIN(0,$Z$2),Z13<=MAX(0,$Z$2)),IF($Z$2=0,0,Z13/$Z$2*$AA$2),NA()),NA()) -> 0.21221672 | AH13: -0.84 | AI13: =SQRT(MAX(0,1-AH13^2)) -> 0.5425864 | AJ13: =IF(ISNUMBER($B$18),IF(AND($C$18=1,AH13<=-COS(PI()*$B$18)),AI13,NA()),NA()) -> 0.5425864 | AK13: =IF(ISNUMBER($B$18),IF(AND($C$18=2,AH13<=-COS(PI()*$B$18)),AI13,NA()),NA()) -> #N/A | AL13: =IF(ISNUMBER($B$18),IF(AND($C$18=3,AH13<=-COS(PI()*$B$18)),AI13,NA()),NA()) -> #N/A | AM13: =IF(ISNUMBER($B$18),IF(AND($C$18=4,AH13<=-COS(PI()*$B$18)),AI13,NA()),NA()) -> #N/A | AN13: =IF(ISNUMBER($B$18),IF(AND($C$18=5,AH13<=-COS(PI()*$B$18)),AI13,NA()),NA()) -> #N/A | AO13: =IF(ISNUMBER($B$18),IF(AND(ISNUMBER($B$18),AH13>=MIN(0,$AH$2),AH13<=MAX(0,$AH$2)),IF($AH$2=0,0,AH13/$AH$2*$AI$2),NA()),NA()) -> #N/A
R14: -0.82 | S14: =SQRT(MAX(0,1-R14^2)) -> 0.57236352 | T14: =IF(ISNUMBER($B$16),IF(AND($C$16=1,R14<=-COS(PI()*$B$16)),S14,NA()),NA()) -> #N/A | U14: =IF(ISNUMBER($B$16),IF(AND($C$16=2,R14<=-COS(PI()*$B$16)),S14,NA()),NA()) -> #N/A | V14: =IF(ISNUMBER($B$16),IF(AND($C$16=3,R14<=-COS(PI()*$B$16)),S14,NA()),NA()) -> #N/A | W14: =IF(ISNUMBER($B$16),IF(AND($C$16=4,R14<=-COS(PI()*$B$16)),S14,NA()),NA()) -> #N/A | X14: =IF(ISNUMBER($B$16),IF(AND($C$16=5,R14<=-COS(PI()*$B$16)),S14,NA()),NA()) -> #N/A | Y14: =IF(ISNUMBER($B$16),IF(AND(ISNUMBER($B$16),R14>=MIN(0,$R$2),R14<=MAX(0,$R$2)),IF($R$2=0,0,R14/$R$2*$S$2),NA()),NA()) -> 0.30465454 | Z14: -0.82 | AA14: =SQRT(MAX(0,1-Z14^2)) -> 0.57236352 | AB14: =IF(ISNUMBER($B$17),IF(AND($C$17=1,Z14<=-COS(PI()*$B$17)),AA14,NA()),NA()) -> #N/A | AC14: =IF(ISNUMBER($B$17),IF(AND($C$17=2,Z14<=-COS(PI()*$B$17)),AA14,NA()),NA()) -> #N/A | AD14: =IF(ISNUMBER($B$17),IF(AND($C$17=3,Z14<=-COS(PI()*$B$17)),AA14,NA()),NA()) -> #N/A | AE14: =IF(ISNUMBER($B$17),IF(AND($C$17=4,Z14<=-COS(PI()*$B$17)),AA14,NA()),NA()) -> #N/A | AF14: =IF(ISNUMBER($B$17),IF(AND($C$17=5,Z14<=-COS(PI()*$B$17)),AA14,NA()),NA()) -> #N/A | AG14: =IF(ISNUMBER($B$17),IF(AND(ISNUMBER($B$17),Z14>=MIN(0,$Z$2),Z14<=MAX(0,$Z$2)),IF($Z$2=0,0,Z14/$Z$2*$AA$2),NA()),NA()) -> 0.20716394 | AH14: -0.82 | AI14: =SQRT(MAX(0,1-AH14^2)) -> 0.57236352 | AJ14: =IF(ISNUMBER($B$18),IF(AND($C$18=1,AH14<=-COS(PI()*$B$18)),AI14,NA()),NA()) -> #N/A | AK14: =IF(ISNUMBER($B$18),IF(AND($C$18=2,AH14<=-COS(PI()*$B$18)),AI14,NA()),NA()) -> #N/A | AL14: =IF(ISNUMBER($B$18),IF(AND($C$18=3,AH14<=-COS(PI()*$B$18)),AI14,NA()),NA()) -> #N/A | AM14: =IF(ISNUMBER($B$18),IF(AND($C$18=4,AH14<=-COS(PI()*$B$18)),AI14,NA()),NA()) -> #N/A | AN14: =IF(ISNUMBER($B$18),IF(AND($C$18=5,AH14<=-COS(PI()*$B$18)),AI14,NA()),NA()) -> #N/A | AO14: =IF(ISNUMBER($B$18),IF(AND(ISNUMBER($B$18),AH14>=MIN(0,$AH$2),AH14<=MAX(0,$AH$2)),IF($AH$2=0,0,AH14/$AH$2*$AI$2),NA()),NA()) -> 0.56483561
R15: -0.8 | S15: =SQRT(MAX(0,1-R15^2)) -> 0.6 | T15: =IF(ISNUMBER($B$16),IF(AND($C$16=1,R15<=-COS(PI()*$B$16)),S15,NA()),NA()) -> #N/A | U15: =IF(ISNUMBER($B$16),IF(AND($C$16=2,R15<=-COS(PI()*$B$16)),S15,NA()),NA()) -> #N/A | V15: =IF(ISNUMBER($B$16),IF(AND($C$16=3,R15<=-COS(PI()*$B$16)),S15,NA()),NA()) -> #N/A | W15: =IF(ISNUMBER($B$16),IF(AND($C$16=4,R15<=-COS(PI()*$B$16)),S15,NA()),NA()) -> #N/A | X15: =IF(ISNUMBER($B$16),IF(AND($C$16=5,R15<=-COS(PI()*$B$16)),S15,NA()),NA()) -> #N/A | Y15: =IF(ISNUMBER($B$16),IF(AND(ISNUMBER($B$16),R15>=MIN(0,$R$2),R15<=MAX(0,$R$2)),IF($R$2=0,0,R15/$R$2*$S$2),NA()),NA()) -> 0.29722394 | Z15: -0.8 | AA15: =SQRT(MAX(0,1-Z15^2)) -> 0.6 | AB15: =IF(ISNUMBER($B$17),IF(AND($C$17=1,Z15<=-COS(PI()*$B$17)),AA15,NA()),NA()) -> #N/A | AC15: =IF(ISNUMBER($B$17),IF(AND($C$17=2,Z15<=-COS(PI()*$B$17)),AA15,NA()),NA()) -> #N/A | AD15: =IF(ISNUMBER($B$17),IF(AND($C$17=3,Z15<=-COS(PI()*$B$17)),AA15,NA()),NA()) -> #N/A | AE15: =IF(ISNUMBER($B$17),IF(AND($C$17=4,Z15<=-COS(PI()*$B$17)),AA15,NA()),NA()) -> #N/A | AF15: =IF(ISNUMBER($B$17),IF(AND($C$17=5,Z15<=-COS(PI()*$B$17)),AA15,NA()),NA()) -> #N/A | AG15: =IF(ISNUMBER($B$17),IF(AND(ISNUMBER($B$17),Z15>=MIN(0,$Z$2),Z15<=MAX(0,$Z$2)),IF($Z$2=0,0,Z15/$Z$2*$AA$2),NA()),NA()) -> 0.20211116 | AH15: -0.8 | AI15: =SQRT(MAX(0,1-AH15^2)) -> 0.6 | AJ15: =IF(ISNUMBER($B$18),IF(AND($C$18=1,AH15<=-COS(PI()*$B$18)),AI15,NA()),NA()) -> #N/A | AK15: =IF(ISNUMBER($B$18),IF(AND($C$18=2,AH15<=-COS(PI()*$B$18)),AI15,NA()),NA()) -> #N/A | AL15: =IF(ISNUMBER($B$18),IF(AND($C$18=3,AH15<=-COS(PI()*$B$18)),AI15,NA()),NA()) -> #N/A | AM15: =IF(ISNUMBER($B$18),IF(AND($C$18=4,AH15<=-COS(PI()*$B$18)),AI15,NA()),NA()) -> #N/A | AN15: =IF(ISNUMBER($B$18),IF(AND($C$18=5,AH15<=-COS(PI()*$B$18)),AI15,NA()),NA()) -> #N/A | AO15: =IF(ISNUMBER($B$18),IF(AND(ISNUMBER($B$18),AH15>=MIN(0,$AH$2),AH15<=MAX(0,$AH$2)),IF($AH$2=0,0,AH15/$AH$2*$AI$2),NA()),NA()) -> 0.55105913
A16: Overdue Ratio | B16: =IF(B6=0,"n.a.",B7/B6) -> 0.11323077 | C16: =IF(B16<0.2,1,IF(B16<0.3,2,IF(B16<0.45,3,IF(B16<=0.6,4,5)))) -> 1 | R16: -0.78 | S16: =SQRT(MAX(0,1-R16^2)) -> 0.62577951 | T16: =IF(ISNUMBER($B$16),IF(AND($C$16=1,R16<=-COS(PI()*$B$16)),S16,NA()),NA()) -> #N/A | U16: =IF(ISNUMBER($B$16),IF(AND($C$16=2,R16<=-COS(PI()*$B$16)),S16,NA()),NA()) -> #N/A | V16: =IF(ISNUMBER($B$16),IF(AND($C$16=3,R16<=-COS(PI()*$B$16)),S16,NA()),NA()) -> #N/A | W16: =IF(ISNUMBER($B$16),IF(AND($C$16=4,R16<=-COS(PI()*$B$16)),S16,NA()),NA()) -> #N/A | X16: =IF(ISNUMBER($B$16),IF(AND($C$16=5,R16<=-COS(PI()*$B$16)),S16,NA()),NA()) -> #N/A | Y16: =IF(ISNUMBER($B$16),IF(AND(ISNUMBER($B$16),R16>=MIN(0,$R$2),R16<=MAX(0,$R$2)),IF($R$2=0,0,R16/$R$2*$S$2),NA()),NA()) -> 0.28979335 | Z16: -0.78 | AA16: =SQRT(MAX(0,1-Z16^2)) -> 0.62577951 | AB16: =IF(ISNUMBER($B$17),IF(AND($C$17=1,Z16<=-COS(PI()*$B$17)),AA16,NA()),NA()) -> #N/A | AC16: =IF(ISNUMBER($B$17),IF(AND($C$17=2,Z16<=-COS(PI()*$B$17)),AA16,NA()),NA()) -> #N/A | AD16: =IF(ISNUMBER($B$17),IF(AND($C$17=3,Z16<=-COS(PI()*$B$17)),AA16,NA()),NA()) -> #N/A | AE16: =IF(ISNUMBER($B$17),IF(AND($C$17=4,Z16<=-COS(PI()*$B$17)),AA16,NA()),NA()) -> #N/A | AF16: =IF(ISNUMBER($B$17),IF(AND($C$17=5,Z16<=-COS(PI()*$B$17)),AA16,NA()),NA()) -> #N/A | AG16: =IF(ISNUMBER($B$17),IF(AND(ISNUMBER($B$17),Z16>=MIN(0,$Z$2),Z16<=MAX(0,$Z$2)),IF($Z$2=0,0,Z16/$Z$2*$AA$2),NA()),NA()) -> 0.19705838 | AH16: -0.78 | AI16: =SQRT(MAX(0,1-AH16^2)) -> 0.62577951 | AJ16: =IF(ISNUMBER($B$18),IF(AND($C$18=1,AH16<=-COS(PI()*$B$18)),AI16,NA()),NA()) -> #N/A | AK16: =IF(ISNUMBER($B$18),IF(AND($C$18=2,AH16<=-COS(PI()*$B$18)),AI16,NA()),NA()) -> #N/A | AL16: =IF(ISNUMBER($B$18),IF(AND($C$18=3,AH16<=-COS(PI()*$B$18)),AI16,NA()),NA()) -> #N/A | AM16: =IF(ISNUMBER($B$18),IF(AND($C$18=4,AH16<=-COS(PI()*$B$18)),AI16,NA()),NA()) -> #N/A | AN16: =IF(ISNUMBER($B$18),IF(AND($C$18=5,AH16<=-COS(PI()*$B$18)),AI16,NA()),NA()) -> #N/A | AO16: =IF(ISNUMBER($B$18),IF(AND(ISNUMBER($B$18),AH16>=MIN(0,$AH$2),AH16<=MAX(0,$AH$2)),IF($AH$2=0,0,AH16/$AH$2*$AI$2),NA()),NA()) -> 0.53728265
A17: >60-Day Ratio | B17: =IF(B6=0,"n.a.",B8/B6) -> 0.078769231 | C17: =IF(B17<0.2,1,IF(B17<0.3,2,IF(B17<0.45,3,IF(B17<=0.6,4,5)))) -> 1 | R17: -0.76 | S17: =SQRT(MAX(0,1-R17^2)) -> 0.64992307 | T17: =IF(ISNUMBER($B$16),IF(AND($C$16=1,R17<=-COS(PI()*$B$16)),S17,NA()),NA()) -> #N/A | U17: =IF(ISNUMBER($B$16),IF(AND($C$16=2,R17<=-COS(PI()*$B$16)),S17,NA()),NA()) -> #N/A | V17: =IF(ISNUMBER($B$16),IF(AND($C$16=3,R17<=-COS(PI()*$B$16)),S17,NA()),NA()) -> #N/A | W17: =IF(ISNUMBER($B$16),IF(AND($C$16=4,R17<=-COS(PI()*$B$16)),S17,NA()),NA()) -> #N/A | X17: =IF(ISNUMBER($B$16),IF(AND($C$16=5,R17<=-COS(PI()*$B$16)),S17,NA()),NA()) -> #N/A | Y17: =IF(ISNUMBER($B$16),IF(AND(ISNUMBER($B$16),R17>=MIN(0,$R$2),R17<=MAX(0,$R$2)),IF($R$2=0,0,R17/$R$2*$S$2),NA()),NA()) -> 0.28236275 | Z17: -0.76 | AA17: =SQRT(MAX(0,1-Z17^2)) -> 0.64992307 | AB17: =IF(ISNUMBER($B$17),IF(AND($C$17=1,Z17<=-COS(PI()*$B$17)),AA17,NA()),NA()) -> #N/A | AC17: =IF(ISNUMBER($B$17),IF(AND($C$17=2,Z17<=-COS(PI()*$B$17)),AA17,NA()),NA()) -> #N/A | AD17: =IF(ISNUMBER($B$17),IF(AND($C$17=3,Z17<=-COS(PI()*$B$17)),AA17,NA()),NA()) -> #N/A | AE17: =IF(ISNUMBER($B$17),IF(AND($C$17=4,Z17<=-COS(PI()*$B$17)),AA17,NA()),NA()) -> #N/A | AF17: =IF(ISNUMBER($B$17),IF(AND($C$17=5,Z17<=-COS(PI()*$B$17)),AA17,NA()),NA()) -> #N/A | AG17: =IF(ISNUMBER($B$17),IF(AND(ISNUMBER($B$17),Z17>=MIN(0,$Z$2),Z17<=MAX(0,$Z$2)),IF($Z$2=0,0,Z17/$Z$2*$AA$2),NA()),NA()) -> 0.1920056 | AH17: -0.76 | AI17: =SQRT(MAX(0,1-AH17^2)) -> 0.64992307 | AJ17: =IF(ISNUMBER($B$18),IF(AND($C$18=1,AH17<=-COS(PI()*$B$18)),AI17,NA()),NA()) -> #N/A | AK17: =IF(ISNUMBER($B$18),IF(AND($C$18=2,AH17<=-COS(PI()*$B$18)),AI17,NA()),NA()) -> #N/A | AL17: =IF(ISNUMBER($B$18),IF(AND($C$18=3,AH17<=-COS(PI()*$B$18)),AI17,NA()),NA()) -> #N/A | AM17: =IF(ISNUMBER($B$18),IF(AND($C$18=4,AH17<=-COS(PI()*$B$18)),AI17,NA()),NA()) -> #N/A | AN17: =IF(ISNUMBER($B$18),IF(AND($C$18=5,AH17<=-COS(PI()*$B$18)),AI17,NA()),NA()) -> #N/A | AO17: =IF(ISNUMBER($B$18),IF(AND(ISNUMBER($B$18),AH17>=MIN(0,$AH$2),AH17<=MAX(0,$AH$2)),IF($AH$2=0,0,AH17/$AH$2*$AI$2),NA()),NA()) -> 0.52350618
A18: Total Overdue Ratio | B18: =B10 -> 0.192 | C18: =IF(B18<0.2,1,IF(B18<0.3,2,IF(B18<0.45,3,IF(B18<=0.6,4,5)))) -> 1 | R18: -0.74 | S18: =SQRT(MAX(0,1-R18^2)) -> 0.67260687 | T18: =IF(ISNUMBER($B$16),IF(AND($C$16=1,R18<=-COS(PI()*$B$16)),S18,NA()),NA()) -> #N/A | U18: =IF(ISNUMBER($B$16),IF(AND($C$16=2,R18<=-COS(PI()*$B$16)),S18,NA()),NA()) -> #N/A | V18: =IF(ISNUMBER($B$16),IF(AND($C$16=3,R18<=-COS(PI()*$B$16)),S18,NA()),NA()) -> #N/A | W18: =IF(ISNUMBER($B$16),IF(AND($C$16=4,R18<=-COS(PI()*$B$16)),S18,NA()),NA()) -> #N/A | X18: =IF(ISNUMBER($B$16),IF(AND($C$16=5,R18<=-COS(PI()*$B$16)),S18,NA()),NA()) -> #N/A | Y18: =IF(ISNUMBER($B$16),IF(AND(ISNUMBER($B$16),R18>=MIN(0,$R$2),R18<=MAX(0,$R$2)),IF($R$2=0,0,R18/$R$2*$S$2),NA()),NA()) -> 0.27493215 | Z18: -0.74 | AA18: =SQRT(MAX(0,1-Z18^2)) -> 0.67260687 | AB18: =IF(ISNUMBER($B$17),IF(AND($C$17=1,Z18<=-COS(PI()*$B$17)),AA18,NA()),NA()) -> #N/A | AC18: =IF(ISNUMBER($B$17),IF(AND($C$17=2,Z18<=-COS(PI()*$B$17)),AA18,NA()),NA()) -> #N/A | AD18: =IF(ISNUMBER($B$17),IF(AND($C$17=3,Z18<=-COS(PI()*$B$17)),AA18,NA()),NA()) -> #N/A | AE18: =IF(ISNUMBER($B$17),IF(AND($C$17=4,Z18<=-COS(PI()*$B$17)),AA18,NA()),NA()) -> #N/A | AF18: =IF(ISNUMBER($B$17),IF(AND($C$17=5,Z18<=-COS(PI()*$B$17)),AA18,NA()),NA()) -> #N/A | AG18: =IF(ISNUMBER($B$17),IF(AND(ISNUMBER($B$17),Z18>=MIN(0,$Z$2),Z18<=MAX(0,$Z$2)),IF($Z$2=0,0,Z18/$Z$2*$AA$2),NA()),NA()) -> 0.18695282 | AH18: -0.74 | AI18: =SQRT(MAX(0,1-AH18^2)) -> 0.67260687 | AJ18: =IF(ISNUMBER($B$18),IF(AND($C$18=1,AH18<=-COS(PI()*$B$18)),AI18,NA()),NA()) -> #N/A | AK18: =IF(ISNUMBER($B$18),IF(AND($C$18=2,AH18<=-COS(PI()*$B$18)),AI18,NA()),NA()) -> #N/A | AL18: =IF(ISNUMBER($B$18),IF(AND($C$18=3,AH18<=-COS(PI()*$B$18)),AI18,NA()),NA()) -> #N/A | AM18: =IF(ISNUMBER($B$18),IF(AND($C$18=4,AH18<=-COS(PI()*$B$18)),AI18,NA()),NA()) -> #N/A | AN18: =IF(ISNUMBER($B$18),IF(AND($C$18=5,AH18<=-COS(PI()*$B$18)),AI18,NA()),NA()) -> #N/A | AO18: =IF(ISNUMBER($B$18),IF(AND(ISNUMBER($B$18),AH18>=MIN(0,$AH$2),AH18<=MAX(0,$AH$2)),IF($AH$2=0,0,AH18/$AH$2*$AI$2),NA()),NA()) -> 0.5097297
R19: -0.72 | S19: =SQRT(MAX(0,1-R19^2)) -> 0.69397406 | T19: =IF(ISNUMBER($B$16),IF(AND($C$16=1,R19<=-COS(PI()*$B$16)),S19,NA()),NA()) -> #N/A | U19: =IF(ISNUMBER($B$16),IF(AND($C$16=2,R19<=-COS(PI()*$B$16)),S19,NA()),NA()) -> #N/A | V19: =IF(ISNUMBER($B$16),IF(AND($C$16=3,R19<=-COS(PI()*$B$16)),S19,NA()),NA()) -> #N/A | W19: =IF(ISNUMBER($B$16),IF(AND($C$16=4,R19<=-COS(PI()*$B$16)),S19,NA()),NA()) -> #N/A | X19: =IF(ISNUMBER($B$16),IF(AND($C$16=5,R19<=-COS(PI()*$B$16)),S19,NA()),NA()) -> #N/A | Y19: =IF(ISNUMBER($B$16),IF(AND(ISNUMBER($B$16),R19>=MIN(0,$R$2),R19<=MAX(0,$R$2)),IF($R$2=0,0,R19/$R$2*$S$2),NA()),NA()) -> 0.26750155 | Z19: -0.72 | AA19: =SQRT(MAX(0,1-Z19^2)) -> 0.69397406 | AB19: =IF(ISNUMBER($B$17),IF(AND($C$17=1,Z19<=-COS(PI()*$B$17)),AA19,NA()),NA()) -> #N/A | AC19: =IF(ISNUMBER($B$17),IF(AND($C$17=2,Z19<=-COS(PI()*$B$17)),AA19,NA()),NA()) -> #N/A | AD19: =IF(ISNUMBER($B$17),IF(AND($C$17=3,Z19<=-COS(PI()*$B$17)),AA19,NA()),NA()) -> #N/A | AE19: =IF(ISNUMBER($B$17),IF(AND($C$17=4,Z19<=-COS(PI()*$B$17)),AA19,NA()),NA()) -> #N/A | AF19: =IF(ISNUMBER($B$17),IF(AND($C$17=5,Z19<=-COS(PI()*$B$17)),AA19,NA()),NA()) -> #N/A | AG19: =IF(ISNUMBER($B$17),IF(AND(ISNUMBER($B$17),Z19>=MIN(0,$Z$2),Z19<=MAX(0,$Z$2)),IF($Z$2=0,0,Z19/$Z$2*$AA$2),NA()),NA()) -> 0.18190005 | AH19: -0.72 | AI19: =SQRT(MAX(0,1-AH19^2)) -> 0.69397406 | AJ19: =IF(ISNUMBER($B$18),IF(AND($C$18=1,AH19<=-COS(PI()*$B$18)),AI19,NA()),NA()) -> #N/A | AK19: =IF(ISNUMBER($B$18),IF(AND($C$18=2,AH19<=-COS(PI()*$B$18)),AI19,NA()),NA()) -> #N/A | AL19: =IF(ISNUMBER($B$18),IF(AND($C$18=3,AH19<=-COS(PI()*$B$18)),AI19,NA()),NA()) -> #N/A | AM19: =IF(ISNUMBER($B$18),IF(AND($C$18=4,AH19<=-COS(PI()*$B$18)),AI19,NA()),NA()) -> #N/A | AN19: =IF(ISNUMBER($B$18),IF(AND($C$18=5,AH19<=-COS(PI()*$B$18)),AI19,NA()),NA()) -> #N/A | AO19: =IF(ISNUMBER($B$18),IF(AND(ISNUMBER($B$18),AH19>=MIN(0,$AH$2),AH19<=MAX(0,$AH$2)),IF($AH$2=0,0,AH19/$AH$2*$AI$2),NA()),NA()) -> 0.49595322
R20: -0.7 | S20: =SQRT(MAX(0,1-R20^2)) -> 0.71414284 | T20: =IF(ISNUMBER($B$16),IF(AND($C$16=1,R20<=-COS(PI()*$B$16)),S20,NA()),NA()) -> #N/A | U20: =IF(ISNUMBER($B$16),IF(AND($C$16=2,R20<=-COS(PI()*$B$16)),S20,NA()),NA()) -> #N/A | V20: =IF(ISNUMBER($B$16),IF(AND($C$16=3,R20<=-COS(PI()*$B$16)),S20,NA()),NA()) -> #N/A | W20: =IF(ISNUMBER($B$16),IF(AND($C$16=4,R20<=-COS(PI()*$B$16)),S20,NA()),NA()) -> #N/A | X20: =IF(ISNUMBER($B$16),IF(AND($C$16=5,R20<=-COS(PI()*$B$16)),S20,NA()),NA()) -> #N/A | Y20: =IF(ISNUMBER($B$16),IF(AND(ISNUMBER($B$16),R20>=MIN(0,$R$2),R20<=MAX(0,$R$2)),IF($R$2=0,0,R20/$R$2*$S$2),NA()),NA()) -> 0.26007095 | Z20: -0.7 | AA20: =SQRT(MAX(0,1-Z20^2)) -> 0.71414284 | AB20: =IF(ISNUMBER($B$17),IF(AND($C$17=1,Z20<=-COS(PI()*$B$17)),AA20,NA()),NA()) -> #N/A | AC20: =IF(ISNUMBER($B$17),IF(AND($C$17=2,Z20<=-COS(PI()*$B$17)),AA20,NA()),NA()) -> #N/A | AD20: =IF(ISNUMBER($B$17),IF(AND($C$17=3,Z20<=-COS(PI()*$B$17)),AA20,NA()),NA()) -> #N/A | AE20: =IF(ISNUMBER($B$17),IF(AND($C$17=4,Z20<=-COS(PI()*$B$17)),AA20,NA()),NA()) -> #N/A | AF20: =IF(ISNUMBER($B$17),IF(AND($C$17=5,Z20<=-COS(PI()*$B$17)),AA20,NA()),NA()) -> #N/A | AG20: =IF(ISNUMBER($B$17),IF(AND(ISNUMBER($B$17),Z20>=MIN(0,$Z$2),Z20<=MAX(0,$Z$2)),IF($Z$2=0,0,Z20/$Z$2*$AA$2),NA()),NA()) -> 0.17684727 | AH20: -0.7 | AI20: =SQRT(MAX(0,1-AH20^2)) -> 0.71414284 | AJ20: =IF(ISNUMBER($B$18),IF(AND($C$18=1,AH20<=-COS(PI()*$B$18)),AI20,NA()),NA()) -> #N/A | AK20: =IF(ISNUMBER($B$18),IF(AND($C$18=2,AH20<=-COS(PI()*$B$18)),AI20,NA()),NA()) -> #N/A | AL20: =IF(ISNUMBER($B$18),IF(AND($C$18=3,AH20<=-COS(PI()*$B$18)),AI20,NA()),NA()) -> #N/A | AM20: =IF(ISNUMBER($B$18),IF(AND($C$18=4,AH20<=-COS(PI()*$B$18)),AI20,NA()),NA()) -> #N/A | AN20: =IF(ISNUMBER($B$18),IF(AND($C$18=5,AH20<=-COS(PI()*$B$18)),AI20,NA()),NA()) -> #N/A | AO20: =IF(ISNUMBER($B$18),IF(AND(ISNUMBER($B$18),AH20>=MIN(0,$AH$2),AH20<=MAX(0,$AH$2)),IF($AH$2=0,0,AH20/$AH$2*$AI$2),NA()),NA()) -> 0.48217674
R21: -0.68 | S21: =SQRT(MAX(0,1-R21^2)) -> 0.73321211 | T21: =IF(ISNUMBER($B$16),IF(AND($C$16=1,R21<=-COS(PI()*$B$16)),S21,NA()),NA()) -> #N/A | U21: =IF(ISNUMBER($B$16),IF(AND($C$16=2,R21<=-COS(PI()*$B$16)),S21,NA()),NA()) -> #N/A | V21: =IF(ISNUMBER($B$16),IF(AND($C$16=3,R21<=-COS(PI()*$B$16)),S21,NA()),NA()) -> #N/A | W21: =IF(ISNUMBER($B$16),IF(AND($C$16=4,R21<=-COS(PI()*$B$16)),S21,NA()),NA()) -> #N/A | X21: =IF(ISNUMBER($B$16),IF(AND($C$16=5,R21<=-COS(PI()*$B$16)),S21,NA()),NA()) -> #N/A | Y21: =IF(ISNUMBER($B$16),IF(AND(ISNUMBER($B$16),R21>=MIN(0,$R$2),R21<=MAX(0,$R$2)),IF($R$2=0,0,R21/$R$2*$S$2),NA()),NA()) -> 0.25264035 | Z21: -0.68 | AA21: =SQRT(MAX(0,1-Z21^2)) -> 0.73321211 | AB21: =IF(ISNUMBER($B$17),IF(AND($C$17=1,Z21<=-COS(PI()*$B$17)),AA21,NA()),NA()) -> #N/A | AC21: =IF(ISNUMBER($B$17),IF(AND($C$17=2,Z21<=-COS(PI()*$B$17)),AA21,NA()),NA()) -> #N/A | AD21: =IF(ISNUMBER($B$17),IF(AND($C$17=3,Z21<=-COS(PI()*$B$17)),AA21,NA()),NA()) -> #N/A | AE21: =IF(ISNUMBER($B$17),IF(AND($C$17=4,Z21<=-COS(PI()*$B$17)),AA21,NA()),NA()) -> #N/A | AF21: =IF(ISNUMBER($B$17),IF(AND($C$17=5,Z21<=-COS(PI()*$B$17)),AA21,NA()),NA()) -> #N/A | AG21: =IF(ISNUMBER($B$17),IF(AND(ISNUMBER($B$17),Z21>=MIN(0,$Z$2),Z21<=MAX(0,$Z$2)),IF($Z$2=0,0,Z21/$Z$2*$AA$2),NA()),NA()) -> 0.17179449 | AH21: -0.68 | AI21: =SQRT(MAX(0,1-AH21^2)) -> 0.73321211 | AJ21: =IF(ISNUMBER($B$18),IF(AND($C$18=1,AH21<=-COS(PI()*$B$18)),AI21,NA()),NA()) -> #N/A | AK21: =IF(ISNUMBER($B$18),IF(AND($C$18=2,AH21<=-COS(PI()*$B$18)),AI21,NA()),NA()) -> #N/A | AL21: =IF(ISNUMBER($B$18),IF(AND($C$18=3,AH21<=-COS(PI()*$B$18)),AI21,NA()),NA()) -> #N/A | AM21: =IF(ISNUMBER($B$18),IF(AND($C$18=4,AH21<=-COS(PI()*$B$18)),AI21,NA()),NA()) -> #N/A | AN21: =IF(ISNUMBER($B$18),IF(AND($C$18=5,AH21<=-COS(PI()*$B$18)),AI21,NA()),NA()) -> #N/A | AO21: =IF(ISNUMBER($B$18),IF(AND(ISNUMBER($B$18),AH21>=MIN(0,$AH$2),AH21<=MAX(0,$AH$2)),IF($AH$2=0,0,AH21/$AH$2*$AI$2),NA()),NA()) -> 0.46840026
R22: -0.66 | S22: =SQRT(MAX(0,1-R22^2)) -> 0.7512656 | T22: =IF(ISNUMBER($B$16),IF(AND($C$16=1,R22<=-COS(PI()*$B$16)),S22,NA()),NA()) -> #N/A | U22: =IF(ISNUMBER($B$16),IF(AND($C$16=2,R22<=-COS(PI()*$B$16)),S22,NA()),NA()) -> #N/A | V22: =IF(ISNUMBER($B$16),IF(AND($C$16=3,R22<=-COS(PI()*$B$16)),S22,NA()),NA()) -> #N/A | W22: =IF(ISNUMBER($B$16),IF(AND($C$16=4,R22<=-COS(PI()*$B$16)),S22,NA()),NA()) -> #N/A | X22: =IF(ISNUMBER($B$16),IF(AND($C$16=5,R22<=-COS(PI()*$B$16)),S22,NA()),NA()) -> #N/A | Y22: =IF(ISNUMBER($B$16),IF(AND(ISNUMBER($B$16),R22>=MIN(0,$R$2),R22<=MAX(0,$R$2)),IF($R$2=0,0,R22/$R$2*$S$2),NA()),NA()) -> 0.24520975 | Z22: -0.66 | AA22: =SQRT(MAX(0,1-Z22^2)) -> 0.7512656 | AB22: =IF(ISNUMBER($B$17),IF(AND($C$17=1,Z22<=-COS(PI()*$B$17)),AA22,NA()),NA()) -> #N/A | AC22: =IF(ISNUMBER($B$17),IF(AND($C$17=2,Z22<=-COS(PI()*$B$17)),AA22,NA()),NA()) -> #N/A | AD22: =IF(ISNUMBER($B$17),IF(AND($C$17=3,Z22<=-COS(PI()*$B$17)),AA22,NA()),NA()) -> #N/A | AE22: =IF(ISNUMBER($B$17),IF(AND($C$17=4,Z22<=-COS(PI()*$B$17)),AA22,NA()),NA()) -> #N/A | AF22: =IF(ISNUMBER($B$17),IF(AND($C$17=5,Z22<=-COS(PI()*$B$17)),AA22,NA()),NA()) -> #N/A | AG22: =IF(ISNUMBER($B$17),IF(AND(ISNUMBER($B$17),Z22>=MIN(0,$Z$2),Z22<=MAX(0,$Z$2)),IF($Z$2=0,0,Z22/$Z$2*$AA$2),NA()),NA()) -> 0.16674171 | AH22: -0.66 | AI22: =SQRT(MAX(0,1-AH22^2)) -> 0.7512656 | AJ22: =IF(ISNUMBER($B$18),IF(AND($C$18=1,AH22<=-COS(PI()*$B$18)),AI22,NA()),NA()) -> #N/A | AK22: =IF(ISNUMBER($B$18),IF(AND($C$18=2,AH22<=-COS(PI()*$B$18)),AI22,NA()),NA()) -> #N/A | AL22: =IF(ISNUMBER($B$18),IF(AND($C$18=3,AH22<=-COS(PI()*$B$18)),AI22,NA()),NA()) -> #N/A | AM22: =IF(ISNUMBER($B$18),IF(AND($C$18=4,AH22<=-COS(PI()*$B$18)),AI22,NA()),NA()) -> #N/A | AN22: =IF(ISNUMBER($B$18),IF(AND($C$18=5,AH22<=-COS(PI()*$B$18)),AI22,NA()),NA()) -> #N/A | AO22: =IF(ISNUMBER($B$18),IF(AND(ISNUMBER($B$18),AH22>=MIN(0,$AH$2),AH22<=MAX(0,$AH$2)),IF($AH$2=0,0,AH22/$AH$2*$AI$2),NA()),NA()) -> 0.45462378
A23: Client Beta (Heavy Const.) | B23: =SUMIFS('Current AR'!$S$6:$S$103,'Current AR'!$A$6:$A$103,A23) -> 2.000343e+09 | C23: =SUMIFS('Prior AR'!$S$6:$S$85,'Prior AR'!$A$6:$A$85,A23) -> 1.6031727e+09 | D23: =SUMIFS('Current AR'!$V$6:$V$103,'Current AR'!$A$6:$A$103,A23,'Current AR'!$Q$6:$Q$103,"<=0") -> 4.50339e+08 | E23: =SUMIFS('Current AR'!$V$6:$V$103,'Current AR'!$A$6:$A$103,A23,'Current AR'!$Q$6:$Q$103,">0") -> 1.550004e+09 | R23: -0.64 | S23: =SQRT(MAX(0,1-R23^2)) -> 0.76837491 | T23: =IF(ISNUMBER($B$16),IF(AND($C$16=1,R23<=-COS(PI()*$B$16)),S23,NA()),NA()) -> #N/A | U23: =IF(ISNUMBER($B$16),IF(AND($C$16=2,R23<=-COS(PI()*$B$16)),S23,NA()),NA()) -> #N/A | V23: =IF(ISNUMBER($B$16),IF(AND($C$16=3,R23<=-COS(PI()*$B$16)),S23,NA()),NA()) -> #N/A | W23: =IF(ISNUMBER($B$16),IF(AND($C$16=4,R23<=-COS(PI()*$B$16)),S23,NA()),NA()) -> #N/A | X23: =IF(ISNUMBER($B$16),IF(AND($C$16=5,R23<=-COS(PI()*$B$16)),S23,NA()),NA()) -> #N/A | Y23: =IF(ISNUMBER($B$16),IF(AND(ISNUMBER($B$16),R23>=MIN(0,$R$2),R23<=MAX(0,$R$2)),IF($R$2=0,0,R23/$R$2*$S$2),NA()),NA()) -> 0.23777916 | Z23: -0.64 | AA23: =SQRT(MAX(0,1-Z23^2)) -> 0.76837491 | AB23: =IF(ISNUMBER($B$17),IF(AND($C$17=1,Z23<=-COS(PI()*$B$17)),AA23,NA()),NA()) -> #N/A | AC23: =IF(ISNUMBER($B$17),IF(AND($C$17=2,Z23<=-COS(PI()*$B$17)),AA23,NA()),NA()) -> #N/A | AD23: =IF(ISNUMBER($B$17),IF(AND($C$17=3,Z23<=-COS(PI()*$B$17)),AA23,NA()),NA()) -> #N/A | AE23: =IF(ISNUMBER($B$17),IF(AND($C$17=4,Z23<=-COS(PI()*$B$17)),AA23,NA()),NA()) -> #N/A | AF23: =IF(ISNUMBER($B$17),IF(AND($C$17=5,Z23<=-COS(PI()*$B$17)),AA23,NA()),NA()) -> #N/A | AG23: =IF(ISNUMBER($B$17),IF(AND(ISNUMBER($B$17),Z23>=MIN(0,$Z$2),Z23<=MAX(0,$Z$2)),IF($Z$2=0,0,Z23/$Z$2*$AA$2),NA()),NA()) -> 0.16168893 | AH23: -0.64 | AI23: =SQRT(MAX(0,1-AH23^2)) -> 0.76837491 | AJ23: =IF(ISNUMBER($B$18),IF(AND($C$18=1,AH23<=-COS(PI()*$B$18)),AI23,NA()),NA()) -> #N/A | AK23: =IF(ISNUMBER($B$18),IF(AND($C$18=2,AH23<=-COS(PI()*$B$18)),AI23,NA()),NA()) -> #N/A | AL23: =IF(ISNUMBER($B$18),IF(AND($C$18=3,AH23<=-COS(PI()*$B$18)),AI23,NA()),NA()) -> #N/A | AM23: =IF(ISNUMBER($B$18),IF(AND($C$18=4,AH23<=-COS(PI()*$B$18)),AI23,NA()),NA()) -> #N/A | AN23: =IF(ISNUMBER($B$18),IF(AND($C$18=5,AH23<=-COS(PI()*$B$18)),AI23,NA()),NA()) -> #N/A | AO23: =IF(ISNUMBER($B$18),IF(AND(ISNUMBER($B$18),AH23>=MIN(0,$AH$2),AH23<=MAX(0,$AH$2)),IF($AH$2=0,0,AH23/$AH$2*$AI$2),NA()),NA()) -> 0.44084731 | AW23: =IF(D23=0,"",IF(ABS(D23)>=1000000000,TEXT(D23/1000000000,IF(MOD(ROUND(D23/1000000000,2),1)=0,"0","0.00"))&" B VND",IF(ABS(D23)>=1000000,TEXT(D23/1000000,IF(MOD(ROUND(D23/1000000,2),1)=0,"0","0.00"))&" M VND",TEXT(D23/1000,IF(MOD(ROUND(D23/1000,2),1)=0,"0","0.00"))&"k"))) -> 430M VND | AX23: =IF(E23=0,"",IF(ABS(E23)>=1000000000,TEXT(E23/1000000000,IF(MOD(ROUND(E23/1000000000,2),1)=0,"0","0.00"))&" B VND",IF(ABS(E23)>=1000000,TEXT(E23/1000000,IF(MOD(ROUND(E23/1000000,2),1)=0,"0","0.00"))&" M VND",TEXT(E23/1000,IF(MOD(ROUND(E23/1000,2),1)=0,"0","0.00"))&"k"))) -> 1.48B VND
A24: Client Delta (Commercial Facade) | B24: =SUMIFS('Current AR'!$S$6:$S$103,'Current AR'!$A$6:$A$103,A24) -> 2.283114e+09 | C24: =SUMIFS('Prior AR'!$S$6:$S$85,'Prior AR'!$A$6:$A$85,A24) -> 0 | D24: =SUMIFS('Current AR'!$V$6:$V$103,'Current AR'!$A$6:$A$103,A24,'Current AR'!$Q$6:$Q$103,"<=0") -> 2.283114e+09 | E24: =SUMIFS('Current AR'!$V$6:$V$103,'Current AR'!$A$6:$A$103,A24,'Current AR'!$Q$6:$Q$103,">0") -> 0 | R24: -0.62 | S24: =SQRT(MAX(0,1-R24^2)) -> 0.78460181 | T24: =IF(ISNUMBER($B$16),IF(AND($C$16=1,R24<=-COS(PI()*$B$16)),S24,NA()),NA()) -> #N/A | U24: =IF(ISNUMBER($B$16),IF(AND($C$16=2,R24<=-COS(PI()*$B$16)),S24,NA()),NA()) -> #N/A | V24: =IF(ISNUMBER($B$16),IF(AND($C$16=3,R24<=-COS(PI()*$B$16)),S24,NA()),NA()) -> #N/A | W24: =IF(ISNUMBER($B$16),IF(AND($C$16=4,R24<=-COS(PI()*$B$16)),S24,NA()),NA()) -> #N/A | X24: =IF(ISNUMBER($B$16),IF(AND($C$16=5,R24<=-COS(PI()*$B$16)),S24,NA()),NA()) -> #N/A | Y24: =IF(ISNUMBER($B$16),IF(AND(ISNUMBER($B$16),R24>=MIN(0,$R$2),R24<=MAX(0,$R$2)),IF($R$2=0,0,R24/$R$2*$S$2),NA()),NA()) -> 0.23034856 | Z24: -0.62 | AA24: =SQRT(MAX(0,1-Z24^2)) -> 0.78460181 | AB24: =IF(ISNUMBER($B$17),IF(AND($C$17=1,Z24<=-COS(PI()*$B$17)),AA24,NA()),NA()) -> #N/A | AC24: =IF(ISNUMBER($B$17),IF(AND($C$17=2,Z24<=-COS(PI()*$B$17)),AA24,NA()),NA()) -> #N/A | AD24: =IF(ISNUMBER($B$17),IF(AND($C$17=3,Z24<=-COS(PI()*$B$17)),AA24,NA()),NA()) -> #N/A | AE24: =IF(ISNUMBER($B$17),IF(AND($C$17=4,Z24<=-COS(PI()*$B$17)),AA24,NA()),NA()) -> #N/A | AF24: =IF(ISNUMBER($B$17),IF(AND($C$17=5,Z24<=-COS(PI()*$B$17)),AA24,NA()),NA()) -> #N/A | AG24: =IF(ISNUMBER($B$17),IF(AND(ISNUMBER($B$17),Z24>=MIN(0,$Z$2),Z24<=MAX(0,$Z$2)),IF($Z$2=0,0,Z24/$Z$2*$AA$2),NA()),NA()) -> 0.15663615 | AH24: -0.62 | AI24: =SQRT(MAX(0,1-AH24^2)) -> 0.78460181 | AJ24: =IF(ISNUMBER($B$18),IF(AND($C$18=1,AH24<=-COS(PI()*$B$18)),AI24,NA()),NA()) -> #N/A | AK24: =IF(ISNUMBER($B$18),IF(AND($C$18=2,AH24<=-COS(PI()*$B$18)),AI24,NA()),NA()) -> #N/A | AL24: =IF(ISNUMBER($B$18),IF(AND($C$18=3,AH24<=-COS(PI()*$B$18)),AI24,NA()),NA()) -> #N/A | AM24: =IF(ISNUMBER($B$18),IF(AND($C$18=4,AH24<=-COS(PI()*$B$18)),AI24,NA()),NA()) -> #N/A | AN24: =IF(ISNUMBER($B$18),IF(AND($C$18=5,AH24<=-COS(PI()*$B$18)),AI24,NA()),NA()) -> #N/A | AO24: =IF(ISNUMBER($B$18),IF(AND(ISNUMBER($B$18),AH24>=MIN(0,$AH$2),AH24<=MAX(0,$AH$2)),IF($AH$2=0,0,AH24/$AH$2*$AI$2),NA()),NA()) -> 0.42707083 | AW24: =IF(D24=0,"",IF(ABS(D24)>=1000000000,TEXT(D24/1000000000,IF(MOD(ROUND(D24/1000000000,2),1)=0,"0","0.00"))&" B VND",IF(ABS(D24)>=1000000,TEXT(D24/1000000,IF(MOD(ROUND(D24/1000000,2),1)=0,"0","0.00"))&" M VND",TEXT(D24/1000,IF(MOD(ROUND(D24/1000,2),1)=0,"0","0.00"))&"k"))) -> 2.18B VND | AX24: =IF(E24=0,"",IF(ABS(E24)>=1000000000,TEXT(E24/1000000000,IF(MOD(ROUND(E24/1000000000,2),1)=0,"0","0.00"))&" B VND",IF(ABS(E24)>=1000000,TEXT(E24/1000000,IF(MOD(ROUND(E24/1000000,2),1)=0,"0","0.00"))&" M VND",TEXT(E24/1000,IF(MOD(ROUND(E24/1000,2),1)=0,"0","0.00"))&"k")))
A25: Client Alpha (Steel EPC) | B25: =SUMIFS('Current AR'!$S$6:$S$103,'Current AR'!$A$6:$A$103,A25) -> 3.9053817e+10 | C25: =SUMIFS('Prior AR'!$S$6:$S$85,'Prior AR'!$A$6:$A$85,A25) -> 2.3724533e+10 | D25: =SUMIFS('Current AR'!$V$6:$V$103,'Current AR'!$A$6:$A$103,A25,'Current AR'!$Q$6:$Q$103,"<=0") -> 3.6498405e+10 | E25: =SUMIFS('Current AR'!$V$6:$V$103,'Current AR'!$A$6:$A$103,A25,'Current AR'!$Q$6:$Q$103,">0") -> 2.555412e+09 | R25: -0.6 | S25: =SQRT(MAX(0,1-R25^2)) -> 0.8 | T25: =IF(ISNUMBER($B$16),IF(AND($C$16=1,R25<=-COS(PI()*$B$16)),S25,NA()),NA()) -> #N/A | U25: =IF(ISNUMBER($B$16),IF(AND($C$16=2,R25<=-COS(PI()*$B$16)),S25,NA()),NA()) -> #N/A | V25: =IF(ISNUMBER($B$16),IF(AND($C$16=3,R25<=-COS(PI()*$B$16)),S25,NA()),NA()) -> #N/A | W25: =IF(ISNUMBER($B$16),IF(AND($C$16=4,R25<=-COS(PI()*$B$16)),S25,NA()),NA()) -> #N/A | X25: =IF(ISNUMBER($B$16),IF(AND($C$16=5,R25<=-COS(PI()*$B$16)),S25,NA()),NA()) -> #N/A | Y25: =IF(ISNUMBER($B$16),IF(AND(ISNUMBER($B$16),R25>=MIN(0,$R$2),R25<=MAX(0,$R$2)),IF($R$2=0,0,R25/$R$2*$S$2),NA()),NA()) -> 0.22291796 | Z25: -0.6 | AA25: =SQRT(MAX(0,1-Z25^2)) -> 0.8 | AB25: =IF(ISNUMBER($B$17),IF(AND($C$17=1,Z25<=-COS(PI()*$B$17)),AA25,NA()),NA()) -> #N/A | AC25: =IF(ISNUMBER($B$17),IF(AND($C$17=2,Z25<=-COS(PI()*$B$17)),AA25,NA()),NA()) -> #N/A | AD25: =IF(ISNUMBER($B$17),IF(AND($C$17=3,Z25<=-COS(PI()*$B$17)),AA25,NA()),NA()) -> #N/A | AE25: =IF(ISNUMBER($B$17),IF(AND($C$17=4,Z25<=-COS(PI()*$B$17)),AA25,NA()),NA()) -> #N/A | AF25: =IF(ISNUMBER($B$17),IF(AND($C$17=5,Z25<=-COS(PI()*$B$17)),AA25,NA()),NA()) -> #N/A | AG25: =IF(ISNUMBER($B$17),IF(AND(ISNUMBER($B$17),Z25>=MIN(0,$Z$2),Z25<=MAX(0,$Z$2)),IF($Z$2=0,0,Z25/$Z$2*$AA$2),NA()),NA()) -> 0.15158337 | AH25: -0.6 | AI25: =SQRT(MAX(0,1-AH25^2)) -> 0.8 | AJ25: =IF(ISNUMBER($B$18),IF(AND($C$18=1,AH25<=-COS(PI()*$B$18)),AI25,NA()),NA()) -> #N/A | AK25: =IF(ISNUMBER($B$18),IF(AND($C$18=2,AH25<=-COS(PI()*$B$18)),AI25,NA()),NA()) -> #N/A | AL25: =IF(ISNUMBER($B$18),IF(AND($C$18=3,AH25<=-COS(PI()*$B$18)),AI25,NA()),NA()) -> #N/A | AM25: =IF(ISNUMBER($B$18),IF(AND($C$18=4,AH25<=-COS(PI()*$B$18)),AI25,NA()),NA()) -> #N/A | AN25: =IF(ISNUMBER($B$18),IF(AND($C$18=5,AH25<=-COS(PI()*$B$18)),AI25,NA()),NA()) -> #N/A | AO25: =IF(ISNUMBER($B$18),IF(AND(ISNUMBER($B$18),AH25>=MIN(0,$AH$2),AH25<=MAX(0,$AH$2)),IF($AH$2=0,0,AH25/$AH$2*$AI$2),NA()),NA()) -> 0.41329435 | AW25: =IF(D25=0,"",IF(ABS(D25)>=1000000000,TEXT(D25/1000000000,IF(MOD(ROUND(D25/1000000000,2),1)=0,"0","0.00"))&" B VND",IF(ABS(D25)>=1000000,TEXT(D25/1000000,IF(MOD(ROUND(D25/1000000,2),1)=0,"0","0.00"))&" M VND",TEXT(D25/1000,IF(MOD(ROUND(D25/1000,2),1)=0,"0","0.00"))&"k"))) -> 34.85B VND | AX25: =IF(E25=0,"",IF(ABS(E25)>=1000000000,TEXT(E25/1000000000,IF(MOD(ROUND(E25/1000000000,2),1)=0,"0","0.00"))&" B VND",IF(ABS(E25)>=1000000,TEXT(E25/1000000,IF(MOD(ROUND(E25/1000000,2),1)=0,"0","0.00"))&" M VND",TEXT(E25/1000,IF(MOD(ROUND(E25/1000,2),1)=0,"0","0.00"))&"k"))) -> 2.44B VND
A26: Client Alpha Sub-Contract | B26: =SUMIFS('Current AR'!$S$6:$S$103,'Current AR'!$A$6:$A$103,A26) -> 3.6531814e+09 | C26: =SUMIFS('Prior AR'!$S$6:$S$85,'Prior AR'!$A$6:$A$85,A26) -> 4.5051769e+09 | D26: =SUMIFS('Current AR'!$V$6:$V$103,'Current AR'!$A$6:$A$103,A26,'Current AR'!$Q$6:$Q$103,"<=0") -> 1.9775014e+09 | E26: =SUMIFS('Current AR'!$V$6:$V$103,'Current AR'!$A$6:$A$103,A26,'Current AR'!$Q$6:$Q$103,">0") -> 1.67568e+09 | R26: -0.58 | S26: =SQRT(MAX(0,1-R26^2)) -> 0.81461647 | T26: =IF(ISNUMBER($B$16),IF(AND($C$16=1,R26<=-COS(PI()*$B$16)),S26,NA()),NA()) -> #N/A | U26: =IF(ISNUMBER($B$16),IF(AND($C$16=2,R26<=-COS(PI()*$B$16)),S26,NA()),NA()) -> #N/A | V26: =IF(ISNUMBER($B$16),IF(AND($C$16=3,R26<=-COS(PI()*$B$16)),S26,NA()),NA()) -> #N/A | W26: =IF(ISNUMBER($B$16),IF(AND($C$16=4,R26<=-COS(PI()*$B$16)),S26,NA()),NA()) -> #N/A | X26: =IF(ISNUMBER($B$16),IF(AND($C$16=5,R26<=-COS(PI()*$B$16)),S26,NA()),NA()) -> #N/A | Y26: =IF(ISNUMBER($B$16),IF(AND(ISNUMBER($B$16),R26>=MIN(0,$R$2),R26<=MAX(0,$R$2)),IF($R$2=0,0,R26/$R$2*$S$2),NA()),NA()) -> 0.21548736 | Z26: -0.58 | AA26: =SQRT(MAX(0,1-Z26^2)) -> 0.81461647 | AB26: =IF(ISNUMBER($B$17),IF(AND($C$17=1,Z26<=-COS(PI()*$B$17)),AA26,NA()),NA()) -> #N/A | AC26: =IF(ISNUMBER($B$17),IF(AND($C$17=2,Z26<=-COS(PI()*$B$17)),AA26,NA()),NA()) -> #N/A | AD26: =IF(ISNUMBER($B$17),IF(AND($C$17=3,Z26<=-COS(PI()*$B$17)),AA26,NA()),NA()) -> #N/A | AE26: =IF(ISNUMBER($B$17),IF(AND($C$17=4,Z26<=-COS(PI()*$B$17)),AA26,NA()),NA()) -> #N/A | AF26: =IF(ISNUMBER($B$17),IF(AND($C$17=5,Z26<=-COS(PI()*$B$17)),AA26,NA()),NA()) -> #N/A | AG26: =IF(ISNUMBER($B$17),IF(AND(ISNUMBER($B$17),Z26>=MIN(0,$Z$2),Z26<=MAX(0,$Z$2)),IF($Z$2=0,0,Z26/$Z$2*$AA$2),NA()),NA()) -> 0.14653059 | AH26: -0.58 | AI26: =SQRT(MAX(0,1-AH26^2)) -> 0.81461647 | AJ26: =IF(ISNUMBER($B$18),IF(AND($C$18=1,AH26<=-COS(PI()*$B$18)),AI26,NA()),NA()) -> #N/A | AK26: =IF(ISNUMBER($B$18),IF(AND($C$18=2,AH26<=-COS(PI()*$B$18)),AI26,NA()),NA()) -> #N/A | AL26: =IF(ISNUMBER($B$18),IF(AND($C$18=3,AH26<=-COS(PI()*$B$18)),AI26,NA()),NA()) -> #N/A | AM26: =IF(ISNUMBER($B$18),IF(AND($C$18=4,AH26<=-COS(PI()*$B$18)),AI26,NA()),NA()) -> #N/A | AN26: =IF(ISNUMBER($B$18),IF(AND($C$18=5,AH26<=-COS(PI()*$B$18)),AI26,NA()),NA()) -> #N/A | AO26: =IF(ISNUMBER($B$18),IF(AND(ISNUMBER($B$18),AH26>=MIN(0,$AH$2),AH26<=MAX(0,$AH$2)),IF($AH$2=0,0,AH26/$AH$2*$AI$2),NA()),NA()) -> 0.39951787 | AW26: =IF(D26=0,"",IF(ABS(D26)>=1000000000,TEXT(D26/1000000000,IF(MOD(ROUND(D26/1000000000,2),1)=0,"0","0.00"))&" B VND",IF(ABS(D26)>=1000000,TEXT(D26/1000000,IF(MOD(ROUND(D26/1000000,2),1)=0,"0","0.00"))&" M VND",TEXT(D26/1000,IF(MOD(ROUND(D26/1000,2),1)=0,"0","0.00"))&"k"))) -> 1.89B VND | AX26: =IF(E26=0,"",IF(ABS(E26)>=1000000000,TEXT(E26/1000000000,IF(MOD(ROUND(E26/1000000000,2),1)=0,"0","0.00"))&" B VND",IF(ABS(E26)>=1000000,TEXT(E26/1000000,IF(MOD(ROUND(E26/1000000,2),1)=0,"0","0.00"))&" M VND",TEXT(E26/1000,IF(MOD(ROUND(E26/1000,2),1)=0,"0","0.00"))&"k"))) -> 1.60B VND
A27: Client Epsilon (Equipment) | B27: =SUMIFS('Current AR'!$S$6:$S$103,'Current AR'!$A$6:$A$103,A27) -> 43462950 | C27: =SUMIFS('Prior AR'!$S$6:$S$85,'Prior AR'!$A$6:$A$85,A27) -> 0 | D27: =SUMIFS('Current AR'!$V$6:$V$103,'Current AR'!$A$6:$A$103,A27,'Current AR'!$Q$6:$Q$103,"<=0") -> 43462950 | E27: =SUMIFS('Current AR'!$V$6:$V$103,'Current AR'!$A$6:$A$103,A27,'Current AR'!$Q$6:$Q$103,">0") -> 0 | R27: -0.56 | S27: =SQRT(MAX(0,1-R27^2)) -> 0.82849261 | T27: =IF(ISNUMBER($B$16),IF(AND($C$16=1,R27<=-COS(PI()*$B$16)),S27,NA()),NA()) -> #N/A | U27: =IF(ISNUMBER($B$16),IF(AND($C$16=2,R27<=-COS(PI()*$B$16)),S27,NA()),NA()) -> #N/A | V27: =IF(ISNUMBER($B$16),IF(AND($C$16=3,R27<=-COS(PI()*$B$16)),S27,NA()),NA()) -> #N/A | W27: =IF(ISNUMBER($B$16),IF(AND($C$16=4,R27<=-COS(PI()*$B$16)),S27,NA()),NA()) -> #N/A | X27: =IF(ISNUMBER($B$16),IF(AND($C$16=5,R27<=-COS(PI()*$B$16)),S27,NA()),NA()) -> #N/A | Y27: =IF(ISNUMBER($B$16),IF(AND(ISNUMBER($B$16),R27>=MIN(0,$R$2),R27<=MAX(0,$R$2)),IF($R$2=0,0,R27/$R$2*$S$2),NA()),NA()) -> 0.20805676 | Z27: -0.56 | AA27: =SQRT(MAX(0,1-Z27^2)) -> 0.82849261 | AB27: =IF(ISNUMBER($B$17),IF(AND($C$17=1,Z27<=-COS(PI()*$B$17)),AA27,NA()),NA()) -> #N/A | AC27: =IF(ISNUMBER($B$17),IF(AND($C$17=2,Z27<=-COS(PI()*$B$17)),AA27,NA()),NA()) -> #N/A | AD27: =IF(ISNUMBER($B$17),IF(AND($C$17=3,Z27<=-COS(PI()*$B$17)),AA27,NA()),NA()) -> #N/A | AE27: =IF(ISNUMBER($B$17),IF(AND($C$17=4,Z27<=-COS(PI()*$B$17)),AA27,NA()),NA()) -> #N/A | AF27: =IF(ISNUMBER($B$17),IF(AND($C$17=5,Z27<=-COS(PI()*$B$17)),AA27,NA()),NA()) -> #N/A | AG27: =IF(ISNUMBER($B$17),IF(AND(ISNUMBER($B$17),Z27>=MIN(0,$Z$2),Z27<=MAX(0,$Z$2)),IF($Z$2=0,0,Z27/$Z$2*$AA$2),NA()),NA()) -> 0.14147781 | AH27: -0.56 | AI27: =SQRT(MAX(0,1-AH27^2)) -> 0.82849261 | AJ27: =IF(ISNUMBER($B$18),IF(AND($C$18=1,AH27<=-COS(PI()*$B$18)),AI27,NA()),NA()) -> #N/A | AK27: =IF(ISNUMBER($B$18),IF(AND($C$18=2,AH27<=-COS(PI()*$B$18)),AI27,NA()),NA()) -> #N/A | AL27: =IF(ISNUMBER($B$18),IF(AND($C$18=3,AH27<=-COS(PI()*$B$18)),AI27,NA()),NA()) -> #N/A | AM27: =IF(ISNUMBER($B$18),IF(AND($C$18=4,AH27<=-COS(PI()*$B$18)),AI27,NA()),NA()) -> #N/A | AN27: =IF(ISNUMBER($B$18),IF(AND($C$18=5,AH27<=-COS(PI()*$B$18)),AI27,NA()),NA()) -> #N/A | AO27: =IF(ISNUMBER($B$18),IF(AND(ISNUMBER($B$18),AH27>=MIN(0,$AH$2),AH27<=MAX(0,$AH$2)),IF($AH$2=0,0,AH27/$AH$2*$AI$2),NA()),NA()) -> 0.38574139 | AW27: =IF(D27=0,"",IF(ABS(D27)>=1000000000,TEXT(D27/1000000000,IF(MOD(ROUND(D27/1000000000,2),1)=0,"0","0.00"))&" B VND",IF(ABS(D27)>=1000000,TEXT(D27/1000000,IF(MOD(ROUND(D27/1000000,2),1)=0,"0","0.00"))&" M VND",TEXT(D27/1000,IF(MOD(ROUND(D27/1000,2),1)=0,"0","0.00"))&"k"))) -> 41.50M VND | AX27: =IF(E27=0,"",IF(ABS(E27)>=1000000000,TEXT(E27/1000000000,IF(MOD(ROUND(E27/1000000000,2),1)=0,"0","0.00"))&" B VND",IF(ABS(E27)>=1000000,TEXT(E27/1000000,IF(MOD(ROUND(E27/1000000,2),1)=0,"0","0.00"))&" M VND",TEXT(E27/1000,IF(MOD(ROUND(E27/1000,2),1)=0,"0","0.00"))&"k")))
A28: Client Zeta (Building Tech) | B28: =SUMIFS('Current AR'!$S$6:$S$103,'Current AR'!$A$6:$A$103,A28) -> 324663 | C28: =SUMIFS('Prior AR'!$S$6:$S$85,'Prior AR'!$A$6:$A$85,A28) -> 333943.13 | D28: =SUMIFS('Current AR'!$V$6:$V$103,'Current AR'!$A$6:$A$103,A28,'Current AR'!$Q$6:$Q$103,"<=0") -> 324663 | E28: =SUMIFS('Current AR'!$V$6:$V$103,'Current AR'!$A$6:$A$103,A28,'Current AR'!$Q$6:$Q$103,">0") -> 0 | R28: -0.54 | S28: =SQRT(MAX(0,1-R28^2)) -> 0.84166502 | T28: =IF(ISNUMBER($B$16),IF(AND($C$16=1,R28<=-COS(PI()*$B$16)),S28,NA()),NA()) -> #N/A | U28: =IF(ISNUMBER($B$16),IF(AND($C$16=2,R28<=-COS(PI()*$B$16)),S28,NA()),NA()) -> #N/A | V28: =IF(ISNUMBER($B$16),IF(AND($C$16=3,R28<=-COS(PI()*$B$16)),S28,NA()),NA()) -> #N/A | W28: =IF(ISNUMBER($B$16),IF(AND($C$16=4,R28<=-COS(PI()*$B$16)),S28,NA()),NA()) -> #N/A | X28: =IF(ISNUMBER($B$16),IF(AND($C$16=5,R28<=-COS(PI()*$B$16)),S28,NA()),NA()) -> #N/A | Y28: =IF(ISNUMBER($B$16),IF(AND(ISNUMBER($B$16),R28>=MIN(0,$R$2),R28<=MAX(0,$R$2)),IF($R$2=0,0,R28/$R$2*$S$2),NA()),NA()) -> 0.20062616 | Z28: -0.54 | AA28: =SQRT(MAX(0,1-Z28^2)) -> 0.84166502 | AB28: =IF(ISNUMBER($B$17),IF(AND($C$17=1,Z28<=-COS(PI()*$B$17)),AA28,NA()),NA()) -> #N/A | AC28: =IF(ISNUMBER($B$17),IF(AND($C$17=2,Z28<=-COS(PI()*$B$17)),AA28,NA()),NA()) -> #N/A | AD28: =IF(ISNUMBER($B$17),IF(AND($C$17=3,Z28<=-COS(PI()*$B$17)),AA28,NA()),NA()) -> #N/A | AE28: =IF(ISNUMBER($B$17),IF(AND($C$17=4,Z28<=-COS(PI()*$B$17)),AA28,NA()),NA()) -> #N/A | AF28: =IF(ISNUMBER($B$17),IF(AND($C$17=5,Z28<=-COS(PI()*$B$17)),AA28,NA()),NA()) -> #N/A | AG28: =IF(ISNUMBER($B$17),IF(AND(ISNUMBER($B$17),Z28>=MIN(0,$Z$2),Z28<=MAX(0,$Z$2)),IF($Z$2=0,0,Z28/$Z$2*$AA$2),NA()),NA()) -> 0.13642503 | AH28: -0.54 | AI28: =SQRT(MAX(0,1-AH28^2)) -> 0.84166502 | AJ28: =IF(ISNUMBER($B$18),IF(AND($C$18=1,AH28<=-COS(PI()*$B$18)),AI28,NA()),NA()) -> #N/A | AK28: =IF(ISNUMBER($B$18),IF(AND($C$18=2,AH28<=-COS(PI()*$B$18)),AI28,NA()),NA()) -> #N/A | AL28: =IF(ISNUMBER($B$18),IF(AND($C$18=3,AH28<=-COS(PI()*$B$18)),AI28,NA()),NA()) -> #N/A | AM28: =IF(ISNUMBER($B$18),IF(AND($C$18=4,AH28<=-COS(PI()*$B$18)),AI28,NA()),NA()) -> #N/A | AN28: =IF(ISNUMBER($B$18),IF(AND($C$18=5,AH28<=-COS(PI()*$B$18)),AI28,NA()),NA()) -> #N/A | AO28: =IF(ISNUMBER($B$18),IF(AND(ISNUMBER($B$18),AH28>=MIN(0,$AH$2),AH28<=MAX(0,$AH$2)),IF($AH$2=0,0,AH28/$AH$2*$AI$2),NA()),NA()) -> 0.37196491 | AW28: =IF(D28=0,"",IF(ABS(D28)>=1000000000,TEXT(D28/1000000000,IF(MOD(ROUND(D28/1000000000,2),1)=0,"0","0.00"))&" B VND",IF(ABS(D28)>=1000000,TEXT(D28/1000000,IF(MOD(ROUND(D28/1000000,2),1)=0,"0","0.00"))&" M VND",TEXT(D28/1000,IF(MOD(ROUND(D28/1000,2),1)=0,"0","0.00"))&"k"))) -> 310k | AX28: =IF(E28=0,"",IF(ABS(E28)>=1000000000,TEXT(E28/1000000000,IF(MOD(ROUND(E28/1000000000,2),1)=0,"0","0.00"))&" B VND",IF(ABS(E28)>=1000000,TEXT(E28/1000000,IF(MOD(ROUND(E28/1000000,2),1)=0,"0","0.00"))&" M VND",TEXT(E28/1000,IF(MOD(ROUND(E28/1000,2),1)=0,"0","0.00"))&"k")))
A29: Client Gamma (Offshore Energy) | B29: =SUMIFS('Current AR'!$S$6:$S$103,'Current AR'!$A$6:$A$103,A29) -> 4.021632e+09 | C29: =SUMIFS('Prior AR'!$S$6:$S$85,'Prior AR'!$A$6:$A$85,A29) -> 4.0993038e+09 | D29: =SUMIFS('Current AR'!$V$6:$V$103,'Current AR'!$A$6:$A$103,A29,'Current AR'!$Q$6:$Q$103,"<=0") -> 0 | E29: =SUMIFS('Current AR'!$V$6:$V$103,'Current AR'!$A$6:$A$103,A29,'Current AR'!$Q$6:$Q$103,">0") -> 4.021632e+09 | R29: -0.52 | S29: =SQRT(MAX(0,1-R29^2)) -> 0.85416626 | T29: =IF(ISNUMBER($B$16),IF(AND($C$16=1,R29<=-COS(PI()*$B$16)),S29,NA()),NA()) -> #N/A | U29: =IF(ISNUMBER($B$16),IF(AND($C$16=2,R29<=-COS(PI()*$B$16)),S29,NA()),NA()) -> #N/A | V29: =IF(ISNUMBER($B$16),IF(AND($C$16=3,R29<=-COS(PI()*$B$16)),S29,NA()),NA()) -> #N/A | W29: =IF(ISNUMBER($B$16),IF(AND($C$16=4,R29<=-COS(PI()*$B$16)),S29,NA()),NA()) -> #N/A | X29: =IF(ISNUMBER($B$16),IF(AND($C$16=5,R29<=-COS(PI()*$B$16)),S29,NA()),NA()) -> #N/A | Y29: =IF(ISNUMBER($B$16),IF(AND(ISNUMBER($B$16),R29>=MIN(0,$R$2),R29<=MAX(0,$R$2)),IF($R$2=0,0,R29/$R$2*$S$2),NA()),NA()) -> 0.19319556 | Z29: -0.52 | AA29: =SQRT(MAX(0,1-Z29^2)) -> 0.85416626 | AB29: =IF(ISNUMBER($B$17),IF(AND($C$17=1,Z29<=-COS(PI()*$B$17)),AA29,NA()),NA()) -> #N/A | AC29: =IF(ISNUMBER($B$17),IF(AND($C$17=2,Z29<=-COS(PI()*$B$17)),AA29,NA()),NA()) -> #N/A | AD29: =IF(ISNUMBER($B$17),IF(AND($C$17=3,Z29<=-COS(PI()*$B$17)),AA29,NA()),NA()) -> #N/A | AE29: =IF(ISNUMBER($B$17),IF(AND($C$17=4,Z29<=-COS(PI()*$B$17)),AA29,NA()),NA()) -> #N/A | AF29: =IF(ISNUMBER($B$17),IF(AND($C$17=5,Z29<=-COS(PI()*$B$17)),AA29,NA()),NA()) -> #N/A | AG29: =IF(ISNUMBER($B$17),IF(AND(ISNUMBER($B$17),Z29>=MIN(0,$Z$2),Z29<=MAX(0,$Z$2)),IF($Z$2=0,0,Z29/$Z$2*$AA$2),NA()),NA()) -> 0.13137226 | AH29: -0.52 | AI29: =SQRT(MAX(0,1-AH29^2)) -> 0.85416626 | AJ29: =IF(ISNUMBER($B$18),IF(AND($C$18=1,AH29<=-COS(PI()*$B$18)),AI29,NA()),NA()) -> #N/A | AK29: =IF(ISNUMBER($B$18),IF(AND($C$18=2,AH29<=-COS(PI()*$B$18)),AI29,NA()),NA()) -> #N/A | AL29: =IF(ISNUMBER($B$18),IF(AND($C$18=3,AH29<=-COS(PI()*$B$18)),AI29,NA()),NA()) -> #N/A | AM29: =IF(ISNUMBER($B$18),IF(AND($C$18=4,AH29<=-COS(PI()*$B$18)),AI29,NA()),NA()) -> #N/A | AN29: =IF(ISNUMBER($B$18),IF(AND($C$18=5,AH29<=-COS(PI()*$B$18)),AI29,NA()),NA()) -> #N/A | AO29: =IF(ISNUMBER($B$18),IF(AND(ISNUMBER($B$18),AH29>=MIN(0,$AH$2),AH29<=MAX(0,$AH$2)),IF($AH$2=0,0,AH29/$AH$2*$AI$2),NA()),NA()) -> 0.35818844 | AW29: =IF(D29=0,"",IF(ABS(D29)>=1000000000,TEXT(D29/1000000000,IF(MOD(ROUND(D29/1000000000,2),1)=0,"0","0.00"))&" B VND",IF(ABS(D29)>=1000000,TEXT(D29/1000000,IF(MOD(ROUND(D29/1000000,2),1)=0,"0","0.00"))&" M VND",TEXT(D29/1000,IF(MOD(ROUND(D29/1000,2),1)=0,"0","0.00"))&"k"))) | AX29: =IF(E29=0,"",IF(ABS(E29)>=1000000000,TEXT(E29/1000000000,IF(MOD(ROUND(E29/1000000000,2),1)=0,"0","0.00"))&" B VND",IF(ABS(E29)>=1000000,TEXT(E29/1000000,IF(MOD(ROUND(E29/1000000,2),1)=0,"0","0.00"))&" M VND",TEXT(E29/1000,IF(MOD(ROUND(E29/1000,2),1)=0,"0","0.00"))&"k"))) -> 3.84B VND
R30: -0.5 | S30: =SQRT(MAX(0,1-R30^2)) -> 0.8660254 | T30: =IF(ISNUMBER($B$16),IF(AND($C$16=1,R30<=-COS(PI()*$B$16)),S30,NA()),NA()) -> #N/A | U30: =IF(ISNUMBER($B$16),IF(AND($C$16=2,R30<=-COS(PI()*$B$16)),S30,NA()),NA()) -> #N/A | V30: =IF(ISNUMBER($B$16),IF(AND($C$16=3,R30<=-COS(PI()*$B$16)),S30,NA()),NA()) -> #N/A | W30: =IF(ISNUMBER($B$16),IF(AND($C$16=4,R30<=-COS(PI()*$B$16)),S30,NA()),NA()) -> #N/A | X30: =IF(ISNUMBER($B$16),IF(AND($C$16=5,R30<=-COS(PI()*$B$16)),S30,NA()),NA()) -> #N/A | Y30: =IF(ISNUMBER($B$16),IF(AND(ISNUMBER($B$16),R30>=MIN(0,$R$2),R30<=MAX(0,$R$2)),IF($R$2=0,0,R30/$R$2*$S$2),NA()),NA()) -> 0.18576497 | Z30: -0.5 | AA30: =SQRT(MAX(0,1-Z30^2)) -> 0.8660254 | AB30: =IF(ISNUMBER($B$17),IF(AND($C$17=1,Z30<=-COS(PI()*$B$17)),AA30,NA()),NA()) -> #N/A | AC30: =IF(ISNUMBER($B$17),IF(AND($C$17=2,Z30<=-COS(PI()*$B$17)),AA30,NA()),NA()) -> #N/A | AD30: =IF(ISNUMBER($B$17),IF(AND($C$17=3,Z30<=-COS(PI()*$B$17)),AA30,NA()),NA()) -> #N/A | AE30: =IF(ISNUMBER($B$17),IF(AND($C$17=4,Z30<=-COS(PI()*$B$17)),AA30,NA()),NA()) -> #N/A | AF30: =IF(ISNUMBER($B$17),IF(AND($C$17=5,Z30<=-COS(PI()*$B$17)),AA30,NA()),NA()) -> #N/A | AG30: =IF(ISNUMBER($B$17),IF(AND(ISNUMBER($B$17),Z30>=MIN(0,$Z$2),Z30<=MAX(0,$Z$2)),IF($Z$2=0,0,Z30/$Z$2*$AA$2),NA()),NA()) -> 0.12631948 | AH30: -0.5 | AI30: =SQRT(MAX(0,1-AH30^2)) -> 0.8660254 | AJ30: =IF(ISNUMBER($B$18),IF(AND($C$18=1,AH30<=-COS(PI()*$B$18)),AI30,NA()),NA()) -> #N/A | AK30: =IF(ISNUMBER($B$18),IF(AND($C$18=2,AH30<=-COS(PI()*$B$18)),AI30,NA()),NA()) -> #N/A | AL30: =IF(ISNUMBER($B$18),IF(AND($C$18=3,AH30<=-COS(PI()*$B$18)),AI30,NA()),NA()) -> #N/A | AM30: =IF(ISNUMBER($B$18),IF(AND($C$18=4,AH30<=-COS(PI()*$B$18)),AI30,NA()),NA()) -> #N/A | AN30: =IF(ISNUMBER($B$18),IF(AND($C$18=5,AH30<=-COS(PI()*$B$18)),AI30,NA()),NA()) -> #N/A | AO30: =IF(ISNUMBER($B$18),IF(AND(ISNUMBER($B$18),AH30>=MIN(0,$AH$2),AH30<=MAX(0,$AH$2)),IF($AH$2=0,0,AH30/$AH$2*$AI$2),NA()),NA()) -> 0.34441196
A31: Senior Sales Rep 1 | B31: =SUMIFS('Current AR'!$S$6:$S$103,'Current AR'!$J$6:$J$103,A31) -> 1.4614668e+10 | C31: =SUMIFS('Prior AR'!$S$6:$S$85,'Prior AR'!$J$6:$J$85,A31) -> 1.4415883e+10 | D31: =SUMIFS('Current AR'!$V$6:$V$103,'Current AR'!$J$6:$J$103,A31,'Current AR'!$Q$6:$Q$103,"<=0") -> 1.0509252e+10 | E31: =SUMIFS('Current AR'!$V$6:$V$103,'Current AR'!$J$6:$J$103,A31,'Current AR'!$Q$6:$Q$103,">0") -> 4.105416e+09 | R31: -0.48 | S31: =SQRT(MAX(0,1-R31^2)) -> 0.87726849 | T31: =IF(ISNUMBER($B$16),IF(AND($C$16=1,R31<=-COS(PI()*$B$16)),S31,NA()),NA()) -> #N/A | U31: =IF(ISNUMBER($B$16),IF(AND($C$16=2,R31<=-COS(PI()*$B$16)),S31,NA()),NA()) -> #N/A | V31: =IF(ISNUMBER($B$16),IF(AND($C$16=3,R31<=-COS(PI()*$B$16)),S31,NA()),NA()) -> #N/A | W31: =IF(ISNUMBER($B$16),IF(AND($C$16=4,R31<=-COS(PI()*$B$16)),S31,NA()),NA()) -> #N/A | X31: =IF(ISNUMBER($B$16),IF(AND($C$16=5,R31<=-COS(PI()*$B$16)),S31,NA()),NA()) -> #N/A | Y31: =IF(ISNUMBER($B$16),IF(AND(ISNUMBER($B$16),R31>=MIN(0,$R$2),R31<=MAX(0,$R$2)),IF($R$2=0,0,R31/$R$2*$S$2),NA()),NA()) -> 0.17833437 | Z31: -0.48 | AA31: =SQRT(MAX(0,1-Z31^2)) -> 0.87726849 | AB31: =IF(ISNUMBER($B$17),IF(AND($C$17=1,Z31<=-COS(PI()*$B$17)),AA31,NA()),NA()) -> #N/A | AC31: =IF(ISNUMBER($B$17),IF(AND($C$17=2,Z31<=-COS(PI()*$B$17)),AA31,NA()),NA()) -> #N/A | AD31: =IF(ISNUMBER($B$17),IF(AND($C$17=3,Z31<=-COS(PI()*$B$17)),AA31,NA()),NA()) -> #N/A | AE31: =IF(ISNUMBER($B$17),IF(AND($C$17=4,Z31<=-COS(PI()*$B$17)),AA31,NA()),NA()) -> #N/A | AF31: =IF(ISNUMBER($B$17),IF(AND($C$17=5,Z31<=-COS(PI()*$B$17)),AA31,NA()),NA()) -> #N/A | AG31: =IF(ISNUMBER($B$17),IF(AND(ISNUMBER($B$17),Z31>=MIN(0,$Z$2),Z31<=MAX(0,$Z$2)),IF($Z$2=0,0,Z31/$Z$2*$AA$2),NA()),NA()) -> 0.1212667 | AH31: -0.48 | AI31: =SQRT(MAX(0,1-AH31^2)) -> 0.87726849 | AJ31: =IF(ISNUMBER($B$18),IF(AND($C$18=1,AH31<=-COS(PI()*$B$18)),AI31,NA()),NA()) -> #N/A | AK31: =IF(ISNUMBER($B$18),IF(AND($C$18=2,AH31<=-COS(PI()*$B$18)),AI31,NA()),NA()) -> #N/A | AL31: =IF(ISNUMBER($B$18),IF(AND($C$18=3,AH31<=-COS(PI()*$B$18)),AI31,NA()),NA()) -> #N/A | AM31: =IF(ISNUMBER($B$18),IF(AND($C$18=4,AH31<=-COS(PI()*$B$18)),AI31,NA()),NA()) -> #N/A | AN31: =IF(ISNUMBER($B$18),IF(AND($C$18=5,AH31<=-COS(PI()*$B$18)),AI31,NA()),NA()) -> #N/A | AO31: =IF(ISNUMBER($B$18),IF(AND(ISNUMBER($B$18),AH31>=MIN(0,$AH$2),AH31<=MAX(0,$AH$2)),IF($AH$2=0,0,AH31/$AH$2*$AI$2),NA()),NA()) -> 0.33063548 | AY31: =IF(D31=0,"",IF(ABS(D31)>=1000000000,TEXT(D31/1000000000,IF(MOD(ROUND(D31/1000000000,2),1)=0,"0","0.00"))&" B VND",IF(ABS(D31)>=1000000,TEXT(D31/1000000,IF(MOD(ROUND(D31/1000000,2),1)=0,"0","0.00"))&" M VND",TEXT(D31/1000,IF(MOD(ROUND(D31/1000,2),1)=0,"0","0.00"))&"k"))) -> 10.03B VND | AZ31: =IF(E31=0,"",IF(ABS(E31)>=1000000000,TEXT(E31/1000000000,IF(MOD(ROUND(E31/1000000000,2),1)=0,"0","0.00"))&" B VND",IF(ABS(E31)>=1000000,TEXT(E31/1000000,IF(MOD(ROUND(E31/1000000,2),1)=0,"0","0.00"))&" M VND",TEXT(E31/1000,IF(MOD(ROUND(E31/1000,2),1)=0,"0","0.00"))&"k"))) -> 3.92B VND | BD31: =D31 -> 1.0509252e+10 | BE31: =E31 -> 4.105416e+09 | BF31: =A31 -> Senior Sales Rep 1 | BG31: =AY31 -> 10.03B VND | BH31: =AZ31 -> 3.92B VND
A32: Sales Rep 6 | B32: =SUMIFS('Current AR'!$S$6:$S$103,'Current AR'!$J$6:$J$103,A32) -> 2.283114e+09 | C32: =SUMIFS('Prior AR'!$S$6:$S$85,'Prior AR'!$J$6:$J$85,A32) -> 0 | D32: =SUMIFS('Current AR'!$V$6:$V$103,'Current AR'!$J$6:$J$103,A32,'Current AR'!$Q$6:$Q$103,"<=0") -> 2.283114e+09 | E32: =SUMIFS('Current AR'!$V$6:$V$103,'Current AR'!$J$6:$J$103,A32,'Current AR'!$Q$6:$Q$103,">0") -> 0 | R32: -0.46 | S32: =SQRT(MAX(0,1-R32^2)) -> 0.88791892 | T32: =IF(ISNUMBER($B$16),IF(AND($C$16=1,R32<=-COS(PI()*$B$16)),S32,NA()),NA()) -> #N/A | U32: =IF(ISNUMBER($B$16),IF(AND($C$16=2,R32<=-COS(PI()*$B$16)),S32,NA()),NA()) -> #N/A | V32: =IF(ISNUMBER($B$16),IF(AND($C$16=3,R32<=-COS(PI()*$B$16)),S32,NA()),NA()) -> #N/A | W32: =IF(ISNUMBER($B$16),IF(AND($C$16=4,R32<=-COS(PI()*$B$16)),S32,NA()),NA()) -> #N/A | X32: =IF(ISNUMBER($B$16),IF(AND($C$16=5,R32<=-COS(PI()*$B$16)),S32,NA()),NA()) -> #N/A | Y32: =IF(ISNUMBER($B$16),IF(AND(ISNUMBER($B$16),R32>=MIN(0,$R$2),R32<=MAX(0,$R$2)),IF($R$2=0,0,R32/$R$2*$S$2),NA()),NA()) -> 0.17090377 | Z32: -0.46 | AA32: =SQRT(MAX(0,1-Z32^2)) -> 0.88791892 | AB32: =IF(ISNUMBER($B$17),IF(AND($C$17=1,Z32<=-COS(PI()*$B$17)),AA32,NA()),NA()) -> #N/A | AC32: =IF(ISNUMBER($B$17),IF(AND($C$17=2,Z32<=-COS(PI()*$B$17)),AA32,NA()),NA()) -> #N/A | AD32: =IF(ISNUMBER($B$17),IF(AND($C$17=3,Z32<=-COS(PI()*$B$17)),AA32,NA()),NA()) -> #N/A | AE32: =IF(ISNUMBER($B$17),IF(AND($C$17=4,Z32<=-COS(PI()*$B$17)),AA32,NA()),NA()) -> #N/A | AF32: =IF(ISNUMBER($B$17),IF(AND($C$17=5,Z32<=-COS(PI()*$B$17)),AA32,NA()),NA()) -> #N/A | AG32: =IF(ISNUMBER($B$17),IF(AND(ISNUMBER($B$17),Z32>=MIN(0,$Z$2),Z32<=MAX(0,$Z$2)),IF($Z$2=0,0,Z32/$Z$2*$AA$2),NA()),NA()) -> 0.11621392 | AH32: -0.46 | AI32: =SQRT(MAX(0,1-AH32^2)) -> 0.88791892 | AJ32: =IF(ISNUMBER($B$18),IF(AND($C$18=1,AH32<=-COS(PI()*$B$18)),AI32,NA()),NA()) -> #N/A | AK32: =IF(ISNUMBER($B$18),IF(AND($C$18=2,AH32<=-COS(PI()*$B$18)),AI32,NA()),NA()) -> #N/A | AL32: =IF(ISNUMBER($B$18),IF(AND($C$18=3,AH32<=-COS(PI()*$B$18)),AI32,NA()),NA()) -> #N/A | AM32: =IF(ISNUMBER($B$18),IF(AND($C$18=4,AH32<=-COS(PI()*$B$18)),AI32,NA()),NA()) -> #N/A | AN32: =IF(ISNUMBER($B$18),IF(AND($C$18=5,AH32<=-COS(PI()*$B$18)),AI32,NA()),NA()) -> #N/A | AO32: =IF(ISNUMBER($B$18),IF(AND(ISNUMBER($B$18),AH32>=MIN(0,$AH$2),AH32<=MAX(0,$AH$2)),IF($AH$2=0,0,AH32/$AH$2*$AI$2),NA()),NA()) -> 0.316859 | AY32: =IF(D32=0,"",IF(ABS(D32)>=1000000000,TEXT(D32/1000000000,IF(MOD(ROUND(D32/1000000000,2),1)=0,"0","0.00"))&" B VND",IF(ABS(D32)>=1000000,TEXT(D32/1000000,IF(MOD(ROUND(D32/1000000,2),1)=0,"0","0.00"))&" M VND",TEXT(D32/1000,IF(MOD(ROUND(D32/1000,2),1)=0,"0","0.00"))&"k"))) -> 2.18B VND | AZ32: =IF(E32=0,"",IF(ABS(E32)>=1000000000,TEXT(E32/1000000000,IF(MOD(ROUND(E32/1000000000,2),1)=0,"0","0.00"))&" B VND",IF(ABS(E32)>=1000000,TEXT(E32/1000000,IF(MOD(ROUND(E32/1000000,2),1)=0,"0","0.00"))&" M VND",TEXT(E32/1000,IF(MOD(ROUND(E32/1000,2),1)=0,"0","0.00"))&"k"))) | BD32: =D33 -> 2.8416993e+10 | BE32: =E33 -> 1.67568e+09 | BF32: =A33 -> Senior Sales Rep 2 | BG32: =AY33 -> 27.13B VND | BH32: =AZ33 -> 1.60B VND
A33: Senior Sales Rep 2 | B33: =SUMIFS('Current AR'!$S$6:$S$103,'Current AR'!$J$6:$J$103,A33) -> 3.0092673e+10 | C33: =SUMIFS('Prior AR'!$S$6:$S$85,'Prior AR'!$J$6:$J$85,A33) -> 1.5416999e+10 | D33: =SUMIFS('Current AR'!$V$6:$V$103,'Current AR'!$J$6:$J$103,A33,'Current AR'!$Q$6:$Q$103,"<=0") -> 2.8416993e+10 | E33: =SUMIFS('Current AR'!$V$6:$V$103,'Current AR'!$J$6:$J$103,A33,'Current AR'!$Q$6:$Q$103,">0") -> 1.67568e+09 | R33: -0.44 | S33: =SQRT(MAX(0,1-R33^2)) -> 0.89799777 | T33: =IF(ISNUMBER($B$16),IF(AND($C$16=1,R33<=-COS(PI()*$B$16)),S33,NA()),NA()) -> #N/A | U33: =IF(ISNUMBER($B$16),IF(AND($C$16=2,R33<=-COS(PI()*$B$16)),S33,NA()),NA()) -> #N/A | V33: =IF(ISNUMBER($B$16),IF(AND($C$16=3,R33<=-COS(PI()*$B$16)),S33,NA()),NA()) -> #N/A | W33: =IF(ISNUMBER($B$16),IF(AND($C$16=4,R33<=-COS(PI()*$B$16)),S33,NA()),NA()) -> #N/A | X33: =IF(ISNUMBER($B$16),IF(AND($C$16=5,R33<=-COS(PI()*$B$16)),S33,NA()),NA()) -> #N/A | Y33: =IF(ISNUMBER($B$16),IF(AND(ISNUMBER($B$16),R33>=MIN(0,$R$2),R33<=MAX(0,$R$2)),IF($R$2=0,0,R33/$R$2*$S$2),NA()),NA()) -> 0.16347317 | Z33: -0.44 | AA33: =SQRT(MAX(0,1-Z33^2)) -> 0.89799777 | AB33: =IF(ISNUMBER($B$17),IF(AND($C$17=1,Z33<=-COS(PI()*$B$17)),AA33,NA()),NA()) -> #N/A | AC33: =IF(ISNUMBER($B$17),IF(AND($C$17=2,Z33<=-COS(PI()*$B$17)),AA33,NA()),NA()) -> #N/A | AD33: =IF(ISNUMBER($B$17),IF(AND($C$17=3,Z33<=-COS(PI()*$B$17)),AA33,NA()),NA()) -> #N/A | AE33: =IF(ISNUMBER($B$17),IF(AND($C$17=4,Z33<=-COS(PI()*$B$17)),AA33,NA()),NA()) -> #N/A | AF33: =IF(ISNUMBER($B$17),IF(AND($C$17=5,Z33<=-COS(PI()*$B$17)),AA33,NA()),NA()) -> #N/A | AG33: =IF(ISNUMBER($B$17),IF(AND(ISNUMBER($B$17),Z33>=MIN(0,$Z$2),Z33<=MAX(0,$Z$2)),IF($Z$2=0,0,Z33/$Z$2*$AA$2),NA()),NA()) -> 0.11116114 | AH33: -0.44 | AI33: =SQRT(MAX(0,1-AH33^2)) -> 0.89799777 | AJ33: =IF(ISNUMBER($B$18),IF(AND($C$18=1,AH33<=-COS(PI()*$B$18)),AI33,NA()),NA()) -> #N/A | AK33: =IF(ISNUMBER($B$18),IF(AND($C$18=2,AH33<=-COS(PI()*$B$18)),AI33,NA()),NA()) -> #N/A | AL33: =IF(ISNUMBER($B$18),IF(AND($C$18=3,AH33<=-COS(PI()*$B$18)),AI33,NA()),NA()) -> #N/A | AM33: =IF(ISNUMBER($B$18),IF(AND($C$18=4,AH33<=-COS(PI()*$B$18)),AI33,NA()),NA()) -> #N/A | AN33: =IF(ISNUMBER($B$18),IF(AND($C$18=5,AH33<=-COS(PI()*$B$18)),AI33,NA()),NA()) -> #N/A | AO33: =IF(ISNUMBER($B$18),IF(AND(ISNUMBER($B$18),AH33>=MIN(0,$AH$2),AH33<=MAX(0,$AH$2)),IF($AH$2=0,0,AH33/$AH$2*$AI$2),NA()),NA()) -> 0.30308252 | AY33: =IF(D33=0,"",IF(ABS(D33)>=1000000000,TEXT(D33/1000000000,IF(MOD(ROUND(D33/1000000000,2),1)=0,"0","0.00"))&" B VND",IF(ABS(D33)>=1000000,TEXT(D33/1000000,IF(MOD(ROUND(D33/1000000,2),1)=0,"0","0.00"))&" M VND",TEXT(D33/1000,IF(MOD(ROUND(D33/1000,2),1)=0,"0","0.00"))&"k"))) -> 27.13B VND | AZ33: =IF(E33=0,"",IF(ABS(E33)>=1000000000,TEXT(E33/1000000000,IF(MOD(ROUND(E33/1000000000,2),1)=0,"0","0.00"))&" B VND",IF(ABS(E33)>=1000000,TEXT(E33/1000000,IF(MOD(ROUND(E33/1000000,2),1)=0,"0","0.00"))&" M VND",TEXT(E33/1000,IF(MOD(ROUND(E33/1000,2),1)=0,"0","0.00"))&"k"))) -> 1.60B VND | BD33: =D34 -> 0 | BE33: =E34 -> 0 | BF33: =A34 -> Sales Rep 6 | BG33: =AY34 | BH33: =AZ34
A34: Sales Rep 6 | B34: =SUMIFS('Current AR'!$S$6:$S$103,'Current AR'!$J$6:$J$103,A34) -> 0 | C34: =SUMIFS('Prior AR'!$S$6:$S$85,'Prior AR'!$J$6:$J$85,A34) -> 0 | D34: =SUMIFS('Current AR'!$V$6:$V$103,'Current AR'!$J$6:$J$103,A34,'Current AR'!$Q$6:$Q$103,"<=0") -> 0 | E34: =SUMIFS('Current AR'!$V$6:$V$103,'Current AR'!$J$6:$J$103,A34,'Current AR'!$Q$6:$Q$103,">0") -> 0 | R34: -0.42 | S34: =SQRT(MAX(0,1-R34^2)) -> 0.9075241 | T34: =IF(ISNUMBER($B$16),IF(AND($C$16=1,R34<=-COS(PI()*$B$16)),S34,NA()),NA()) -> #N/A | U34: =IF(ISNUMBER($B$16),IF(AND($C$16=2,R34<=-COS(PI()*$B$16)),S34,NA()),NA()) -> #N/A | V34: =IF(ISNUMBER($B$16),IF(AND($C$16=3,R34<=-COS(PI()*$B$16)),S34,NA()),NA()) -> #N/A | W34: =IF(ISNUMBER($B$16),IF(AND($C$16=4,R34<=-COS(PI()*$B$16)),S34,NA()),NA()) -> #N/A | X34: =IF(ISNUMBER($B$16),IF(AND($C$16=5,R34<=-COS(PI()*$B$16)),S34,NA()),NA()) -> #N/A | Y34: =IF(ISNUMBER($B$16),IF(AND(ISNUMBER($B$16),R34>=MIN(0,$R$2),R34<=MAX(0,$R$2)),IF($R$2=0,0,R34/$R$2*$S$2),NA()),NA()) -> 0.15604257 | Z34: -0.42 | AA34: =SQRT(MAX(0,1-Z34^2)) -> 0.9075241 | AB34: =IF(ISNUMBER($B$17),IF(AND($C$17=1,Z34<=-COS(PI()*$B$17)),AA34,NA()),NA()) -> #N/A | AC34: =IF(ISNUMBER($B$17),IF(AND($C$17=2,Z34<=-COS(PI()*$B$17)),AA34,NA()),NA()) -> #N/A | AD34: =IF(ISNUMBER($B$17),IF(AND($C$17=3,Z34<=-COS(PI()*$B$17)),AA34,NA()),NA()) -> #N/A | AE34: =IF(ISNUMBER($B$17),IF(AND($C$17=4,Z34<=-COS(PI()*$B$17)),AA34,NA()),NA()) -> #N/A | AF34: =IF(ISNUMBER($B$17),IF(AND($C$17=5,Z34<=-COS(PI()*$B$17)),AA34,NA()),NA()) -> #N/A | AG34: =IF(ISNUMBER($B$17),IF(AND(ISNUMBER($B$17),Z34>=MIN(0,$Z$2),Z34<=MAX(0,$Z$2)),IF($Z$2=0,0,Z34/$Z$2*$AA$2),NA()),NA()) -> 0.10610836 | AH34: -0.42 | AI34: =SQRT(MAX(0,1-AH34^2)) -> 0.9075241 | AJ34: =IF(ISNUMBER($B$18),IF(AND($C$18=1,AH34<=-COS(PI()*$B$18)),AI34,NA()),NA()) -> #N/A | AK34: =IF(ISNUMBER($B$18),IF(AND($C$18=2,AH34<=-COS(PI()*$B$18)),AI34,NA()),NA()) -> #N/A | AL34: =IF(ISNUMBER($B$18),IF(AND($C$18=3,AH34<=-COS(PI()*$B$18)),AI34,NA()),NA()) -> #N/A | AM34: =IF(ISNUMBER($B$18),IF(AND($C$18=4,AH34<=-COS(PI()*$B$18)),AI34,NA()),NA()) -> #N/A | AN34: =IF(ISNUMBER($B$18),IF(AND($C$18=5,AH34<=-COS(PI()*$B$18)),AI34,NA()),NA()) -> #N/A | AO34: =IF(ISNUMBER($B$18),IF(AND(ISNUMBER($B$18),AH34>=MIN(0,$AH$2),AH34<=MAX(0,$AH$2)),IF($AH$2=0,0,AH34/$AH$2*$AI$2),NA()),NA()) -> 0.28930604 | AY34: =IF(D34=0,"",IF(ABS(D34)>=1000000000,TEXT(D34/1000000000,IF(MOD(ROUND(D34/1000000000,2),1)=0,"0","0.00"))&" B VND",IF(ABS(D34)>=1000000,TEXT(D34/1000000,IF(MOD(ROUND(D34/1000000,2),1)=0,"0","0.00"))&" M VND",TEXT(D34/1000,IF(MOD(ROUND(D34/1000,2),1)=0,"0","0.00"))&"k"))) | AZ34: =IF(E34=0,"",IF(ABS(E34)>=1000000000,TEXT(E34/1000000000,IF(MOD(ROUND(E34/1000000000,2),1)=0,"0","0.00"))&" B VND",IF(ABS(E34)>=1000000,TEXT(E34/1000000,IF(MOD(ROUND(E34/1000000,2),1)=0,"0","0.00"))&" M VND",TEXT(E34/1000,IF(MOD(ROUND(E34/1000,2),1)=0,"0","0.00"))&"k"))) | BD34: =D35 -> 43462950 | BE34: =E35 -> 0 | BF34: =A35 -> Sales Rep 4 | BG34: =AY35 -> 41.50M VND | BH34: =AZ35
A35: Sales Rep 4 | B35: =SUMIFS('Current AR'!$S$6:$S$103,'Current AR'!$J$6:$J$103,A35) -> 43462950 | C35: =SUMIFS('Prior AR'!$S$6:$S$85,'Prior AR'!$J$6:$J$85,A35) -> 0 | D35: =SUMIFS('Current AR'!$V$6:$V$103,'Current AR'!$J$6:$J$103,A35,'Current AR'!$Q$6:$Q$103,"<=0") -> 43462950 | E35: =SUMIFS('Current AR'!$V$6:$V$103,'Current AR'!$J$6:$J$103,A35,'Current AR'!$Q$6:$Q$103,">0") -> 0 | R35: -0.4 | S35: =SQRT(MAX(0,1-R35^2)) -> 0.91651514 | T35: =IF(ISNUMBER($B$16),IF(AND($C$16=1,R35<=-COS(PI()*$B$16)),S35,NA()),NA()) -> #N/A | U35: =IF(ISNUMBER($B$16),IF(AND($C$16=2,R35<=-COS(PI()*$B$16)),S35,NA()),NA()) -> #N/A | V35: =IF(ISNUMBER($B$16),IF(AND($C$16=3,R35<=-COS(PI()*$B$16)),S35,NA()),NA()) -> #N/A | W35: =IF(ISNUMBER($B$16),IF(AND($C$16=4,R35<=-COS(PI()*$B$16)),S35,NA()),NA()) -> #N/A | X35: =IF(ISNUMBER($B$16),IF(AND($C$16=5,R35<=-COS(PI()*$B$16)),S35,NA()),NA()) -> #N/A | Y35: =IF(ISNUMBER($B$16),IF(AND(ISNUMBER($B$16),R35>=MIN(0,$R$2),R35<=MAX(0,$R$2)),IF($R$2=0,0,R35/$R$2*$S$2),NA()),NA()) -> 0.14861197 | Z35: -0.4 | AA35: =SQRT(MAX(0,1-Z35^2)) -> 0.91651514 | AB35: =IF(ISNUMBER($B$17),IF(AND($C$17=1,Z35<=-COS(PI()*$B$17)),AA35,NA()),NA()) -> #N/A | AC35: =IF(ISNUMBER($B$17),IF(AND($C$17=2,Z35<=-COS(PI()*$B$17)),AA35,NA()),NA()) -> #N/A | AD35: =IF(ISNUMBER($B$17),IF(AND($C$17=3,Z35<=-COS(PI()*$B$17)),AA35,NA()),NA()) -> #N/A | AE35: =IF(ISNUMBER($B$17),IF(AND($C$17=4,Z35<=-COS(PI()*$B$17)),AA35,NA()),NA()) -> #N/A | AF35: =IF(ISNUMBER($B$17),IF(AND($C$17=5,Z35<=-COS(PI()*$B$17)),AA35,NA()),NA()) -> #N/A | AG35: =IF(ISNUMBER($B$17),IF(AND(ISNUMBER($B$17),Z35>=MIN(0,$Z$2),Z35<=MAX(0,$Z$2)),IF($Z$2=0,0,Z35/$Z$2*$AA$2),NA()),NA()) -> 0.10105558 | AH35: -0.4 | AI35: =SQRT(MAX(0,1-AH35^2)) -> 0.91651514 | AJ35: =IF(ISNUMBER($B$18),IF(AND($C$18=1,AH35<=-COS(PI()*$B$18)),AI35,NA()),NA()) -> #N/A | AK35: =IF(ISNUMBER($B$18),IF(AND($C$18=2,AH35<=-COS(PI()*$B$18)),AI35,NA()),NA()) -> #N/A | AL35: =IF(ISNUMBER($B$18),IF(AND($C$18=3,AH35<=-COS(PI()*$B$18)),AI35,NA()),NA()) -> #N/A | AM35: =IF(ISNUMBER($B$18),IF(AND($C$18=4,AH35<=-COS(PI()*$B$18)),AI35,NA()),NA()) -> #N/A | AN35: =IF(ISNUMBER($B$18),IF(AND($C$18=5,AH35<=-COS(PI()*$B$18)),AI35,NA()),NA()) -> #N/A | AO35: =IF(ISNUMBER($B$18),IF(AND(ISNUMBER($B$18),AH35>=MIN(0,$AH$2),AH35<=MAX(0,$AH$2)),IF($AH$2=0,0,AH35/$AH$2*$AI$2),NA()),NA()) -> 0.27552957 | AY35: =IF(D35=0,"",IF(ABS(D35)>=1000000000,TEXT(D35/1000000000,IF(MOD(ROUND(D35/1000000000,2),1)=0,"0","0.00"))&" B VND",IF(ABS(D35)>=1000000,TEXT(D35/1000000,IF(MOD(ROUND(D35/1000000,2),1)=0,"0","0.00"))&" M VND",TEXT(D35/1000,IF(MOD(ROUND(D35/1000,2),1)=0,"0","0.00"))&"k"))) -> 41.50M VND | AZ35: =IF(E35=0,"",IF(ABS(E35)>=1000000000,TEXT(E35/1000000000,IF(MOD(ROUND(E35/1000000000,2),1)=0,"0","0.00"))&" B VND",IF(ABS(E35)>=1000000,TEXT(E35/1000000,IF(MOD(ROUND(E35/1000000,2),1)=0,"0","0.00"))&" M VND",TEXT(E35/1000,IF(MOD(ROUND(E35/1000,2),1)=0,"0","0.00"))&"k"))) | BD35: =D36 -> 324663 | BE35: =E36 -> 0 | BF35: =A36 -> Sales Rep 5 | BG35: =AY36 -> 310k | BH35: =AZ36
A36: Sales Rep 5 | B36: =SUMIFS('Current AR'!$S$6:$S$103,'Current AR'!$J$6:$J$103,A36) -> 324663 | C36: =SUMIFS('Prior AR'!$S$6:$S$85,'Prior AR'!$J$6:$J$85,A36) -> 333943.13 | D36: =SUMIFS('Current AR'!$V$6:$V$103,'Current AR'!$J$6:$J$103,A36,'Current AR'!$Q$6:$Q$103,"<=0") -> 324663 | E36: =SUMIFS('Current AR'!$V$6:$V$103,'Current AR'!$J$6:$J$103,A36,'Current AR'!$Q$6:$Q$103,">0") -> 0 | R36: -0.38 | S36: =SQRT(MAX(0,1-R36^2)) -> 0.92498649 | T36: =IF(ISNUMBER($B$16),IF(AND($C$16=1,R36<=-COS(PI()*$B$16)),S36,NA()),NA()) -> #N/A | U36: =IF(ISNUMBER($B$16),IF(AND($C$16=2,R36<=-COS(PI()*$B$16)),S36,NA()),NA()) -> #N/A | V36: =IF(ISNUMBER($B$16),IF(AND($C$16=3,R36<=-COS(PI()*$B$16)),S36,NA()),NA()) -> #N/A | W36: =IF(ISNUMBER($B$16),IF(AND($C$16=4,R36<=-COS(PI()*$B$16)),S36,NA()),NA()) -> #N/A | X36: =IF(ISNUMBER($B$16),IF(AND($C$16=5,R36<=-COS(PI()*$B$16)),S36,NA()),NA()) -> #N/A | Y36: =IF(ISNUMBER($B$16),IF(AND(ISNUMBER($B$16),R36>=MIN(0,$R$2),R36<=MAX(0,$R$2)),IF($R$2=0,0,R36/$R$2*$S$2),NA()),NA()) -> 0.14118137 | Z36: -0.38 | AA36: =SQRT(MAX(0,1-Z36^2)) -> 0.92498649 | AB36: =IF(ISNUMBER($B$17),IF(AND($C$17=1,Z36<=-COS(PI()*$B$17)),AA36,NA()),NA()) -> #N/A | AC36: =IF(ISNUMBER($B$17),IF(AND($C$17=2,Z36<=-COS(PI()*$B$17)),AA36,NA()),NA()) -> #N/A | AD36: =IF(ISNUMBER($B$17),IF(AND($C$17=3,Z36<=-COS(PI()*$B$17)),AA36,NA()),NA()) -> #N/A | AE36: =IF(ISNUMBER($B$17),IF(AND($C$17=4,Z36<=-COS(PI()*$B$17)),AA36,NA()),NA()) -> #N/A | AF36: =IF(ISNUMBER($B$17),IF(AND($C$17=5,Z36<=-COS(PI()*$B$17)),AA36,NA()),NA()) -> #N/A | AG36: =IF(ISNUMBER($B$17),IF(AND(ISNUMBER($B$17),Z36>=MIN(0,$Z$2),Z36<=MAX(0,$Z$2)),IF($Z$2=0,0,Z36/$Z$2*$AA$2),NA()),NA()) -> 0.096002802 | AH36: -0.38 | AI36: =SQRT(MAX(0,1-AH36^2)) -> 0.92498649 | AJ36: =IF(ISNUMBER($B$18),IF(AND($C$18=1,AH36<=-COS(PI()*$B$18)),AI36,NA()),NA()) -> #N/A | AK36: =IF(ISNUMBER($B$18),IF(AND($C$18=2,AH36<=-COS(PI()*$B$18)),AI36,NA()),NA()) -> #N/A | AL36: =IF(ISNUMBER($B$18),IF(AND($C$18=3,AH36<=-COS(PI()*$B$18)),AI36,NA()),NA()) -> #N/A | AM36: =IF(ISNUMBER($B$18),IF(AND($C$18=4,AH36<=-COS(PI()*$B$18)),AI36,NA()),NA()) -> #N/A | AN36: =IF(ISNUMBER($B$18),IF(AND($C$18=5,AH36<=-COS(PI()*$B$18)),AI36,NA()),NA()) -> #N/A | AO36: =IF(ISNUMBER($B$18),IF(AND(ISNUMBER($B$18),AH36>=MIN(0,$AH$2),AH36<=MAX(0,$AH$2)),IF($AH$2=0,0,AH36/$AH$2*$AI$2),NA()),NA()) -> 0.26175309 | AY36: =IF(D36=0,"",IF(ABS(D36)>=1000000000,TEXT(D36/1000000000,IF(MOD(ROUND(D36/1000000000,2),1)=0,"0","0.00"))&" B VND",IF(ABS(D36)>=1000000,TEXT(D36/1000000,IF(MOD(ROUND(D36/1000000,2),1)=0,"0","0.00"))&" M VND",TEXT(D36/1000,IF(MOD(ROUND(D36/1000,2),1)=0,"0","0.00"))&"k"))) -> 310k | AZ36: =IF(E36=0,"",IF(ABS(E36)>=1000000000,TEXT(E36/1000000000,IF(MOD(ROUND(E36/1000000000,2),1)=0,"0","0.00"))&" B VND",IF(ABS(E36)>=1000000,TEXT(E36/1000000,IF(MOD(ROUND(E36/1000000,2),1)=0,"0","0.00"))&" M VND",TEXT(E36/1000,IF(MOD(ROUND(E36/1000,2),1)=0,"0","0.00"))&"k"))) | BD36: =D37 -> 0 | BE36: =E37 -> 4.021632e+09 | BF36: =A37 -> Sales Rep 3 | BG36: =AY37 | BH36: =AZ37 -> 3.84B VND
A37: Sales Rep 3 | B37: =SUMIFS('Current AR'!$S$6:$S$103,'Current AR'!$J$6:$J$103,A37) -> 4.021632e+09 | C37: =SUMIFS('Prior AR'!$S$6:$S$85,'Prior AR'!$J$6:$J$85,A37) -> 4.0993038e+09 | D37: =SUMIFS('Current AR'!$V$6:$V$103,'Current AR'!$J$6:$J$103,A37,'Current AR'!$Q$6:$Q$103,"<=0") -> 0 | E37: =SUMIFS('Current AR'!$V$6:$V$103,'Current AR'!$J$6:$J$103,A37,'Current AR'!$Q$6:$Q$103,">0") -> 4.021632e+09 | R37: -0.36 | S37: =SQRT(MAX(0,1-R37^2)) -> 0.9329523 | T37: =IF(ISNUMBER($B$16),IF(AND($C$16=1,R37<=-COS(PI()*$B$16)),S37,NA()),NA()) -> #N/A | U37: =IF(ISNUMBER($B$16),IF(AND($C$16=2,R37<=-COS(PI()*$B$16)),S37,NA()),NA()) -> #N/A | V37: =IF(ISNUMBER($B$16),IF(AND($C$16=3,R37<=-COS(PI()*$B$16)),S37,NA()),NA()) -> #N/A | W37: =IF(ISNUMBER($B$16),IF(AND($C$16=4,R37<=-COS(PI()*$B$16)),S37,NA()),NA()) -> #N/A | X37: =IF(ISNUMBER($B$16),IF(AND($C$16=5,R37<=-COS(PI()*$B$16)),S37,NA()),NA()) -> #N/A | Y37: =IF(ISNUMBER($B$16),IF(AND(ISNUMBER($B$16),R37>=MIN(0,$R$2),R37<=MAX(0,$R$2)),IF($R$2=0,0,R37/$R$2*$S$2),NA()),NA()) -> 0.13375078 | Z37: -0.36 | AA37: =SQRT(MAX(0,1-Z37^2)) -> 0.9329523 | AB37: =IF(ISNUMBER($B$17),IF(AND($C$17=1,Z37<=-COS(PI()*$B$17)),AA37,NA()),NA()) -> #N/A | AC37: =IF(ISNUMBER($B$17),IF(AND($C$17=2,Z37<=-COS(PI()*$B$17)),AA37,NA()),NA()) -> #N/A | AD37: =IF(ISNUMBER($B$17),IF(AND($C$17=3,Z37<=-COS(PI()*$B$17)),AA37,NA()),NA()) -> #N/A | AE37: =IF(ISNUMBER($B$17),IF(AND($C$17=4,Z37<=-COS(PI()*$B$17)),AA37,NA()),NA()) -> #N/A | AF37: =IF(ISNUMBER($B$17),IF(AND($C$17=5,Z37<=-COS(PI()*$B$17)),AA37,NA()),NA()) -> #N/A | AG37: =IF(ISNUMBER($B$17),IF(AND(ISNUMBER($B$17),Z37>=MIN(0,$Z$2),Z37<=MAX(0,$Z$2)),IF($Z$2=0,0,Z37/$Z$2*$AA$2),NA()),NA()) -> 0.090950023 | AH37: -0.36 | AI37: =SQRT(MAX(0,1-AH37^2)) -> 0.9329523 | AJ37: =IF(ISNUMBER($B$18),IF(AND($C$18=1,AH37<=-COS(PI()*$B$18)),AI37,NA()),NA()) -> #N/A | AK37: =IF(ISNUMBER($B$18),IF(AND($C$18=2,AH37<=-COS(PI()*$B$18)),AI37,NA()),NA()) -> #N/A | AL37: =IF(ISNUMBER($B$18),IF(AND($C$18=3,AH37<=-COS(PI()*$B$18)),AI37,NA()),NA()) -> #N/A | AM37: =IF(ISNUMBER($B$18),IF(AND($C$18=4,AH37<=-COS(PI()*$B$18)),AI37,NA()),NA()) -> #N/A | AN37: =IF(ISNUMBER($B$18),IF(AND($C$18=5,AH37<=-COS(PI()*$B$18)),AI37,NA()),NA()) -> #N/A | AO37: =IF(ISNUMBER($B$18),IF(AND(ISNUMBER($B$18),AH37>=MIN(0,$AH$2),AH37<=MAX(0,$AH$2)),IF($AH$2=0,0,AH37/$AH$2*$AI$2),NA()),NA()) -> 0.24797661 | AY37: =IF(D37=0,"",IF(ABS(D37)>=1000000000,TEXT(D37/1000000000,IF(MOD(ROUND(D37/1000000000,2),1)=0,"0","0.00"))&" B VND",IF(ABS(D37)>=1000000,TEXT(D37/1000000,IF(MOD(ROUND(D37/1000000,2),1)=0,"0","0.00"))&" M VND",TEXT(D37/1000,IF(MOD(ROUND(D37/1000,2),1)=0,"0","0.00"))&"k"))) | AZ37: =IF(E37=0,"",IF(ABS(E37)>=1000000000,TEXT(E37/1000000000,IF(MOD(ROUND(E37/1000000000,2),1)=0,"0","0.00"))&" B VND",IF(ABS(E37)>=1000000,TEXT(E37/1000000,IF(MOD(ROUND(E37/1000000,2),1)=0,"0","0.00"))&" M VND",TEXT(E37/1000,IF(MOD(ROUND(E37/1000,2),1)=0,"0","0.00"))&"k"))) -> 3.84B VND
A38: Current / In-Term | B38: =SUMIFS('Current AR'!$V$6:$V$160,'Current AR'!$Q$6:$Q$160,"<0") -> 41216259755 | R38: -0.34 | S38: =SQRT(MAX(0,1-R38^2)) -> 0.94042544 | T38: =IF(ISNUMBER($B$16),IF(AND($C$16=1,R38<=-COS(PI()*$B$16)),S38,NA()),NA()) -> #N/A | U38: =IF(ISNUMBER($B$16),IF(AND($C$16=2,R38<=-COS(PI()*$B$16)),S38,NA()),NA()) -> #N/A | V38: =IF(ISNUMBER($B$16),IF(AND($C$16=3,R38<=-COS(PI()*$B$16)),S38,NA()),NA()) -> #N/A | W38: =IF(ISNUMBER($B$16),IF(AND($C$16=4,R38<=-COS(PI()*$B$16)),S38,NA()),NA()) -> #N/A | X38: =IF(ISNUMBER($B$16),IF(AND($C$16=5,R38<=-COS(PI()*$B$16)),S38,NA()),NA()) -> #N/A | Y38: =IF(ISNUMBER($B$16),IF(AND(ISNUMBER($B$16),R38>=MIN(0,$R$2),R38<=MAX(0,$R$2)),IF($R$2=0,0,R38/$R$2*$S$2),NA()),NA()) -> 0.12632018 | Z38: -0.34 | AA38: =SQRT(MAX(0,1-Z38^2)) -> 0.94042544 | AB38: =IF(ISNUMBER($B$17),IF(AND($C$17=1,Z38<=-COS(PI()*$B$17)),AA38,NA()),NA()) -> #N/A | AC38: =IF(ISNUMBER($B$17),IF(AND($C$17=2,Z38<=-COS(PI()*$B$17)),AA38,NA()),NA()) -> #N/A | AD38: =IF(ISNUMBER($B$17),IF(AND($C$17=3,Z38<=-COS(PI()*$B$17)),AA38,NA()),NA()) -> #N/A | AE38: =IF(ISNUMBER($B$17),IF(AND($C$17=4,Z38<=-COS(PI()*$B$17)),AA38,NA()),NA()) -> #N/A | AF38: =IF(ISNUMBER($B$17),IF(AND($C$17=5,Z38<=-COS(PI()*$B$17)),AA38,NA()),NA()) -> #N/A | AG38: =IF(ISNUMBER($B$17),IF(AND(ISNUMBER($B$17),Z38>=MIN(0,$Z$2),Z38<=MAX(0,$Z$2)),IF($Z$2=0,0,Z38/$Z$2*$AA$2),NA()),NA()) -> 0.085897244 | AH38: -0.34 | AI38: =SQRT(MAX(0,1-AH38^2)) -> 0.94042544 | AJ38: =IF(ISNUMBER($B$18),IF(AND($C$18=1,AH38<=-COS(PI()*$B$18)),AI38,NA()),NA()) -> #N/A | AK38: =IF(ISNUMBER($B$18),IF(AND($C$18=2,AH38<=-COS(PI()*$B$18)),AI38,NA()),NA()) -> #N/A | AL38: =IF(ISNUMBER($B$18),IF(AND($C$18=3,AH38<=-COS(PI()*$B$18)),AI38,NA()),NA()) -> #N/A | AM38: =IF(ISNUMBER($B$18),IF(AND($C$18=4,AH38<=-COS(PI()*$B$18)),AI38,NA()),NA()) -> #N/A | AN38: =IF(ISNUMBER($B$18),IF(AND($C$18=5,AH38<=-COS(PI()*$B$18)),AI38,NA()),NA()) -> #N/A | AO38: =IF(ISNUMBER($B$18),IF(AND(ISNUMBER($B$18),AH38>=MIN(0,$AH$2),AH38<=MAX(0,$AH$2)),IF($AH$2=0,0,AH38/$AH$2*$AI$2),NA()),NA()) -> 0.23420013 | BB38: =IF(B38=0,"–",IF(ABS(B38)>=1000000000,TEXT(B38/1000000000,"0.00")&"B",IF(ABS(B38)>=1000000,TEXT(B38/1000000,"0.0")&"M",TEXT(B38/1000,"0")&"K"))) -> 41.22B | CB38: Current (not due)
A39: Due Today | B39: =SUMIFS('Current AR'!$V$6:$V$160,'Current AR'!$Q$6:$Q$160,"=0") -> 36887245 | R39: -0.32 | S39: =SQRT(MAX(0,1-R39^2)) -> 0.94741754 | T39: =IF(ISNUMBER($B$16),IF(AND($C$16=1,R39<=-COS(PI()*$B$16)),S39,NA()),NA()) -> #N/A | U39: =IF(ISNUMBER($B$16),IF(AND($C$16=2,R39<=-COS(PI()*$B$16)),S39,NA()),NA()) -> #N/A | V39: =IF(ISNUMBER($B$16),IF(AND($C$16=3,R39<=-COS(PI()*$B$16)),S39,NA()),NA()) -> #N/A | W39: =IF(ISNUMBER($B$16),IF(AND($C$16=4,R39<=-COS(PI()*$B$16)),S39,NA()),NA()) -> #N/A | X39: =IF(ISNUMBER($B$16),IF(AND($C$16=5,R39<=-COS(PI()*$B$16)),S39,NA()),NA()) -> #N/A | Y39: =IF(ISNUMBER($B$16),IF(AND(ISNUMBER($B$16),R39>=MIN(0,$R$2),R39<=MAX(0,$R$2)),IF($R$2=0,0,R39/$R$2*$S$2),NA()),NA()) -> 0.11888958 | Z39: -0.32 | AA39: =SQRT(MAX(0,1-Z39^2)) -> 0.94741754 | AB39: =IF(ISNUMBER($B$17),IF(AND($C$17=1,Z39<=-COS(PI()*$B$17)),AA39,NA()),NA()) -> #N/A | AC39: =IF(ISNUMBER($B$17),IF(AND($C$17=2,Z39<=-COS(PI()*$B$17)),AA39,NA()),NA()) -> #N/A | AD39: =IF(ISNUMBER($B$17),IF(AND($C$17=3,Z39<=-COS(PI()*$B$17)),AA39,NA()),NA()) -> #N/A | AE39: =IF(ISNUMBER($B$17),IF(AND($C$17=4,Z39<=-COS(PI()*$B$17)),AA39,NA()),NA()) -> #N/A | AF39: =IF(ISNUMBER($B$17),IF(AND($C$17=5,Z39<=-COS(PI()*$B$17)),AA39,NA()),NA()) -> #N/A | AG39: =IF(ISNUMBER($B$17),IF(AND(ISNUMBER($B$17),Z39>=MIN(0,$Z$2),Z39<=MAX(0,$Z$2)),IF($Z$2=0,0,Z39/$Z$2*$AA$2),NA()),NA()) -> 0.080844465 | AH39: -0.32 | AI39: =SQRT(MAX(0,1-AH39^2)) -> 0.94741754 | AJ39: =IF(ISNUMBER($B$18),IF(AND($C$18=1,AH39<=-COS(PI()*$B$18)),AI39,NA()),NA()) -> #N/A | AK39: =IF(ISNUMBER($B$18),IF(AND($C$18=2,AH39<=-COS(PI()*$B$18)),AI39,NA()),NA()) -> #N/A | AL39: =IF(ISNUMBER($B$18),IF(AND($C$18=3,AH39<=-COS(PI()*$B$18)),AI39,NA()),NA()) -> #N/A | AM39: =IF(ISNUMBER($B$18),IF(AND($C$18=4,AH39<=-COS(PI()*$B$18)),AI39,NA()),NA()) -> #N/A | AN39: =IF(ISNUMBER($B$18),IF(AND($C$18=5,AH39<=-COS(PI()*$B$18)),AI39,NA()),NA()) -> #N/A | AO39: =IF(ISNUMBER($B$18),IF(AND(ISNUMBER($B$18),AH39>=MIN(0,$AH$2),AH39<=MAX(0,$AH$2)),IF($AH$2=0,0,AH39/$AH$2*$AI$2),NA()),NA()) -> 0.22042365 | BB39: =IF(B39=0,"–",IF(ABS(B39)>=1000000000,TEXT(B39/1000000000,"0.00")&"B",IF(ABS(B39)>=1000000,TEXT(B39/1000000,"0.0")&"M",TEXT(B39/1000,"0")&"K"))) -> 36.9M | CB39: Due today
A40: 1–30d Overdue | B40: =SUMIFS('Current AR'!$V$6:$V$160,'Current AR'!$Q$6:$Q$160,">0",'Current AR'!$Q$6:$Q$160,"<=30") -> 5235411407 | R40: -0.3 | S40: =SQRT(MAX(0,1-R40^2)) -> 0.9539392 | T40: =IF(ISNUMBER($B$16),IF(AND($C$16=1,R40<=-COS(PI()*$B$16)),S40,NA()),NA()) -> #N/A | U40: =IF(ISNUMBER($B$16),IF(AND($C$16=2,R40<=-COS(PI()*$B$16)),S40,NA()),NA()) -> #N/A | V40: =IF(ISNUMBER($B$16),IF(AND($C$16=3,R40<=-COS(PI()*$B$16)),S40,NA()),NA()) -> #N/A | W40: =IF(ISNUMBER($B$16),IF(AND($C$16=4,R40<=-COS(PI()*$B$16)),S40,NA()),NA()) -> #N/A | X40: =IF(ISNUMBER($B$16),IF(AND($C$16=5,R40<=-COS(PI()*$B$16)),S40,NA()),NA()) -> #N/A | Y40: =IF(ISNUMBER($B$16),IF(AND(ISNUMBER($B$16),R40>=MIN(0,$R$2),R40<=MAX(0,$R$2)),IF($R$2=0,0,R40/$R$2*$S$2),NA()),NA()) -> 0.11145898 | Z40: -0.3 | AA40: =SQRT(MAX(0,1-Z40^2)) -> 0.9539392 | AB40: =IF(ISNUMBER($B$17),IF(AND($C$17=1,Z40<=-COS(PI()*$B$17)),AA40,NA()),NA()) -> #N/A | AC40: =IF(ISNUMBER($B$17),IF(AND($C$17=2,Z40<=-COS(PI()*$B$17)),AA40,NA()),NA()) -> #N/A | AD40: =IF(ISNUMBER($B$17),IF(AND($C$17=3,Z40<=-COS(PI()*$B$17)),AA40,NA()),NA()) -> #N/A | AE40: =IF(ISNUMBER($B$17),IF(AND($C$17=4,Z40<=-COS(PI()*$B$17)),AA40,NA()),NA()) -> #N/A | AF40: =IF(ISNUMBER($B$17),IF(AND($C$17=5,Z40<=-COS(PI()*$B$17)),AA40,NA()),NA()) -> #N/A | AG40: =IF(ISNUMBER($B$17),IF(AND(ISNUMBER($B$17),Z40>=MIN(0,$Z$2),Z40<=MAX(0,$Z$2)),IF($Z$2=0,0,Z40/$Z$2*$AA$2),NA()),NA()) -> 0.075791686 | AH40: -0.3 | AI40: =SQRT(MAX(0,1-AH40^2)) -> 0.9539392 | AJ40: =IF(ISNUMBER($B$18),IF(AND($C$18=1,AH40<=-COS(PI()*$B$18)),AI40,NA()),NA()) -> #N/A | AK40: =IF(ISNUMBER($B$18),IF(AND($C$18=2,AH40<=-COS(PI()*$B$18)),AI40,NA()),NA()) -> #N/A | AL40: =IF(ISNUMBER($B$18),IF(AND($C$18=3,AH40<=-COS(PI()*$B$18)),AI40,NA()),NA()) -> #N/A | AM40: =IF(ISNUMBER($B$18),IF(AND($C$18=4,AH40<=-COS(PI()*$B$18)),AI40,NA()),NA()) -> #N/A | AN40: =IF(ISNUMBER($B$18),IF(AND($C$18=5,AH40<=-COS(PI()*$B$18)),AI40,NA()),NA()) -> #N/A | AO40: =IF(ISNUMBER($B$18),IF(AND(ISNUMBER($B$18),AH40>=MIN(0,$AH$2),AH40<=MAX(0,$AH$2)),IF($AH$2=0,0,AH40/$AH$2*$AI$2),NA()),NA()) -> 0.20664717 | BB40: =IF(B40=0,"–",IF(ABS(B40)>=1000000000,TEXT(B40/1000000000,"0.00")&"B",IF(ABS(B40)>=1000000,TEXT(B40/1000000,"0.0")&"M",TEXT(B40/1000,"0")&"K"))) -> 5.24B | CB40: 1–30d overdue
A41: 31–60d Overdue | B41: =SUMIFS('Current AR'!$V$6:$V$160,'Current AR'!$Q$6:$Q$160,">30",'Current AR'!$Q$6:$Q$160,"<=60") -> 545684593 | R41: -0.28 | S41: =SQRT(MAX(0,1-R41^2)) -> 0.96 | T41: =IF(ISNUMBER($B$16),IF(AND($C$16=1,R41<=-COS(PI()*$B$16)),S41,NA()),NA()) -> #N/A | U41: =IF(ISNUMBER($B$16),IF(AND($C$16=2,R41<=-COS(PI()*$B$16)),S41,NA()),NA()) -> #N/A | V41: =IF(ISNUMBER($B$16),IF(AND($C$16=3,R41<=-COS(PI()*$B$16)),S41,NA()),NA()) -> #N/A | W41: =IF(ISNUMBER($B$16),IF(AND($C$16=4,R41<=-COS(PI()*$B$16)),S41,NA()),NA()) -> #N/A | X41: =IF(ISNUMBER($B$16),IF(AND($C$16=5,R41<=-COS(PI()*$B$16)),S41,NA()),NA()) -> #N/A | Y41: =IF(ISNUMBER($B$16),IF(AND(ISNUMBER($B$16),R41>=MIN(0,$R$2),R41<=MAX(0,$R$2)),IF($R$2=0,0,R41/$R$2*$S$2),NA()),NA()) -> 0.10402838 | Z41: -0.28 | AA41: =SQRT(MAX(0,1-Z41^2)) -> 0.96 | AB41: =IF(ISNUMBER($B$17),IF(AND($C$17=1,Z41<=-COS(PI()*$B$17)),AA41,NA()),NA()) -> #N/A | AC41: =IF(ISNUMBER($B$17),IF(AND($C$17=2,Z41<=-COS(PI()*$B$17)),AA41,NA()),NA()) -> #N/A | AD41: =IF(ISNUMBER($B$17),IF(AND($C$17=3,Z41<=-COS(PI()*$B$17)),AA41,NA()),NA()) -> #N/A | AE41: =IF(ISNUMBER($B$17),IF(AND($C$17=4,Z41<=-COS(PI()*$B$17)),AA41,NA()),NA()) -> #N/A | AF41: =IF(ISNUMBER($B$17),IF(AND($C$17=5,Z41<=-COS(PI()*$B$17)),AA41,NA()),NA()) -> #N/A | AG41: =IF(ISNUMBER($B$17),IF(AND(ISNUMBER($B$17),Z41>=MIN(0,$Z$2),Z41<=MAX(0,$Z$2)),IF($Z$2=0,0,Z41/$Z$2*$AA$2),NA()),NA()) -> 0.070738907 | AH41: -0.28 | AI41: =SQRT(MAX(0,1-AH41^2)) -> 0.96 | AJ41: =IF(ISNUMBER($B$18),IF(AND($C$18=1,AH41<=-COS(PI()*$B$18)),AI41,NA()),NA()) -> #N/A | AK41: =IF(ISNUMBER($B$18),IF(AND($C$18=2,AH41<=-COS(PI()*$B$18)),AI41,NA()),NA()) -> #N/A | AL41: =IF(ISNUMBER($B$18),IF(AND($C$18=3,AH41<=-COS(PI()*$B$18)),AI41,NA()),NA()) -> #N/A | AM41: =IF(ISNUMBER($B$18),IF(AND($C$18=4,AH41<=-COS(PI()*$B$18)),AI41,NA()),NA()) -> #N/A | AN41: =IF(ISNUMBER($B$18),IF(AND($C$18=5,AH41<=-COS(PI()*$B$18)),AI41,NA()),NA()) -> #N/A | AO41: =IF(ISNUMBER($B$18),IF(AND(ISNUMBER($B$18),AH41>=MIN(0,$AH$2),AH41<=MAX(0,$AH$2)),IF($AH$2=0,0,AH41/$AH$2*$AI$2),NA()),NA()) -> 0.1928707 | BB41: =IF(B41=0,"–",IF(ABS(B41)>=1000000000,TEXT(B41/1000000000,"0.00")&"B",IF(ABS(B41)>=1000000,TEXT(B41/1000000,"0.0")&"M",TEXT(B41/1000,"0")&"K"))) -> 545.7M | CB41: 31–60d overdue
A42: 61–90d Doubtful | B42: =SUMIFS('Current AR'!$V$6:$V$160,'Current AR'!$Q$6:$Q$160,">60",'Current AR'!$Q$6:$Q$160,"<=90") -> 4021632000 | R42: -0.26 | S42: =SQRT(MAX(0,1-R42^2)) -> 0.96560862 | T42: =IF(ISNUMBER($B$16),IF(AND($C$16=1,R42<=-COS(PI()*$B$16)),S42,NA()),NA()) -> #N/A | U42: =IF(ISNUMBER($B$16),IF(AND($C$16=2,R42<=-COS(PI()*$B$16)),S42,NA()),NA()) -> #N/A | V42: =IF(ISNUMBER($B$16),IF(AND($C$16=3,R42<=-COS(PI()*$B$16)),S42,NA()),NA()) -> #N/A | W42: =IF(ISNUMBER($B$16),IF(AND($C$16=4,R42<=-COS(PI()*$B$16)),S42,NA()),NA()) -> #N/A | X42: =IF(ISNUMBER($B$16),IF(AND($C$16=5,R42<=-COS(PI()*$B$16)),S42,NA()),NA()) -> #N/A | Y42: =IF(ISNUMBER($B$16),IF(AND(ISNUMBER($B$16),R42>=MIN(0,$R$2),R42<=MAX(0,$R$2)),IF($R$2=0,0,R42/$R$2*$S$2),NA()),NA()) -> 0.096597782 | Z42: -0.26 | AA42: =SQRT(MAX(0,1-Z42^2)) -> 0.96560862 | AB42: =IF(ISNUMBER($B$17),IF(AND($C$17=1,Z42<=-COS(PI()*$B$17)),AA42,NA()),NA()) -> #N/A | AC42: =IF(ISNUMBER($B$17),IF(AND($C$17=2,Z42<=-COS(PI()*$B$17)),AA42,NA()),NA()) -> #N/A | AD42: =IF(ISNUMBER($B$17),IF(AND($C$17=3,Z42<=-COS(PI()*$B$17)),AA42,NA()),NA()) -> #N/A | AE42: =IF(ISNUMBER($B$17),IF(AND($C$17=4,Z42<=-COS(PI()*$B$17)),AA42,NA()),NA()) -> #N/A | AF42: =IF(ISNUMBER($B$17),IF(AND($C$17=5,Z42<=-COS(PI()*$B$17)),AA42,NA()),NA()) -> #N/A | AG42: =IF(ISNUMBER($B$17),IF(AND(ISNUMBER($B$17),Z42>=MIN(0,$Z$2),Z42<=MAX(0,$Z$2)),IF($Z$2=0,0,Z42/$Z$2*$AA$2),NA()),NA()) -> 0.065686128 | AH42: -0.26 | AI42: =SQRT(MAX(0,1-AH42^2)) -> 0.96560862 | AJ42: =IF(ISNUMBER($B$18),IF(AND($C$18=1,AH42<=-COS(PI()*$B$18)),AI42,NA()),NA()) -> #N/A | AK42: =IF(ISNUMBER($B$18),IF(AND($C$18=2,AH42<=-COS(PI()*$B$18)),AI42,NA()),NA()) -> #N/A | AL42: =IF(ISNUMBER($B$18),IF(AND($C$18=3,AH42<=-COS(PI()*$B$18)),AI42,NA()),NA()) -> #N/A | AM42: =IF(ISNUMBER($B$18),IF(AND($C$18=4,AH42<=-COS(PI()*$B$18)),AI42,NA()),NA()) -> #N/A | AN42: =IF(ISNUMBER($B$18),IF(AND($C$18=5,AH42<=-COS(PI()*$B$18)),AI42,NA()),NA()) -> #N/A | AO42: =IF(ISNUMBER($B$18),IF(AND(ISNUMBER($B$18),AH42>=MIN(0,$AH$2),AH42<=MAX(0,$AH$2)),IF($AH$2=0,0,AH42/$AH$2*$AI$2),NA()),NA()) -> 0.17909422 | BB42: =IF(B42=0,"–",IF(ABS(B42)>=1000000000,TEXT(B42/1000000000,"0.00")&"B",IF(ABS(B42)>=1000000,TEXT(B42/1000000,"0.0")&"M",TEXT(B42/1000,"0")&"K"))) -> 4.02B | CB42: 61–90d >60 days
A43: 91–180d Doubtful | B43: =SUMIFS('Current AR'!$V$6:$V$160,'Current AR'!$Q$6:$Q$160,">90",'Current AR'!$Q$6:$Q$160,"<=180") -> 0 | R43: -0.24 | S43: =SQRT(MAX(0,1-R43^2)) -> 0.97077289 | T43: =IF(ISNUMBER($B$16),IF(AND($C$16=1,R43<=-COS(PI()*$B$16)),S43,NA()),NA()) -> #N/A | U43: =IF(ISNUMBER($B$16),IF(AND($C$16=2,R43<=-COS(PI()*$B$16)),S43,NA()),NA()) -> #N/A | V43: =IF(ISNUMBER($B$16),IF(AND($C$16=3,R43<=-COS(PI()*$B$16)),S43,NA()),NA()) -> #N/A | W43: =IF(ISNUMBER($B$16),IF(AND($C$16=4,R43<=-COS(PI()*$B$16)),S43,NA()),NA()) -> #N/A | X43: =IF(ISNUMBER($B$16),IF(AND($C$16=5,R43<=-COS(PI()*$B$16)),S43,NA()),NA()) -> #N/A | Y43: =IF(ISNUMBER($B$16),IF(AND(ISNUMBER($B$16),R43>=MIN(0,$R$2),R43<=MAX(0,$R$2)),IF($R$2=0,0,R43/$R$2*$S$2),NA()),NA()) -> 0.089167183 | Z43: -0.24 | AA43: =SQRT(MAX(0,1-Z43^2)) -> 0.97077289 | AB43: =IF(ISNUMBER($B$17),IF(AND($C$17=1,Z43<=-COS(PI()*$B$17)),AA43,NA()),NA()) -> #N/A | AC43: =IF(ISNUMBER($B$17),IF(AND($C$17=2,Z43<=-COS(PI()*$B$17)),AA43,NA()),NA()) -> #N/A | AD43: =IF(ISNUMBER($B$17),IF(AND($C$17=3,Z43<=-COS(PI()*$B$17)),AA43,NA()),NA()) -> #N/A | AE43: =IF(ISNUMBER($B$17),IF(AND($C$17=4,Z43<=-COS(PI()*$B$17)),AA43,NA()),NA()) -> #N/A | AF43: =IF(ISNUMBER($B$17),IF(AND($C$17=5,Z43<=-COS(PI()*$B$17)),AA43,NA()),NA()) -> #N/A | AG43: =IF(ISNUMBER($B$17),IF(AND(ISNUMBER($B$17),Z43>=MIN(0,$Z$2),Z43<=MAX(0,$Z$2)),IF($Z$2=0,0,Z43/$Z$2*$AA$2),NA()),NA()) -> 0.060633349 | AH43: -0.24 | AI43: =SQRT(MAX(0,1-AH43^2)) -> 0.97077289 | AJ43: =IF(ISNUMBER($B$18),IF(AND($C$18=1,AH43<=-COS(PI()*$B$18)),AI43,NA()),NA()) -> #N/A | AK43: =IF(ISNUMBER($B$18),IF(AND($C$18=2,AH43<=-COS(PI()*$B$18)),AI43,NA()),NA()) -> #N/A | AL43: =IF(ISNUMBER($B$18),IF(AND($C$18=3,AH43<=-COS(PI()*$B$18)),AI43,NA()),NA()) -> #N/A | AM43: =IF(ISNUMBER($B$18),IF(AND($C$18=4,AH43<=-COS(PI()*$B$18)),AI43,NA()),NA()) -> #N/A | AN43: =IF(ISNUMBER($B$18),IF(AND($C$18=5,AH43<=-COS(PI()*$B$18)),AI43,NA()),NA()) -> #N/A | AO43: =IF(ISNUMBER($B$18),IF(AND(ISNUMBER($B$18),AH43>=MIN(0,$AH$2),AH43<=MAX(0,$AH$2)),IF($AH$2=0,0,AH43/$AH$2*$AI$2),NA()),NA()) -> 0.16531774 | BB43: =IF(B43=0,"–",IF(ABS(B43)>=1000000000,TEXT(B43/1000000000,"0.00")&"B",IF(ABS(B43)>=1000000,TEXT(B43/1000000,"0.0")&"M",TEXT(B43/1000,"0")&"K"))) -> – | CB43: 91–180d >60 days
A44: >180d Doubtful | B44: =SUMIFS('Current AR'!$V$6:$V$160,'Current AR'!$Q$6:$Q$160,">180") -> 0 | R44: -0.22 | S44: =SQRT(MAX(0,1-R44^2)) -> 0.97549987 | T44: =IF(ISNUMBER($B$16),IF(AND($C$16=1,R44<=-COS(PI()*$B$16)),S44,NA()),NA()) -> #N/A | U44: =IF(ISNUMBER($B$16),IF(AND($C$16=2,R44<=-COS(PI()*$B$16)),S44,NA()),NA()) -> #N/A | V44: =IF(ISNUMBER($B$16),IF(AND($C$16=3,R44<=-COS(PI()*$B$16)),S44,NA()),NA()) -> #N/A | W44: =IF(ISNUMBER($B$16),IF(AND($C$16=4,R44<=-COS(PI()*$B$16)),S44,NA()),NA()) -> #N/A | X44: =IF(ISNUMBER($B$16),IF(AND($C$16=5,R44<=-COS(PI()*$B$16)),S44,NA()),NA()) -> #N/A | Y44: =IF(ISNUMBER($B$16),IF(AND(ISNUMBER($B$16),R44>=MIN(0,$R$2),R44<=MAX(0,$R$2)),IF($R$2=0,0,R44/$R$2*$S$2),NA()),NA()) -> 0.081736585 | Z44: -0.22 | AA44: =SQRT(MAX(0,1-Z44^2)) -> 0.97549987 | AB44: =IF(ISNUMBER($B$17),IF(AND($C$17=1,Z44<=-COS(PI()*$B$17)),AA44,NA()),NA()) -> #N/A | AC44: =IF(ISNUMBER($B$17),IF(AND($C$17=2,Z44<=-COS(PI()*$B$17)),AA44,NA()),NA()) -> #N/A | AD44: =IF(ISNUMBER($B$17),IF(AND($C$17=3,Z44<=-COS(PI()*$B$17)),AA44,NA()),NA()) -> #N/A | AE44: =IF(ISNUMBER($B$17),IF(AND($C$17=4,Z44<=-COS(PI()*$B$17)),AA44,NA()),NA()) -> #N/A | AF44: =IF(ISNUMBER($B$17),IF(AND($C$17=5,Z44<=-COS(PI()*$B$17)),AA44,NA()),NA()) -> #N/A | AG44: =IF(ISNUMBER($B$17),IF(AND(ISNUMBER($B$17),Z44>=MIN(0,$Z$2),Z44<=MAX(0,$Z$2)),IF($Z$2=0,0,Z44/$Z$2*$AA$2),NA()),NA()) -> 0.05558057 | AH44: -0.22 | AI44: =SQRT(MAX(0,1-AH44^2)) -> 0.97549987 | AJ44: =IF(ISNUMBER($B$18),IF(AND($C$18=1,AH44<=-COS(PI()*$B$18)),AI44,NA()),NA()) -> #N/A | AK44: =IF(ISNUMBER($B$18),IF(AND($C$18=2,AH44<=-COS(PI()*$B$18)),AI44,NA()),NA()) -> #N/A | AL44: =IF(ISNUMBER($B$18),IF(AND($C$18=3,AH44<=-COS(PI()*$B$18)),AI44,NA()),NA()) -> #N/A | AM44: =IF(ISNUMBER($B$18),IF(AND($C$18=4,AH44<=-COS(PI()*$B$18)),AI44,NA()),NA()) -> #N/A | AN44: =IF(ISNUMBER($B$18),IF(AND($C$18=5,AH44<=-COS(PI()*$B$18)),AI44,NA()),NA()) -> #N/A | AO44: =IF(ISNUMBER($B$18),IF(AND(ISNUMBER($B$18),AH44>=MIN(0,$AH$2),AH44<=MAX(0,$AH$2)),IF($AH$2=0,0,AH44/$AH$2*$AI$2),NA()),NA()) -> 0.15154126 | BB44: =IF(B44=0,"–",IF(ABS(B44)>=1000000000,TEXT(B44/1000000000,"0.00")&"B",IF(ABS(B44)>=1000000,TEXT(B44/1000000,"0.0")&"M",TEXT(B44/1000,"0")&"K"))) -> – | CB44: >180d >60 days
R45: -0.2 | S45: =SQRT(MAX(0,1-R45^2)) -> 0.9797959 | T45: =IF(ISNUMBER($B$16),IF(AND($C$16=1,R45<=-COS(PI()*$B$16)),S45,NA()),NA()) -> #N/A | U45: =IF(ISNUMBER($B$16),IF(AND($C$16=2,R45<=-COS(PI()*$B$16)),S45,NA()),NA()) -> #N/A | V45: =IF(ISNUMBER($B$16),IF(AND($C$16=3,R45<=-COS(PI()*$B$16)),S45,NA()),NA()) -> #N/A | W45: =IF(ISNUMBER($B$16),IF(AND($C$16=4,R45<=-COS(PI()*$B$16)),S45,NA()),NA()) -> #N/A | X45: =IF(ISNUMBER($B$16),IF(AND($C$16=5,R45<=-COS(PI()*$B$16)),S45,NA()),NA()) -> #N/A | Y45: =IF(ISNUMBER($B$16),IF(AND(ISNUMBER($B$16),R45>=MIN(0,$R$2),R45<=MAX(0,$R$2)),IF($R$2=0,0,R45/$R$2*$S$2),NA()),NA()) -> 0.074305986 | Z45: -0.2 | AA45: =SQRT(MAX(0,1-Z45^2)) -> 0.9797959 | AB45: =IF(ISNUMBER($B$17),IF(AND($C$17=1,Z45<=-COS(PI()*$B$17)),AA45,NA()),NA()) -> #N/A | AC45: =IF(ISNUMBER($B$17),IF(AND($C$17=2,Z45<=-COS(PI()*$B$17)),AA45,NA()),NA()) -> #N/A | AD45: =IF(ISNUMBER($B$17),IF(AND($C$17=3,Z45<=-COS(PI()*$B$17)),AA45,NA()),NA()) -> #N/A | AE45: =IF(ISNUMBER($B$17),IF(AND($C$17=4,Z45<=-COS(PI()*$B$17)),AA45,NA()),NA()) -> #N/A | AF45: =IF(ISNUMBER($B$17),IF(AND($C$17=5,Z45<=-COS(PI()*$B$17)),AA45,NA()),NA()) -> #N/A | AG45: =IF(ISNUMBER($B$17),IF(AND(ISNUMBER($B$17),Z45>=MIN(0,$Z$2),Z45<=MAX(0,$Z$2)),IF($Z$2=0,0,Z45/$Z$2*$AA$2),NA()),NA()) -> 0.05052779 | AH45: -0.2 | AI45: =SQRT(MAX(0,1-AH45^2)) -> 0.9797959 | AJ45: =IF(ISNUMBER($B$18),IF(AND($C$18=1,AH45<=-COS(PI()*$B$18)),AI45,NA()),NA()) -> #N/A | AK45: =IF(ISNUMBER($B$18),IF(AND($C$18=2,AH45<=-COS(PI()*$B$18)),AI45,NA()),NA()) -> #N/A | AL45: =IF(ISNUMBER($B$18),IF(AND($C$18=3,AH45<=-COS(PI()*$B$18)),AI45,NA()),NA()) -> #N/A | AM45: =IF(ISNUMBER($B$18),IF(AND($C$18=4,AH45<=-COS(PI()*$B$18)),AI45,NA()),NA()) -> #N/A | AN45: =IF(ISNUMBER($B$18),IF(AND($C$18=5,AH45<=-COS(PI()*$B$18)),AI45,NA()),NA()) -> #N/A | AO45: =IF(ISNUMBER($B$18),IF(AND(ISNUMBER($B$18),AH45>=MIN(0,$AH$2),AH45<=MAX(0,$AH$2)),IF($AH$2=0,0,AH45/$AH$2*$AI$2),NA()),NA()) -> 0.13776478
R46: -0.18 | S46: =SQRT(MAX(0,1-R46^2)) -> 0.98366661 | T46: =IF(ISNUMBER($B$16),IF(AND($C$16=1,R46<=-COS(PI()*$B$16)),S46,NA()),NA()) -> #N/A | U46: =IF(ISNUMBER($B$16),IF(AND($C$16=2,R46<=-COS(PI()*$B$16)),S46,NA()),NA()) -> #N/A | V46: =IF(ISNUMBER($B$16),IF(AND($C$16=3,R46<=-COS(PI()*$B$16)),S46,NA()),NA()) -> #N/A | W46: =IF(ISNUMBER($B$16),IF(AND($C$16=4,R46<=-COS(PI()*$B$16)),S46,NA()),NA()) -> #N/A | X46: =IF(ISNUMBER($B$16),IF(AND($C$16=5,R46<=-COS(PI()*$B$16)),S46,NA()),NA()) -> #N/A | Y46: =IF(ISNUMBER($B$16),IF(AND(ISNUMBER($B$16),R46>=MIN(0,$R$2),R46<=MAX(0,$R$2)),IF($R$2=0,0,R46/$R$2*$S$2),NA()),NA()) -> 0.066875388 | Z46: -0.18 | AA46: =SQRT(MAX(0,1-Z46^2)) -> 0.98366661 | AB46: =IF(ISNUMBER($B$17),IF(AND($C$17=1,Z46<=-COS(PI()*$B$17)),AA46,NA()),NA()) -> #N/A | AC46: =IF(ISNUMBER($B$17),IF(AND($C$17=2,Z46<=-COS(PI()*$B$17)),AA46,NA()),NA()) -> #N/A | AD46: =IF(ISNUMBER($B$17),IF(AND($C$17=3,Z46<=-COS(PI()*$B$17)),AA46,NA()),NA()) -> #N/A | AE46: =IF(ISNUMBER($B$17),IF(AND($C$17=4,Z46<=-COS(PI()*$B$17)),AA46,NA()),NA()) -> #N/A | AF46: =IF(ISNUMBER($B$17),IF(AND($C$17=5,Z46<=-COS(PI()*$B$17)),AA46,NA()),NA()) -> #N/A | AG46: =IF(ISNUMBER($B$17),IF(AND(ISNUMBER($B$17),Z46>=MIN(0,$Z$2),Z46<=MAX(0,$Z$2)),IF($Z$2=0,0,Z46/$Z$2*$AA$2),NA()),NA()) -> 0.045475011 | AH46: -0.18 | AI46: =SQRT(MAX(0,1-AH46^2)) -> 0.98366661 | AJ46: =IF(ISNUMBER($B$18),IF(AND($C$18=1,AH46<=-COS(PI()*$B$18)),AI46,NA()),NA()) -> #N/A | AK46: =IF(ISNUMBER($B$18),IF(AND($C$18=2,AH46<=-COS(PI()*$B$18)),AI46,NA()),NA()) -> #N/A | AL46: =IF(ISNUMBER($B$18),IF(AND($C$18=3,AH46<=-COS(PI()*$B$18)),AI46,NA()),NA()) -> #N/A | AM46: =IF(ISNUMBER($B$18),IF(AND($C$18=4,AH46<=-COS(PI()*$B$18)),AI46,NA()),NA()) -> #N/A | AN46: =IF(ISNUMBER($B$18),IF(AND($C$18=5,AH46<=-COS(PI()*$B$18)),AI46,NA()),NA()) -> #N/A | AO46: =IF(ISNUMBER($B$18),IF(AND(ISNUMBER($B$18),AH46>=MIN(0,$AH$2),AH46<=MAX(0,$AH$2)),IF($AH$2=0,0,AH46/$AH$2*$AI$2),NA()),NA()) -> 0.1239883
R47: -0.16 | S47: =SQRT(MAX(0,1-R47^2)) -> 0.98711701 | T47: =IF(ISNUMBER($B$16),IF(AND($C$16=1,R47<=-COS(PI()*$B$16)),S47,NA()),NA()) -> #N/A | U47: =IF(ISNUMBER($B$16),IF(AND($C$16=2,R47<=-COS(PI()*$B$16)),S47,NA()),NA()) -> #N/A | V47: =IF(ISNUMBER($B$16),IF(AND($C$16=3,R47<=-COS(PI()*$B$16)),S47,NA()),NA()) -> #N/A | W47: =IF(ISNUMBER($B$16),IF(AND($C$16=4,R47<=-COS(PI()*$B$16)),S47,NA()),NA()) -> #N/A | X47: =IF(ISNUMBER($B$16),IF(AND($C$16=5,R47<=-COS(PI()*$B$16)),S47,NA()),NA()) -> #N/A | Y47: =IF(ISNUMBER($B$16),IF(AND(ISNUMBER($B$16),R47>=MIN(0,$R$2),R47<=MAX(0,$R$2)),IF($R$2=0,0,R47/$R$2*$S$2),NA()),NA()) -> 0.059444789 | Z47: -0.16 | AA47: =SQRT(MAX(0,1-Z47^2)) -> 0.98711701 | AB47: =IF(ISNUMBER($B$17),IF(AND($C$17=1,Z47<=-COS(PI()*$B$17)),AA47,NA()),NA()) -> #N/A | AC47: =IF(ISNUMBER($B$17),IF(AND($C$17=2,Z47<=-COS(PI()*$B$17)),AA47,NA()),NA()) -> #N/A | AD47: =IF(ISNUMBER($B$17),IF(AND($C$17=3,Z47<=-COS(PI()*$B$17)),AA47,NA()),NA()) -> #N/A | AE47: =IF(ISNUMBER($B$17),IF(AND($C$17=4,Z47<=-COS(PI()*$B$17)),AA47,NA()),NA()) -> #N/A | AF47: =IF(ISNUMBER($B$17),IF(AND($C$17=5,Z47<=-COS(PI()*$B$17)),AA47,NA()),NA()) -> #N/A | AG47: =IF(ISNUMBER($B$17),IF(AND(ISNUMBER($B$17),Z47>=MIN(0,$Z$2),Z47<=MAX(0,$Z$2)),IF($Z$2=0,0,Z47/$Z$2*$AA$2),NA()),NA()) -> 0.040422232 | AH47: -0.16 | AI47: =SQRT(MAX(0,1-AH47^2)) -> 0.98711701 | AJ47: =IF(ISNUMBER($B$18),IF(AND($C$18=1,AH47<=-COS(PI()*$B$18)),AI47,NA()),NA()) -> #N/A | AK47: =IF(ISNUMBER($B$18),IF(AND($C$18=2,AH47<=-COS(PI()*$B$18)),AI47,NA()),NA()) -> #N/A | AL47: =IF(ISNUMBER($B$18),IF(AND($C$18=3,AH47<=-COS(PI()*$B$18)),AI47,NA()),NA()) -> #N/A | AM47: =IF(ISNUMBER($B$18),IF(AND($C$18=4,AH47<=-COS(PI()*$B$18)),AI47,NA()),NA()) -> #N/A | AN47: =IF(ISNUMBER($B$18),IF(AND($C$18=5,AH47<=-COS(PI()*$B$18)),AI47,NA()),NA()) -> #N/A | AO47: =IF(ISNUMBER($B$18),IF(AND(ISNUMBER($B$18),AH47>=MIN(0,$AH$2),AH47<=MAX(0,$AH$2)),IF($AH$2=0,0,AH47/$AH$2*$AI$2),NA()),NA()) -> 0.11021183
A48: Days 0–6 | B48: =SUMIFS('Current AR'!$V$6:$V$103,'Current AR'!$F$6:$F$103,">="&Dashboard!D2+0,'Current AR'!$F$6:$F$103,"<="&Dashboard!D2+6) -> 6.5134679e+08 | R48: -0.14 | S48: =SQRT(MAX(0,1-R48^2)) -> 0.9901515 | T48: =IF(ISNUMBER($B$16),IF(AND($C$16=1,R48<=-COS(PI()*$B$16)),S48,NA()),NA()) -> #N/A | U48: =IF(ISNUMBER($B$16),IF(AND($C$16=2,R48<=-COS(PI()*$B$16)),S48,NA()),NA()) -> #N/A | V48: =IF(ISNUMBER($B$16),IF(AND($C$16=3,R48<=-COS(PI()*$B$16)),S48,NA()),NA()) -> #N/A | W48: =IF(ISNUMBER($B$16),IF(AND($C$16=4,R48<=-COS(PI()*$B$16)),S48,NA()),NA()) -> #N/A | X48: =IF(ISNUMBER($B$16),IF(AND($C$16=5,R48<=-COS(PI()*$B$16)),S48,NA()),NA()) -> #N/A | Y48: =IF(ISNUMBER($B$16),IF(AND(ISNUMBER($B$16),R48>=MIN(0,$R$2),R48<=MAX(0,$R$2)),IF($R$2=0,0,R48/$R$2*$S$2),NA()),NA()) -> 0.05201419 | Z48: -0.14 | AA48: =SQRT(MAX(0,1-Z48^2)) -> 0.9901515 | AB48: =IF(ISNUMBER($B$17),IF(AND($C$17=1,Z48<=-COS(PI()*$B$17)),AA48,NA()),NA()) -> #N/A | AC48: =IF(ISNUMBER($B$17),IF(AND($C$17=2,Z48<=-COS(PI()*$B$17)),AA48,NA()),NA()) -> #N/A | AD48: =IF(ISNUMBER($B$17),IF(AND($C$17=3,Z48<=-COS(PI()*$B$17)),AA48,NA()),NA()) -> #N/A | AE48: =IF(ISNUMBER($B$17),IF(AND($C$17=4,Z48<=-COS(PI()*$B$17)),AA48,NA()),NA()) -> #N/A | AF48: =IF(ISNUMBER($B$17),IF(AND($C$17=5,Z48<=-COS(PI()*$B$17)),AA48,NA()),NA()) -> #N/A | AG48: =IF(ISNUMBER($B$17),IF(AND(ISNUMBER($B$17),Z48>=MIN(0,$Z$2),Z48<=MAX(0,$Z$2)),IF($Z$2=0,0,Z48/$Z$2*$AA$2),NA()),NA()) -> 0.035369453 | AH48: -0.14 | AI48: =SQRT(MAX(0,1-AH48^2)) -> 0.9901515 | AJ48: =IF(ISNUMBER($B$18),IF(AND($C$18=1,AH48<=-COS(PI()*$B$18)),AI48,NA()),NA()) -> #N/A | AK48: =IF(ISNUMBER($B$18),IF(AND($C$18=2,AH48<=-COS(PI()*$B$18)),AI48,NA()),NA()) -> #N/A | AL48: =IF(ISNUMBER($B$18),IF(AND($C$18=3,AH48<=-COS(PI()*$B$18)),AI48,NA()),NA()) -> #N/A | AM48: =IF(ISNUMBER($B$18),IF(AND($C$18=4,AH48<=-COS(PI()*$B$18)),AI48,NA()),NA()) -> #N/A | AN48: =IF(ISNUMBER($B$18),IF(AND($C$18=5,AH48<=-COS(PI()*$B$18)),AI48,NA()),NA()) -> #N/A | AO48: =IF(ISNUMBER($B$18),IF(AND(ISNUMBER($B$18),AH48>=MIN(0,$AH$2),AH48<=MAX(0,$AH$2)),IF($AH$2=0,0,AH48/$AH$2*$AI$2),NA()),NA()) -> 0.096435348 | BC48: =IF(B48=0,"",IF(ABS(B48)>=1000000000,TEXT(B48/1000000000,IF(MOD(ROUND(B48/1000000000,2),1)=0,"0","0.00"))&" B VND",IF(ABS(B48)>=1000000,TEXT(B48/1000000,IF(MOD(ROUND(B48/1000000,2),1)=0,"0","0.00"))&" M VND",TEXT(B48/1000,IF(MOD(ROUND(B48/1000,2),1)=0,"0","0.00"))&"k"))) -> 621.93M VND
A49: Days 7–13 | B49: =SUMIFS('Current AR'!$V$6:$V$103,'Current AR'!$F$6:$F$103,">="&Dashboard!D2+7,'Current AR'!$F$6:$F$103,"<="&Dashboard!D2+13) -> 3.1594499e+09 | R49: -0.12 | S49: =SQRT(MAX(0,1-R49^2)) -> 0.99277389 | T49: =IF(ISNUMBER($B$16),IF(AND($C$16=1,R49<=-COS(PI()*$B$16)),S49,NA()),NA()) -> #N/A | U49: =IF(ISNUMBER($B$16),IF(AND($C$16=2,R49<=-COS(PI()*$B$16)),S49,NA()),NA()) -> #N/A | V49: =IF(ISNUMBER($B$16),IF(AND($C$16=3,R49<=-COS(PI()*$B$16)),S49,NA()),NA()) -> #N/A | W49: =IF(ISNUMBER($B$16),IF(AND($C$16=4,R49<=-COS(PI()*$B$16)),S49,NA()),NA()) -> #N/A | X49: =IF(ISNUMBER($B$16),IF(AND($C$16=5,R49<=-COS(PI()*$B$16)),S49,NA()),NA()) -> #N/A | Y49: =IF(ISNUMBER($B$16),IF(AND(ISNUMBER($B$16),R49>=MIN(0,$R$2),R49<=MAX(0,$R$2)),IF($R$2=0,0,R49/$R$2*$S$2),NA()),NA()) -> 0.044583592 | Z49: -0.12 | AA49: =SQRT(MAX(0,1-Z49^2)) -> 0.99277389 | AB49: =IF(ISNUMBER($B$17),IF(AND($C$17=1,Z49<=-COS(PI()*$B$17)),AA49,NA()),NA()) -> #N/A | AC49: =IF(ISNUMBER($B$17),IF(AND($C$17=2,Z49<=-COS(PI()*$B$17)),AA49,NA()),NA()) -> #N/A | AD49: =IF(ISNUMBER($B$17),IF(AND($C$17=3,Z49<=-COS(PI()*$B$17)),AA49,NA()),NA()) -> #N/A | AE49: =IF(ISNUMBER($B$17),IF(AND($C$17=4,Z49<=-COS(PI()*$B$17)),AA49,NA()),NA()) -> #N/A | AF49: =IF(ISNUMBER($B$17),IF(AND($C$17=5,Z49<=-COS(PI()*$B$17)),AA49,NA()),NA()) -> #N/A | AG49: =IF(ISNUMBER($B$17),IF(AND(ISNUMBER($B$17),Z49>=MIN(0,$Z$2),Z49<=MAX(0,$Z$2)),IF($Z$2=0,0,Z49/$Z$2*$AA$2),NA()),NA()) -> 0.030316674 | AH49: -0.12 | AI49: =SQRT(MAX(0,1-AH49^2)) -> 0.99277389 | AJ49: =IF(ISNUMBER($B$18),IF(AND($C$18=1,AH49<=-COS(PI()*$B$18)),AI49,NA()),NA()) -> #N/A | AK49: =IF(ISNUMBER($B$18),IF(AND($C$18=2,AH49<=-COS(PI()*$B$18)),AI49,NA()),NA()) -> #N/A | AL49: =IF(ISNUMBER($B$18),IF(AND($C$18=3,AH49<=-COS(PI()*$B$18)),AI49,NA()),NA()) -> #N/A | AM49: =IF(ISNUMBER($B$18),IF(AND($C$18=4,AH49<=-COS(PI()*$B$18)),AI49,NA()),NA()) -> #N/A | AN49: =IF(ISNUMBER($B$18),IF(AND($C$18=5,AH49<=-COS(PI()*$B$18)),AI49,NA()),NA()) -> #N/A | AO49: =IF(ISNUMBER($B$18),IF(AND(ISNUMBER($B$18),AH49>=MIN(0,$AH$2),AH49<=MAX(0,$AH$2)),IF($AH$2=0,0,AH49/$AH$2*$AI$2),NA()),NA()) -> 0.08265887 | BC49: =IF(B49=0,"",IF(ABS(B49)>=1000000000,TEXT(B49/1000000000,IF(MOD(ROUND(B49/1000000000,2),1)=0,"0","0.00"))&" B VND",IF(ABS(B49)>=1000000,TEXT(B49/1000000,IF(MOD(ROUND(B49/1000000,2),1)=0,"0","0.00"))&" M VND",TEXT(B49/1000,IF(MOD(ROUND(B49/1000,2),1)=0,"0","0.00"))&"k"))) -> 3.02B VND
A50: Days 14–20 | B50: =SUMIFS('Current AR'!$V$6:$V$103,'Current AR'!$F$6:$F$103,">="&Dashboard!D2+14,'Current AR'!$F$6:$F$103,"<="&Dashboard!D2+20) -> 0 | R50: -0.1 | S50: =SQRT(MAX(0,1-R50^2)) -> 0.99498744 | T50: =IF(ISNUMBER($B$16),IF(AND($C$16=1,R50<=-COS(PI()*$B$16)),S50,NA()),NA()) -> #N/A | U50: =IF(ISNUMBER($B$16),IF(AND($C$16=2,R50<=-COS(PI()*$B$16)),S50,NA()),NA()) -> #N/A | V50: =IF(ISNUMBER($B$16),IF(AND($C$16=3,R50<=-COS(PI()*$B$16)),S50,NA()),NA()) -> #N/A | W50: =IF(ISNUMBER($B$16),IF(AND($C$16=4,R50<=-COS(PI()*$B$16)),S50,NA()),NA()) -> #N/A | X50: =IF(ISNUMBER($B$16),IF(AND($C$16=5,R50<=-COS(PI()*$B$16)),S50,NA()),NA()) -> #N/A | Y50: =IF(ISNUMBER($B$16),IF(AND(ISNUMBER($B$16),R50>=MIN(0,$R$2),R50<=MAX(0,$R$2)),IF($R$2=0,0,R50/$R$2*$S$2),NA()),NA()) -> 0.037152993 | Z50: -0.1 | AA50: =SQRT(MAX(0,1-Z50^2)) -> 0.99498744 | AB50: =IF(ISNUMBER($B$17),IF(AND($C$17=1,Z50<=-COS(PI()*$B$17)),AA50,NA()),NA()) -> #N/A | AC50: =IF(ISNUMBER($B$17),IF(AND($C$17=2,Z50<=-COS(PI()*$B$17)),AA50,NA()),NA()) -> #N/A | AD50: =IF(ISNUMBER($B$17),IF(AND($C$17=3,Z50<=-COS(PI()*$B$17)),AA50,NA()),NA()) -> #N/A | AE50: =IF(ISNUMBER($B$17),IF(AND($C$17=4,Z50<=-COS(PI()*$B$17)),AA50,NA()),NA()) -> #N/A | AF50: =IF(ISNUMBER($B$17),IF(AND($C$17=5,Z50<=-COS(PI()*$B$17)),AA50,NA()),NA()) -> #N/A | AG50: =IF(ISNUMBER($B$17),IF(AND(ISNUMBER($B$17),Z50>=MIN(0,$Z$2),Z50<=MAX(0,$Z$2)),IF($Z$2=0,0,Z50/$Z$2*$AA$2),NA()),NA()) -> 0.025263895 | AH50: -0.1 | AI50: =SQRT(MAX(0,1-AH50^2)) -> 0.99498744 | AJ50: =IF(ISNUMBER($B$18),IF(AND($C$18=1,AH50<=-COS(PI()*$B$18)),AI50,NA()),NA()) -> #N/A | AK50: =IF(ISNUMBER($B$18),IF(AND($C$18=2,AH50<=-COS(PI()*$B$18)),AI50,NA()),NA()) -> #N/A | AL50: =IF(ISNUMBER($B$18),IF(AND($C$18=3,AH50<=-COS(PI()*$B$18)),AI50,NA()),NA()) -> #N/A | AM50: =IF(ISNUMBER($B$18),IF(AND($C$18=4,AH50<=-COS(PI()*$B$18)),AI50,NA()),NA()) -> #N/A | AN50: =IF(ISNUMBER($B$18),IF(AND($C$18=5,AH50<=-COS(PI()*$B$18)),AI50,NA()),NA()) -> #N/A | AO50: =IF(ISNUMBER($B$18),IF(AND(ISNUMBER($B$18),AH50>=MIN(0,$AH$2),AH50<=MAX(0,$AH$2)),IF($AH$2=0,0,AH50/$AH$2*$AI$2),NA()),NA()) -> 0.068882392 | BC50: =IF(B50=0,"",IF(ABS(B50)>=1000000000,TEXT(B50/1000000000,IF(MOD(ROUND(B50/1000000000,2),1)=0,"0","0.00"))&" B VND",IF(ABS(B50)>=1000000,TEXT(B50/1000000,IF(MOD(ROUND(B50/1000000,2),1)=0,"0","0.00"))&" M VND",TEXT(B50/1000,IF(MOD(ROUND(B50/1000,2),1)=0,"0","0.00"))&"k")))
A51: Days 21–27 | B51: =SUMIFS('Current AR'!$V$6:$V$103,'Current AR'!$F$6:$F$103,">="&Dashboard!D2+21,'Current AR'!$F$6:$F$103,"<="&Dashboard!D2+27) -> 4.9412661e+08 | R51: -0.08 | S51: =SQRT(MAX(0,1-R51^2)) -> 0.99679486 | T51: =IF(ISNUMBER($B$16),IF(AND($C$16=1,R51<=-COS(PI()*$B$16)),S51,NA()),NA()) -> #N/A | U51: =IF(ISNUMBER($B$16),IF(AND($C$16=2,R51<=-COS(PI()*$B$16)),S51,NA()),NA()) -> #N/A | V51: =IF(ISNUMBER($B$16),IF(AND($C$16=3,R51<=-COS(PI()*$B$16)),S51,NA()),NA()) -> #N/A | W51: =IF(ISNUMBER($B$16),IF(AND($C$16=4,R51<=-COS(PI()*$B$16)),S51,NA()),NA()) -> #N/A | X51: =IF(ISNUMBER($B$16),IF(AND($C$16=5,R51<=-COS(PI()*$B$16)),S51,NA()),NA()) -> #N/A | Y51: =IF(ISNUMBER($B$16),IF(AND(ISNUMBER($B$16),R51>=MIN(0,$R$2),R51<=MAX(0,$R$2)),IF($R$2=0,0,R51/$R$2*$S$2),NA()),NA()) -> 0.029722394 | Z51: -0.08 | AA51: =SQRT(MAX(0,1-Z51^2)) -> 0.99679486 | AB51: =IF(ISNUMBER($B$17),IF(AND($C$17=1,Z51<=-COS(PI()*$B$17)),AA51,NA()),NA()) -> #N/A | AC51: =IF(ISNUMBER($B$17),IF(AND($C$17=2,Z51<=-COS(PI()*$B$17)),AA51,NA()),NA()) -> #N/A | AD51: =IF(ISNUMBER($B$17),IF(AND($C$17=3,Z51<=-COS(PI()*$B$17)),AA51,NA()),NA()) -> #N/A | AE51: =IF(ISNUMBER($B$17),IF(AND($C$17=4,Z51<=-COS(PI()*$B$17)),AA51,NA()),NA()) -> #N/A | AF51: =IF(ISNUMBER($B$17),IF(AND($C$17=5,Z51<=-COS(PI()*$B$17)),AA51,NA()),NA()) -> #N/A | AG51: =IF(ISNUMBER($B$17),IF(AND(ISNUMBER($B$17),Z51>=MIN(0,$Z$2),Z51<=MAX(0,$Z$2)),IF($Z$2=0,0,Z51/$Z$2*$AA$2),NA()),NA()) -> 0.020211116 | AH51: -0.08 | AI51: =SQRT(MAX(0,1-AH51^2)) -> 0.99679486 | AJ51: =IF(ISNUMBER($B$18),IF(AND($C$18=1,AH51<=-COS(PI()*$B$18)),AI51,NA()),NA()) -> #N/A | AK51: =IF(ISNUMBER($B$18),IF(AND($C$18=2,AH51<=-COS(PI()*$B$18)),AI51,NA()),NA()) -> #N/A | AL51: =IF(ISNUMBER($B$18),IF(AND($C$18=3,AH51<=-COS(PI()*$B$18)),AI51,NA()),NA()) -> #N/A | AM51: =IF(ISNUMBER($B$18),IF(AND($C$18=4,AH51<=-COS(PI()*$B$18)),AI51,NA()),NA()) -> #N/A | AN51: =IF(ISNUMBER($B$18),IF(AND($C$18=5,AH51<=-COS(PI()*$B$18)),AI51,NA()),NA()) -> #N/A | AO51: =IF(ISNUMBER($B$18),IF(AND(ISNUMBER($B$18),AH51>=MIN(0,$AH$2),AH51<=MAX(0,$AH$2)),IF($AH$2=0,0,AH51/$AH$2*$AI$2),NA()),NA()) -> 0.055105913 | BC51: =IF(B51=0,"",IF(ABS(B51)>=1000000000,TEXT(B51/1000000000,IF(MOD(ROUND(B51/1000000000,2),1)=0,"0","0.00"))&" B VND",IF(ABS(B51)>=1000000,TEXT(B51/1000000,IF(MOD(ROUND(B51/1000000,2),1)=0,"0","0.00"))&" M VND",TEXT(B51/1000,IF(MOD(ROUND(B51/1000,2),1)=0,"0","0.00"))&"k"))) -> 471.81M VND
A52: Days 28–30 | B52: =SUMIFS('Current AR'!$V$6:$V$103,'Current AR'!$F$6:$F$103,">="&Dashboard!D2+28,'Current AR'!$F$6:$F$103,"<="&Dashboard!D2+30) -> 9.322049e+08 | R52: -0.06 | S52: =SQRT(MAX(0,1-R52^2)) -> 0.99819838 | T52: =IF(ISNUMBER($B$16),IF(AND($C$16=1,R52<=-COS(PI()*$B$16)),S52,NA()),NA()) -> #N/A | U52: =IF(ISNUMBER($B$16),IF(AND($C$16=2,R52<=-COS(PI()*$B$16)),S52,NA()),NA()) -> #N/A | V52: =IF(ISNUMBER($B$16),IF(AND($C$16=3,R52<=-COS(PI()*$B$16)),S52,NA()),NA()) -> #N/A | W52: =IF(ISNUMBER($B$16),IF(AND($C$16=4,R52<=-COS(PI()*$B$16)),S52,NA()),NA()) -> #N/A | X52: =IF(ISNUMBER($B$16),IF(AND($C$16=5,R52<=-COS(PI()*$B$16)),S52,NA()),NA()) -> #N/A | Y52: =IF(ISNUMBER($B$16),IF(AND(ISNUMBER($B$16),R52>=MIN(0,$R$2),R52<=MAX(0,$R$2)),IF($R$2=0,0,R52/$R$2*$S$2),NA()),NA()) -> 0.022291796 | Z52: -0.06 | AA52: =SQRT(MAX(0,1-Z52^2)) -> 0.99819838 | AB52: =IF(ISNUMBER($B$17),IF(AND($C$17=1,Z52<=-COS(PI()*$B$17)),AA52,NA()),NA()) -> #N/A | AC52: =IF(ISNUMBER($B$17),IF(AND($C$17=2,Z52<=-COS(PI()*$B$17)),AA52,NA()),NA()) -> #N/A | AD52: =IF(ISNUMBER($B$17),IF(AND($C$17=3,Z52<=-COS(PI()*$B$17)),AA52,NA()),NA()) -> #N/A | AE52: =IF(ISNUMBER($B$17),IF(AND($C$17=4,Z52<=-COS(PI()*$B$17)),AA52,NA()),NA()) -> #N/A | AF52: =IF(ISNUMBER($B$17),IF(AND($C$17=5,Z52<=-COS(PI()*$B$17)),AA52,NA()),NA()) -> #N/A | AG52: =IF(ISNUMBER($B$17),IF(AND(ISNUMBER($B$17),Z52>=MIN(0,$Z$2),Z52<=MAX(0,$Z$2)),IF($Z$2=0,0,Z52/$Z$2*$AA$2),NA()),NA()) -> 0.015158337 | AH52: -0.06 | AI52: =SQRT(MAX(0,1-AH52^2)) -> 0.99819838 | AJ52: =IF(ISNUMBER($B$18),IF(AND($C$18=1,AH52<=-COS(PI()*$B$18)),AI52,NA()),NA()) -> #N/A | AK52: =IF(ISNUMBER($B$18),IF(AND($C$18=2,AH52<=-COS(PI()*$B$18)),AI52,NA()),NA()) -> #N/A | AL52: =IF(ISNUMBER($B$18),IF(AND($C$18=3,AH52<=-COS(PI()*$B$18)),AI52,NA()),NA()) -> #N/A | AM52: =IF(ISNUMBER($B$18),IF(AND($C$18=4,AH52<=-COS(PI()*$B$18)),AI52,NA()),NA()) -> #N/A | AN52: =IF(ISNUMBER($B$18),IF(AND($C$18=5,AH52<=-COS(PI()*$B$18)),AI52,NA()),NA()) -> #N/A | AO52: =IF(ISNUMBER($B$18),IF(AND(ISNUMBER($B$18),AH52>=MIN(0,$AH$2),AH52<=MAX(0,$AH$2)),IF($AH$2=0,0,AH52/$AH$2*$AI$2),NA()),NA()) -> 0.041329435 | BC52: =IF(B52=0,"",IF(ABS(B52)>=1000000000,TEXT(B52/1000000000,IF(MOD(ROUND(B52/1000000000,2),1)=0,"0","0.00"))&" B VND",IF(ABS(B52)>=1000000,TEXT(B52/1000000,IF(MOD(ROUND(B52/1000000,2),1)=0,"0","0.00"))&" M VND",TEXT(B52/1000,IF(MOD(ROUND(B52/1000,2),1)=0,"0","0.00"))&"k"))) -> 890.10M VND
R53: -0.04 | S53: =SQRT(MAX(0,1-R53^2)) -> 0.99919968 | T53: =IF(ISNUMBER($B$16),IF(AND($C$16=1,R53<=-COS(PI()*$B$16)),S53,NA()),NA()) -> #N/A | U53: =IF(ISNUMBER($B$16),IF(AND($C$16=2,R53<=-COS(PI()*$B$16)),S53,NA()),NA()) -> #N/A | V53: =IF(ISNUMBER($B$16),IF(AND($C$16=3,R53<=-COS(PI()*$B$16)),S53,NA()),NA()) -> #N/A | W53: =IF(ISNUMBER($B$16),IF(AND($C$16=4,R53<=-COS(PI()*$B$16)),S53,NA()),NA()) -> #N/A | X53: =IF(ISNUMBER($B$16),IF(AND($C$16=5,R53<=-COS(PI()*$B$16)),S53,NA()),NA()) -> #N/A | Y53: =IF(ISNUMBER($B$16),IF(AND(ISNUMBER($B$16),R53>=MIN(0,$R$2),R53<=MAX(0,$R$2)),IF($R$2=0,0,R53/$R$2*$S$2),NA()),NA()) -> 0.014861197 | Z53: -0.04 | AA53: =SQRT(MAX(0,1-Z53^2)) -> 0.99919968 | AB53: =IF(ISNUMBER($B$17),IF(AND($C$17=1,Z53<=-COS(PI()*$B$17)),AA53,NA()),NA()) -> #N/A | AC53: =IF(ISNUMBER($B$17),IF(AND($C$17=2,Z53<=-COS(PI()*$B$17)),AA53,NA()),NA()) -> #N/A | AD53: =IF(ISNUMBER($B$17),IF(AND($C$17=3,Z53<=-COS(PI()*$B$17)),AA53,NA()),NA()) -> #N/A | AE53: =IF(ISNUMBER($B$17),IF(AND($C$17=4,Z53<=-COS(PI()*$B$17)),AA53,NA()),NA()) -> #N/A | AF53: =IF(ISNUMBER($B$17),IF(AND($C$17=5,Z53<=-COS(PI()*$B$17)),AA53,NA()),NA()) -> #N/A | AG53: =IF(ISNUMBER($B$17),IF(AND(ISNUMBER($B$17),Z53>=MIN(0,$Z$2),Z53<=MAX(0,$Z$2)),IF($Z$2=0,0,Z53/$Z$2*$AA$2),NA()),NA()) -> 0.010105558 | AH53: -0.04 | AI53: =SQRT(MAX(0,1-AH53^2)) -> 0.99919968 | AJ53: =IF(ISNUMBER($B$18),IF(AND($C$18=1,AH53<=-COS(PI()*$B$18)),AI53,NA()),NA()) -> #N/A | AK53: =IF(ISNUMBER($B$18),IF(AND($C$18=2,AH53<=-COS(PI()*$B$18)),AI53,NA()),NA()) -> #N/A | AL53: =IF(ISNUMBER($B$18),IF(AND($C$18=3,AH53<=-COS(PI()*$B$18)),AI53,NA()),NA()) -> #N/A | AM53: =IF(ISNUMBER($B$18),IF(AND($C$18=4,AH53<=-COS(PI()*$B$18)),AI53,NA()),NA()) -> #N/A | AN53: =IF(ISNUMBER($B$18),IF(AND($C$18=5,AH53<=-COS(PI()*$B$18)),AI53,NA()),NA()) -> #N/A | AO53: =IF(ISNUMBER($B$18),IF(AND(ISNUMBER($B$18),AH53>=MIN(0,$AH$2),AH53<=MAX(0,$AH$2)),IF($AH$2=0,0,AH53/$AH$2*$AI$2),NA()),NA()) -> 0.027552957
R54: -0.02 | S54: =SQRT(MAX(0,1-R54^2)) -> 0.99979998 | T54: =IF(ISNUMBER($B$16),IF(AND($C$16=1,R54<=-COS(PI()*$B$16)),S54,NA()),NA()) -> #N/A | U54: =IF(ISNUMBER($B$16),IF(AND($C$16=2,R54<=-COS(PI()*$B$16)),S54,NA()),NA()) -> #N/A | V54: =IF(ISNUMBER($B$16),IF(AND($C$16=3,R54<=-COS(PI()*$B$16)),S54,NA()),NA()) -> #N/A | W54: =IF(ISNUMBER($B$16),IF(AND($C$16=4,R54<=-COS(PI()*$B$16)),S54,NA()),NA()) -> #N/A | X54: =IF(ISNUMBER($B$16),IF(AND($C$16=5,R54<=-COS(PI()*$B$16)),S54,NA()),NA()) -> #N/A | Y54: =IF(ISNUMBER($B$16),IF(AND(ISNUMBER($B$16),R54>=MIN(0,$R$2),R54<=MAX(0,$R$2)),IF($R$2=0,0,R54/$R$2*$S$2),NA()),NA()) -> 0.0074305986 | Z54: -0.02 | AA54: =SQRT(MAX(0,1-Z54^2)) -> 0.99979998 | AB54: =IF(ISNUMBER($B$17),IF(AND($C$17=1,Z54<=-COS(PI()*$B$17)),AA54,NA()),NA()) -> #N/A | AC54: =IF(ISNUMBER($B$17),IF(AND($C$17=2,Z54<=-COS(PI()*$B$17)),AA54,NA()),NA()) -> #N/A | AD54: =IF(ISNUMBER($B$17),IF(AND($C$17=3,Z54<=-COS(PI()*$B$17)),AA54,NA()),NA()) -> #N/A | AE54: =IF(ISNUMBER($B$17),IF(AND($C$17=4,Z54<=-COS(PI()*$B$17)),AA54,NA()),NA()) -> #N/A | AF54: =IF(ISNUMBER($B$17),IF(AND($C$17=5,Z54<=-COS(PI()*$B$17)),AA54,NA()),NA()) -> #N/A | AG54: =IF(ISNUMBER($B$17),IF(AND(ISNUMBER($B$17),Z54>=MIN(0,$Z$2),Z54<=MAX(0,$Z$2)),IF($Z$2=0,0,Z54/$Z$2*$AA$2),NA()),NA()) -> 0.005052779 | AH54: -0.02 | AI54: =SQRT(MAX(0,1-AH54^2)) -> 0.99979998 | AJ54: =IF(ISNUMBER($B$18),IF(AND($C$18=1,AH54<=-COS(PI()*$B$18)),AI54,NA()),NA()) -> #N/A | AK54: =IF(ISNUMBER($B$18),IF(AND($C$18=2,AH54<=-COS(PI()*$B$18)),AI54,NA()),NA()) -> #N/A | AL54: =IF(ISNUMBER($B$18),IF(AND($C$18=3,AH54<=-COS(PI()*$B$18)),AI54,NA()),NA()) -> #N/A | AM54: =IF(ISNUMBER($B$18),IF(AND($C$18=4,AH54<=-COS(PI()*$B$18)),AI54,NA()),NA()) -> #N/A | AN54: =IF(ISNUMBER($B$18),IF(AND($C$18=5,AH54<=-COS(PI()*$B$18)),AI54,NA()),NA()) -> #N/A | AO54: =IF(ISNUMBER($B$18),IF(AND(ISNUMBER($B$18),AH54>=MIN(0,$AH$2),AH54<=MAX(0,$AH$2)),IF($AH$2=0,0,AH54/$AH$2*$AI$2),NA()),NA()) -> 0.013776478
A55: Metric | B55: Current | C55: Prior | D55: Difference | E55: Change (%) | R55: 0 | S55: =SQRT(MAX(0,1-R55^2)) -> 1 | T55: =IF(ISNUMBER($B$16),IF(AND($C$16=1,R55<=-COS(PI()*$B$16)),S55,NA()),NA()) -> #N/A | U55: =IF(ISNUMBER($B$16),IF(AND($C$16=2,R55<=-COS(PI()*$B$16)),S55,NA()),NA()) -> #N/A | V55: =IF(ISNUMBER($B$16),IF(AND($C$16=3,R55<=-COS(PI()*$B$16)),S55,NA()),NA()) -> #N/A | W55: =IF(ISNUMBER($B$16),IF(AND($C$16=4,R55<=-COS(PI()*$B$16)),S55,NA()),NA()) -> #N/A | X55: =IF(ISNUMBER($B$16),IF(AND($C$16=5,R55<=-COS(PI()*$B$16)),S55,NA()),NA()) -> #N/A | Y55: =IF(ISNUMBER($B$16),IF(AND(ISNUMBER($B$16),R55>=MIN(0,$R$2),R55<=MAX(0,$R$2)),IF($R$2=0,0,R55/$R$2*$S$2),NA()),NA()) -> 0 | Z55: 0 | AA55: =SQRT(MAX(0,1-Z55^2)) -> 1 | AB55: =IF(ISNUMBER($B$17),IF(AND($C$17=1,Z55<=-COS(PI()*$B$17)),AA55,NA()),NA()) -> #N/A | AC55: =IF(ISNUMBER($B$17),IF(AND($C$17=2,Z55<=-COS(PI()*$B$17)),AA55,NA()),NA()) -> #N/A | AD55: =IF(ISNUMBER($B$17),IF(AND($C$17=3,Z55<=-COS(PI()*$B$17)),AA55,NA()),NA()) -> #N/A | AE55: =IF(ISNUMBER($B$17),IF(AND($C$17=4,Z55<=-COS(PI()*$B$17)),AA55,NA()),NA()) -> #N/A | AF55: =IF(ISNUMBER($B$17),IF(AND($C$17=5,Z55<=-COS(PI()*$B$17)),AA55,NA()),NA()) -> #N/A | AG55: =IF(ISNUMBER($B$17),IF(AND(ISNUMBER($B$17),Z55>=MIN(0,$Z$2),Z55<=MAX(0,$Z$2)),IF($Z$2=0,0,Z55/$Z$2*$AA$2),NA()),NA()) -> 0 | AH55: 0 | AI55: =SQRT(MAX(0,1-AH55^2)) -> 1 | AJ55: =IF(ISNUMBER($B$18),IF(AND($C$18=1,AH55<=-COS(PI()*$B$18)),AI55,NA()),NA()) -> #N/A | AK55: =IF(ISNUMBER($B$18),IF(AND($C$18=2,AH55<=-COS(PI()*$B$18)),AI55,NA()),NA()) -> #N/A | AL55: =IF(ISNUMBER($B$18),IF(AND($C$18=3,AH55<=-COS(PI()*$B$18)),AI55,NA()),NA()) -> #N/A | AM55: =IF(ISNUMBER($B$18),IF(AND($C$18=4,AH55<=-COS(PI()*$B$18)),AI55,NA()),NA()) -> #N/A | AN55: =IF(ISNUMBER($B$18),IF(AND($C$18=5,AH55<=-COS(PI()*$B$18)),AI55,NA()),NA()) -> #N/A | AO55: =IF(ISNUMBER($B$18),IF(AND(ISNUMBER($B$18),AH55>=MIN(0,$AH$2),AH55<=MAX(0,$AH$2)),IF($AH$2=0,0,AH55/$AH$2*$AI$2),NA()),NA()) -> 0
A56: Average Overdue Days | B56: =IF(B9=0,"n.a.",SUM('Current AR'!$W$6:$W$103)/B9) -> 39.498015 | C56: =IF(C9=0,"n.a.",SUM('Prior AR'!$W$6:$W$85)/C9) -> 40.025012 | D56: =IF(AND(ISNUMBER(B56),ISNUMBER(C56)),B56-C56,"n.a.") -> -0.52699736 | E56: =IF(AND(ISNUMBER(C56),C56<>0,ISNUMBER(D56)),D56/C56,"n.a.") -> -0.013166701 | R56: 0.02 | S56: =SQRT(MAX(0,1-R56^2)) -> 0.99979998 | T56: =IF(ISNUMBER($B$16),IF(AND($C$16=1,R56<=-COS(PI()*$B$16)),S56,NA()),NA()) -> #N/A | U56: =IF(ISNUMBER($B$16),IF(AND($C$16=2,R56<=-COS(PI()*$B$16)),S56,NA()),NA()) -> #N/A | V56: =IF(ISNUMBER($B$16),IF(AND($C$16=3,R56<=-COS(PI()*$B$16)),S56,NA()),NA()) -> #N/A | W56: =IF(ISNUMBER($B$16),IF(AND($C$16=4,R56<=-COS(PI()*$B$16)),S56,NA()),NA()) -> #N/A | X56: =IF(ISNUMBER($B$16),IF(AND($C$16=5,R56<=-COS(PI()*$B$16)),S56,NA()),NA()) -> #N/A | Y56: =IF(ISNUMBER($B$16),IF(AND(ISNUMBER($B$16),R56>=MIN(0,$R$2),R56<=MAX(0,$R$2)),IF($R$2=0,0,R56/$R$2*$S$2),NA()),NA()) -> #N/A | Z56: 0.02 | AA56: =SQRT(MAX(0,1-Z56^2)) -> 0.99979998 | AB56: =IF(ISNUMBER($B$17),IF(AND($C$17=1,Z56<=-COS(PI()*$B$17)),AA56,NA()),NA()) -> #N/A | AC56: =IF(ISNUMBER($B$17),IF(AND($C$17=2,Z56<=-COS(PI()*$B$17)),AA56,NA()),NA()) -> #N/A | AD56: =IF(ISNUMBER($B$17),IF(AND($C$17=3,Z56<=-COS(PI()*$B$17)),AA56,NA()),NA()) -> #N/A | AE56: =IF(ISNUMBER($B$17),IF(AND($C$17=4,Z56<=-COS(PI()*$B$17)),AA56,NA()),NA()) -> #N/A | AF56: =IF(ISNUMBER($B$17),IF(AND($C$17=5,Z56<=-COS(PI()*$B$17)),AA56,NA()),NA()) -> #N/A | AG56: =IF(ISNUMBER($B$17),IF(AND(ISNUMBER($B$17),Z56>=MIN(0,$Z$2),Z56<=MAX(0,$Z$2)),IF($Z$2=0,0,Z56/$Z$2*$AA$2),NA()),NA()) -> #N/A | AH56: 0.02 | AI56: =SQRT(MAX(0,1-AH56^2)) -> 0.99979998 | AJ56: =IF(ISNUMBER($B$18),IF(AND($C$18=1,AH56<=-COS(PI()*$B$18)),AI56,NA()),NA()) -> #N/A | AK56: =IF(ISNUMBER($B$18),IF(AND($C$18=2,AH56<=-COS(PI()*$B$18)),AI56,NA()),NA()) -> #N/A | AL56: =IF(ISNUMBER($B$18),IF(AND($C$18=3,AH56<=-COS(PI()*$B$18)),AI56,NA()),NA()) -> #N/A | AM56: =IF(ISNUMBER($B$18),IF(AND($C$18=4,AH56<=-COS(PI()*$B$18)),AI56,NA()),NA()) -> #N/A | AN56: =IF(ISNUMBER($B$18),IF(AND($C$18=5,AH56<=-COS(PI()*$B$18)),AI56,NA()),NA()) -> #N/A | AO56: =IF(ISNUMBER($B$18),IF(AND(ISNUMBER($B$18),AH56>=MIN(0,$AH$2),AH56<=MAX(0,$AH$2)),IF($AH$2=0,0,AH56/$AH$2*$AI$2),NA()),NA()) -> #N/A
A57: >60d / Total Overdue | B57: =IF(B9=0,"n.a.",B8/B9) -> 0.41025641 | C57: =IF(C9=0,"n.a.",C8/C9) -> 0.41287979 | D57: =IF(AND(ISNUMBER(B57),ISNUMBER(C57)),B57-C57,"n.a.") -> -0.0026233795 | E57: =IF(AND(ISNUMBER(C57),C57<>0,ISNUMBER(D57)),D57/C57,"n.a.") -> -0.0063538578 | R57: 0.04 | S57: =SQRT(MAX(0,1-R57^2)) -> 0.99919968 | T57: =IF(ISNUMBER($B$16),IF(AND($C$16=1,R57<=-COS(PI()*$B$16)),S57,NA()),NA()) -> #N/A | U57: =IF(ISNUMBER($B$16),IF(AND($C$16=2,R57<=-COS(PI()*$B$16)),S57,NA()),NA()) -> #N/A | V57: =IF(ISNUMBER($B$16),IF(AND($C$16=3,R57<=-COS(PI()*$B$16)),S57,NA()),NA()) -> #N/A | W57: =IF(ISNUMBER($B$16),IF(AND($C$16=4,R57<=-COS(PI()*$B$16)),S57,NA()),NA()) -> #N/A | X57: =IF(ISNUMBER($B$16),IF(AND($C$16=5,R57<=-COS(PI()*$B$16)),S57,NA()),NA()) -> #N/A | Y57: =IF(ISNUMBER($B$16),IF(AND(ISNUMBER($B$16),R57>=MIN(0,$R$2),R57<=MAX(0,$R$2)),IF($R$2=0,0,R57/$R$2*$S$2),NA()),NA()) -> #N/A | Z57: 0.04 | AA57: =SQRT(MAX(0,1-Z57^2)) -> 0.99919968 | AB57: =IF(ISNUMBER($B$17),IF(AND($C$17=1,Z57<=-COS(PI()*$B$17)),AA57,NA()),NA()) -> #N/A | AC57: =IF(ISNUMBER($B$17),IF(AND($C$17=2,Z57<=-COS(PI()*$B$17)),AA57,NA()),NA()) -> #N/A | AD57: =IF(ISNUMBER($B$17),IF(AND($C$17=3,Z57<=-COS(PI()*$B$17)),AA57,NA()),NA()) -> #N/A | AE57: =IF(ISNUMBER($B$17),IF(AND($C$17=4,Z57<=-COS(PI()*$B$17)),AA57,NA()),NA()) -> #N/A | AF57: =IF(ISNUMBER($B$17),IF(AND($C$17=5,Z57<=-COS(PI()*$B$17)),AA57,NA()),NA()) -> #N/A | AG57: =IF(ISNUMBER($B$17),IF(AND(ISNUMBER($B$17),Z57>=MIN(0,$Z$2),Z57<=MAX(0,$Z$2)),IF($Z$2=0,0,Z57/$Z$2*$AA$2),NA()),NA()) -> #N/A | AH57: 0.04 | AI57: =SQRT(MAX(0,1-AH57^2)) -> 0.99919968 | AJ57: =IF(ISNUMBER($B$18),IF(AND($C$18=1,AH57<=-COS(PI()*$B$18)),AI57,NA()),NA()) -> #N/A | AK57: =IF(ISNUMBER($B$18),IF(AND($C$18=2,AH57<=-COS(PI()*$B$18)),AI57,NA()),NA()) -> #N/A | AL57: =IF(ISNUMBER($B$18),IF(AND($C$18=3,AH57<=-COS(PI()*$B$18)),AI57,NA()),NA()) -> #N/A | AM57: =IF(ISNUMBER($B$18),IF(AND($C$18=4,AH57<=-COS(PI()*$B$18)),AI57,NA()),NA()) -> #N/A | AN57: =IF(ISNUMBER($B$18),IF(AND($C$18=5,AH57<=-COS(PI()*$B$18)),AI57,NA()),NA()) -> #N/A | AO57: =IF(ISNUMBER($B$18),IF(AND(ISNUMBER($B$18),AH57>=MIN(0,$AH$2),AH57<=MAX(0,$AH$2)),IF($AH$2=0,0,AH57/$AH$2*$AI$2),NA()),NA()) -> #N/A
A58: Top Client Share | B58: =IF(B6=0,"n.a.",MAX(B170:B176)/B6) -> 0.76492308 | C58: =IF(C6=0,"n.a.",MAX(C170:C176)/C6) -> 0.69916801 | D58: =IF(AND(ISNUMBER(B58),ISNUMBER(C58)),B58-C58,"n.a.") -> 0.065755063 | E58: =IF(AND(ISNUMBER(C58),C58<>0,ISNUMBER(D58)),D58/C58,"n.a.") -> 0.094047585 | R58: 0.06 | S58: =SQRT(MAX(0,1-R58^2)) -> 0.99819838 | T58: =IF(ISNUMBER($B$16),IF(AND($C$16=1,R58<=-COS(PI()*$B$16)),S58,NA()),NA()) -> #N/A | U58: =IF(ISNUMBER($B$16),IF(AND($C$16=2,R58<=-COS(PI()*$B$16)),S58,NA()),NA()) -> #N/A | V58: =IF(ISNUMBER($B$16),IF(AND($C$16=3,R58<=-COS(PI()*$B$16)),S58,NA()),NA()) -> #N/A | W58: =IF(ISNUMBER($B$16),IF(AND($C$16=4,R58<=-COS(PI()*$B$16)),S58,NA()),NA()) -> #N/A | X58: =IF(ISNUMBER($B$16),IF(AND($C$16=5,R58<=-COS(PI()*$B$16)),S58,NA()),NA()) -> #N/A | Y58: =IF(ISNUMBER($B$16),IF(AND(ISNUMBER($B$16),R58>=MIN(0,$R$2),R58<=MAX(0,$R$2)),IF($R$2=0,0,R58/$R$2*$S$2),NA()),NA()) -> #N/A | Z58: 0.06 | AA58: =SQRT(MAX(0,1-Z58^2)) -> 0.99819838 | AB58: =IF(ISNUMBER($B$17),IF(AND($C$17=1,Z58<=-COS(PI()*$B$17)),AA58,NA()),NA()) -> #N/A | AC58: =IF(ISNUMBER($B$17),IF(AND($C$17=2,Z58<=-COS(PI()*$B$17)),AA58,NA()),NA()) -> #N/A | AD58: =IF(ISNUMBER($B$17),IF(AND($C$17=3,Z58<=-COS(PI()*$B$17)),AA58,NA()),NA()) -> #N/A | AE58: =IF(ISNUMBER($B$17),IF(AND($C$17=4,Z58<=-COS(PI()*$B$17)),AA58,NA()),NA()) -> #N/A | AF58: =IF(ISNUMBER($B$17),IF(AND($C$17=5,Z58<=-COS(PI()*$B$17)),AA58,NA()),NA()) -> #N/A | AG58: =IF(ISNUMBER($B$17),IF(AND(ISNUMBER($B$17),Z58>=MIN(0,$Z$2),Z58<=MAX(0,$Z$2)),IF($Z$2=0,0,Z58/$Z$2*$AA$2),NA()),NA()) -> #N/A | AH58: 0.06 | AI58: =SQRT(MAX(0,1-AH58^2)) -> 0.99819838 | AJ58: =IF(ISNUMBER($B$18),IF(AND($C$18=1,AH58<=-COS(PI()*$B$18)),AI58,NA()),NA()) -> #N/A | AK58: =IF(ISNUMBER($B$18),IF(AND($C$18=2,AH58<=-COS(PI()*$B$18)),AI58,NA()),NA()) -> #N/A | AL58: =IF(ISNUMBER($B$18),IF(AND($C$18=3,AH58<=-COS(PI()*$B$18)),AI58,NA()),NA()) -> #N/A | AM58: =IF(ISNUMBER($B$18),IF(AND($C$18=4,AH58<=-COS(PI()*$B$18)),AI58,NA()),NA()) -> #N/A | AN58: =IF(ISNUMBER($B$18),IF(AND($C$18=5,AH58<=-COS(PI()*$B$18)),AI58,NA()),NA()) -> #N/A | AO58: =IF(ISNUMBER($B$18),IF(AND(ISNUMBER($B$18),AH58>=MIN(0,$AH$2),AH58<=MAX(0,$AH$2)),IF($AH$2=0,0,AH58/$AH$2*$AI$2),NA()),NA()) -> #N/A
A59: Top 3 Clients Share | B59: =IF(B6=0,"n.a.",(IFERROR(LARGE(B170:B176,1),0)+IFERROR(LARGE(B170:B176,2),0)+IFERROR(LARGE(B170:B176,3),0))/B6) -> 0.91524492 | C59: =IF(C6=0,"n.a.",(IFERROR(LARGE(C170:C176,1),0)+IFERROR(LARGE(C170:C176,2),0)+IFERROR(LARGE(C170:C176,3),0))/C6) -> 0.95274425 | D59: =IF(AND(ISNUMBER(B59),ISNUMBER(C59)),B59-C59,"n.a.") -> -0.037499327 | E59: =IF(AND(ISNUMBER(C59),C59<>0,ISNUMBER(D59)),D59/C59,"n.a.") -> -0.039359279 | R59: 0.08 | S59: =SQRT(MAX(0,1-R59^2)) -> 0.99679486 | T59: =IF(ISNUMBER($B$16),IF(AND($C$16=1,R59<=-COS(PI()*$B$16)),S59,NA()),NA()) -> #N/A | U59: =IF(ISNUMBER($B$16),IF(AND($C$16=2,R59<=-COS(PI()*$B$16)),S59,NA()),NA()) -> #N/A | V59: =IF(ISNUMBER($B$16),IF(AND($C$16=3,R59<=-COS(PI()*$B$16)),S59,NA()),NA()) -> #N/A | W59: =IF(ISNUMBER($B$16),IF(AND($C$16=4,R59<=-COS(PI()*$B$16)),S59,NA()),NA()) -> #N/A | X59: =IF(ISNUMBER($B$16),IF(AND($C$16=5,R59<=-COS(PI()*$B$16)),S59,NA()),NA()) -> #N/A | Y59: =IF(ISNUMBER($B$16),IF(AND(ISNUMBER($B$16),R59>=MIN(0,$R$2),R59<=MAX(0,$R$2)),IF($R$2=0,0,R59/$R$2*$S$2),NA()),NA()) -> #N/A | Z59: 0.08 | AA59: =SQRT(MAX(0,1-Z59^2)) -> 0.99679486 | AB59: =IF(ISNUMBER($B$17),IF(AND($C$17=1,Z59<=-COS(PI()*$B$17)),AA59,NA()),NA()) -> #N/A | AC59: =IF(ISNUMBER($B$17),IF(AND($C$17=2,Z59<=-COS(PI()*$B$17)),AA59,NA()),NA()) -> #N/A | AD59: =IF(ISNUMBER($B$17),IF(AND($C$17=3,Z59<=-COS(PI()*$B$17)),AA59,NA()),NA()) -> #N/A | AE59: =IF(ISNUMBER($B$17),IF(AND($C$17=4,Z59<=-COS(PI()*$B$17)),AA59,NA()),NA()) -> #N/A | AF59: =IF(ISNUMBER($B$17),IF(AND($C$17=5,Z59<=-COS(PI()*$B$17)),AA59,NA()),NA()) -> #N/A | AG59: =IF(ISNUMBER($B$17),IF(AND(ISNUMBER($B$17),Z59>=MIN(0,$Z$2),Z59<=MAX(0,$Z$2)),IF($Z$2=0,0,Z59/$Z$2*$AA$2),NA()),NA()) -> #N/A | AH59: 0.08 | AI59: =SQRT(MAX(0,1-AH59^2)) -> 0.99679486 | AJ59: =IF(ISNUMBER($B$18),IF(AND($C$18=1,AH59<=-COS(PI()*$B$18)),AI59,NA()),NA()) -> #N/A | AK59: =IF(ISNUMBER($B$18),IF(AND($C$18=2,AH59<=-COS(PI()*$B$18)),AI59,NA()),NA()) -> #N/A | AL59: =IF(ISNUMBER($B$18),IF(AND($C$18=3,AH59<=-COS(PI()*$B$18)),AI59,NA()),NA()) -> #N/A | AM59: =IF(ISNUMBER($B$18),IF(AND($C$18=4,AH59<=-COS(PI()*$B$18)),AI59,NA()),NA()) -> #N/A | AN59: =IF(ISNUMBER($B$18),IF(AND($C$18=5,AH59<=-COS(PI()*$B$18)),AI59,NA()),NA()) -> #N/A | AO59: =IF(ISNUMBER($B$18),IF(AND(ISNUMBER($B$18),AH59>=MIN(0,$AH$2),AH59<=MAX(0,$AH$2)),IF($AH$2=0,0,AH59/$AH$2*$AI$2),NA()),NA()) -> #N/A
R60: 0.1 | S60: =SQRT(MAX(0,1-R60^2)) -> 0.99498744 | T60: =IF(ISNUMBER($B$16),IF(AND($C$16=1,R60<=-COS(PI()*$B$16)),S60,NA()),NA()) -> #N/A | U60: =IF(ISNUMBER($B$16),IF(AND($C$16=2,R60<=-COS(PI()*$B$16)),S60,NA()),NA()) -> #N/A | V60: =IF(ISNUMBER($B$16),IF(AND($C$16=3,R60<=-COS(PI()*$B$16)),S60,NA()),NA()) -> #N/A | W60: =IF(ISNUMBER($B$16),IF(AND($C$16=4,R60<=-COS(PI()*$B$16)),S60,NA()),NA()) -> #N/A | X60: =IF(ISNUMBER($B$16),IF(AND($C$16=5,R60<=-COS(PI()*$B$16)),S60,NA()),NA()) -> #N/A | Y60: =IF(ISNUMBER($B$16),IF(AND(ISNUMBER($B$16),R60>=MIN(0,$R$2),R60<=MAX(0,$R$2)),IF($R$2=0,0,R60/$R$2*$S$2),NA()),NA()) -> #N/A | Z60: 0.1 | AA60: =SQRT(MAX(0,1-Z60^2)) -> 0.99498744 | AB60: =IF(ISNUMBER($B$17),IF(AND($C$17=1,Z60<=-COS(PI()*$B$17)),AA60,NA()),NA()) -> #N/A | AC60: =IF(ISNUMBER($B$17),IF(AND($C$17=2,Z60<=-COS(PI()*$B$17)),AA60,NA()),NA()) -> #N/A | AD60: =IF(ISNUMBER($B$17),IF(AND($C$17=3,Z60<=-COS(PI()*$B$17)),AA60,NA()),NA()) -> #N/A | AE60: =IF(ISNUMBER($B$17),IF(AND($C$17=4,Z60<=-COS(PI()*$B$17)),AA60,NA()),NA()) -> #N/A | AF60: =IF(ISNUMBER($B$17),IF(AND($C$17=5,Z60<=-COS(PI()*$B$17)),AA60,NA()),NA()) -> #N/A | AG60: =IF(ISNUMBER($B$17),IF(AND(ISNUMBER($B$17),Z60>=MIN(0,$Z$2),Z60<=MAX(0,$Z$2)),IF($Z$2=0,0,Z60/$Z$2*$AA$2),NA()),NA()) -> #N/A | AH60: 0.1 | AI60: =SQRT(MAX(0,1-AH60^2)) -> 0.99498744 | AJ60: =IF(ISNUMBER($B$18),IF(AND($C$18=1,AH60<=-COS(PI()*$B$18)),AI60,NA()),NA()) -> #N/A | AK60: =IF(ISNUMBER($B$18),IF(AND($C$18=2,AH60<=-COS(PI()*$B$18)),AI60,NA()),NA()) -> #N/A | AL60: =IF(ISNUMBER($B$18),IF(AND($C$18=3,AH60<=-COS(PI()*$B$18)),AI60,NA()),NA()) -> #N/A | AM60: =IF(ISNUMBER($B$18),IF(AND($C$18=4,AH60<=-COS(PI()*$B$18)),AI60,NA()),NA()) -> #N/A | AN60: =IF(ISNUMBER($B$18),IF(AND($C$18=5,AH60<=-COS(PI()*$B$18)),AI60,NA()),NA()) -> #N/A | AO60: =IF(ISNUMBER($B$18),IF(AND(ISNUMBER($B$18),AH60>=MIN(0,$AH$2),AH60<=MAX(0,$AH$2)),IF($AH$2=0,0,AH60/$AH$2*$AI$2),NA()),NA()) -> #N/A
R61: 0.12 | S61: =SQRT(MAX(0,1-R61^2)) -> 0.99277389 | T61: =IF(ISNUMBER($B$16),IF(AND($C$16=1,R61<=-COS(PI()*$B$16)),S61,NA()),NA()) -> #N/A | U61: =IF(ISNUMBER($B$16),IF(AND($C$16=2,R61<=-COS(PI()*$B$16)),S61,NA()),NA()) -> #N/A | V61: =IF(ISNUMBER($B$16),IF(AND($C$16=3,R61<=-COS(PI()*$B$16)),S61,NA()),NA()) -> #N/A | W61: =IF(ISNUMBER($B$16),IF(AND($C$16=4,R61<=-COS(PI()*$B$16)),S61,NA()),NA()) -> #N/A | X61: =IF(ISNUMBER($B$16),IF(AND($C$16=5,R61<=-COS(PI()*$B$16)),S61,NA()),NA()) -> #N/A | Y61: =IF(ISNUMBER($B$16),IF(AND(ISNUMBER($B$16),R61>=MIN(0,$R$2),R61<=MAX(0,$R$2)),IF($R$2=0,0,R61/$R$2*$S$2),NA()),NA()) -> #N/A | Z61: 0.12 | AA61: =SQRT(MAX(0,1-Z61^2)) -> 0.99277389 | AB61: =IF(ISNUMBER($B$17),IF(AND($C$17=1,Z61<=-COS(PI()*$B$17)),AA61,NA()),NA()) -> #N/A | AC61: =IF(ISNUMBER($B$17),IF(AND($C$17=2,Z61<=-COS(PI()*$B$17)),AA61,NA()),NA()) -> #N/A | AD61: =IF(ISNUMBER($B$17),IF(AND($C$17=3,Z61<=-COS(PI()*$B$17)),AA61,NA()),NA()) -> #N/A | AE61: =IF(ISNUMBER($B$17),IF(AND($C$17=4,Z61<=-COS(PI()*$B$17)),AA61,NA()),NA()) -> #N/A | AF61: =IF(ISNUMBER($B$17),IF(AND($C$17=5,Z61<=-COS(PI()*$B$17)),AA61,NA()),NA()) -> #N/A | AG61: =IF(ISNUMBER($B$17),IF(AND(ISNUMBER($B$17),Z61>=MIN(0,$Z$2),Z61<=MAX(0,$Z$2)),IF($Z$2=0,0,Z61/$Z$2*$AA$2),NA()),NA()) -> #N/A | AH61: 0.12 | AI61: =SQRT(MAX(0,1-AH61^2)) -> 0.99277389 | AJ61: =IF(ISNUMBER($B$18),IF(AND($C$18=1,AH61<=-COS(PI()*$B$18)),AI61,NA()),NA()) -> #N/A | AK61: =IF(ISNUMBER($B$18),IF(AND($C$18=2,AH61<=-COS(PI()*$B$18)),AI61,NA()),NA()) -> #N/A | AL61: =IF(ISNUMBER($B$18),IF(AND($C$18=3,AH61<=-COS(PI()*$B$18)),AI61,NA()),NA()) -> #N/A | AM61: =IF(ISNUMBER($B$18),IF(AND($C$18=4,AH61<=-COS(PI()*$B$18)),AI61,NA()),NA()) -> #N/A | AN61: =IF(ISNUMBER($B$18),IF(AND($C$18=5,AH61<=-COS(PI()*$B$18)),AI61,NA()),NA()) -> #N/A | AO61: =IF(ISNUMBER($B$18),IF(AND(ISNUMBER($B$18),AH61>=MIN(0,$AH$2),AH61<=MAX(0,$AH$2)),IF($AH$2=0,0,AH61/$AH$2*$AI$2),NA()),NA()) -> #N/A
R62: 0.14 | S62: =SQRT(MAX(0,1-R62^2)) -> 0.9901515 | T62: =IF(ISNUMBER($B$16),IF(AND($C$16=1,R62<=-COS(PI()*$B$16)),S62,NA()),NA()) -> #N/A | U62: =IF(ISNUMBER($B$16),IF(AND($C$16=2,R62<=-COS(PI()*$B$16)),S62,NA()),NA()) -> #N/A | V62: =IF(ISNUMBER($B$16),IF(AND($C$16=3,R62<=-COS(PI()*$B$16)),S62,NA()),NA()) -> #N/A | W62: =IF(ISNUMBER($B$16),IF(AND($C$16=4,R62<=-COS(PI()*$B$16)),S62,NA()),NA()) -> #N/A | X62: =IF(ISNUMBER($B$16),IF(AND($C$16=5,R62<=-COS(PI()*$B$16)),S62,NA()),NA()) -> #N/A | Y62: =IF(ISNUMBER($B$16),IF(AND(ISNUMBER($B$16),R62>=MIN(0,$R$2),R62<=MAX(0,$R$2)),IF($R$2=0,0,R62/$R$2*$S$2),NA()),NA()) -> #N/A | Z62: 0.14 | AA62: =SQRT(MAX(0,1-Z62^2)) -> 0.9901515 | AB62: =IF(ISNUMBER($B$17),IF(AND($C$17=1,Z62<=-COS(PI()*$B$17)),AA62,NA()),NA()) -> #N/A | AC62: =IF(ISNUMBER($B$17),IF(AND($C$17=2,Z62<=-COS(PI()*$B$17)),AA62,NA()),NA()) -> #N/A | AD62: =IF(ISNUMBER($B$17),IF(AND($C$17=3,Z62<=-COS(PI()*$B$17)),AA62,NA()),NA()) -> #N/A | AE62: =IF(ISNUMBER($B$17),IF(AND($C$17=4,Z62<=-COS(PI()*$B$17)),AA62,NA()),NA()) -> #N/A | AF62: =IF(ISNUMBER($B$17),IF(AND($C$17=5,Z62<=-COS(PI()*$B$17)),AA62,NA()),NA()) -> #N/A | AG62: =IF(ISNUMBER($B$17),IF(AND(ISNUMBER($B$17),Z62>=MIN(0,$Z$2),Z62<=MAX(0,$Z$2)),IF($Z$2=0,0,Z62/$Z$2*$AA$2),NA()),NA()) -> #N/A | AH62: 0.14 | AI62: =SQRT(MAX(0,1-AH62^2)) -> 0.9901515 | AJ62: =IF(ISNUMBER($B$18),IF(AND($C$18=1,AH62<=-COS(PI()*$B$18)),AI62,NA()),NA()) -> #N/A | AK62: =IF(ISNUMBER($B$18),IF(AND($C$18=2,AH62<=-COS(PI()*$B$18)),AI62,NA()),NA()) -> #N/A | AL62: =IF(ISNUMBER($B$18),IF(AND($C$18=3,AH62<=-COS(PI()*$B$18)),AI62,NA()),NA()) -> #N/A | AM62: =IF(ISNUMBER($B$18),IF(AND($C$18=4,AH62<=-COS(PI()*$B$18)),AI62,NA()),NA()) -> #N/A | AN62: =IF(ISNUMBER($B$18),IF(AND($C$18=5,AH62<=-COS(PI()*$B$18)),AI62,NA()),NA()) -> #N/A | AO62: =IF(ISNUMBER($B$18),IF(AND(ISNUMBER($B$18),AH62>=MIN(0,$AH$2),AH62<=MAX(0,$AH$2)),IF($AH$2=0,0,AH62/$AH$2*$AI$2),NA()),NA()) -> #N/A
